Workbook

Sheet Start Here
A1: START HERE
A2: Built for Derek Smith, September 2026. Read this page once, then live on 'Dashboard' and 'Deal Log'.
A4: COLOUR CODE — the same convention professional financial models use
B5: BLUE text | C5: A hardcoded input. This is yours to change.
B6: YELLOW fill | C6: An assumption you MUST confirm. Either you did not give me the number, or it changes the answer materially.
B7: BLACK text | C7: A formula. Do not type over it.
B8: GREEN text | C8: A link pulling from another sheet.
B9: GREEN fill | C9: A key output.
B10: RED fill | C10: A warning or a number you should not like.
A12: HOW TO USE IT
B13: Once, this week | C13: Go through 'Inputs' top to bottom and fix every YELLOW cell. Until then, treat the outputs as directional, not precise.
B14: Every deal | C14: Add one row to 'Deal Log'. Date, client, loan amount, the company's bps, status. Your commission calculates itself. DELETE THE THREE EXAMPLE ROWS FIRST.
B15: Every commission check | C15: Open 'Allocation Engine', type the gross amount into the blue cell, and follow the waterfall it gives you.
B16: Every month | C16: Update 'Marketing ROI' with spend, leads and closings. Glance at 'Dashboard'.
B17: Every quarter | C17: Re-read 'Goals'. If the GAP row is negative, something has to give - a date, a target, or your closing volume.
B18: The two toggles that change everything | C18: On 'Inputs': 'Is the draw RECOVERABLE?' and 'Tax status'. Flip them and watch the whole workbook move. That is the point of the model.
A20: WHAT I ASSUMED (because it was not in your notes)
B21: Assumption 1 | C21: Auto insurance $165/mo, phone $60/mo, groceries/dining $400/mo, personal $250/mo, car maintenance $90/mo - all placeholders, all yellow on 'Inputs'.
B22: Assumption 2 | C22: Auto loan APR 7.49% - you gave the balance and payment but not the rate. The payoff schedule depends on it.
B23: Assumption 3 | C23: HYSA rate 4.00% and credit limit $5,000 - both unknown, both material (one decides the certificate question, the other your utilization).
B24: Assumption 4 | C24: Health insurance $0 - assumed you are on a parent's plan. You age off at 26, which is roughly a year away. Budget $350-500/mo from then.
B25: Assumption 5 | C25: Gym treated as 24 charges/year (mid-month + month-end), matching how you described it.
B26: Assumption 6 | C26: Ring budget $12,000 and target home price $400,000 - pure placeholders.
B27: Assumption 7 | C27: Federal 12% / Maine 5.5% effective rates - rough. A CPA should confirm before you rely on the quarterly numbers.
B29: Not advice | C29: This is a planning model built from the figures you gave me, not tax, legal or investment advice. Confirm your comp structure with the owner, your tax status with a CPA, and current loan-program guidelines before acting on the housing section.

Sheet Dashboard
A1: COMMAND CENTER — Derek Smith | Baxter Mortgage | NMLS 2810853
A2: ="Model date: "&TEXT(Inputs!C7,"mmmm d, yyyy")&" | Comp structure: "&IF(Inputs!C17="Yes","RECOVERABLE draw","NON-RECOVERABLE draw ("&Inputs!C18&")")&" | Tax status: "&Inputs!C20&" | Scenario: "&Inputs!C98
B4: THE FIVE NUMBERS THAT MATTER
B5: Cash in checking today | C5: =Inputs!C51 | E5: Monthly cash burn | F5: ='Monthly Budget'!C32 | H5: Emergency fund target | I5: =Accounts!$C$5
B6: Bills due in the next 7 days | C6: =Inputs!C65+Inputs!C28 | E6: Draw income / month | F6: =Inputs!C23 | H6: Months of runway you have now | I6: =IFERROR((Inputs!C53+Inputs!C51)/'Monthly Budget'!C32,0)
B7: Total saved & invested | C7: =Accounts!AC9 | E7: Gap the draw does NOT cover | F7: ='Monthly Budget'!C34 | H7: Roth at 65 if you start now | I7: =Retirement!G6
B8: Net worth (liquid, less car) | C8: =Accounts!AE9 | E8: Loans/mo to break even | F8: ='Monthly Budget'!C37 | H8: Max home price (draw only) | I8: ='Home Purchase'!D28
B9: Advance balance owed | C9: ='Cash Flow'!$E$4 | E9: Loans/mo to bank $3,000 | F9: =Break-Even!E28 | H9: Annual tax to reserve | I9: ='Tax Reserve'!C18
B11: TOP PRIORITIES RIGHT NOW
B12: 1. Get the comp agreement in writing: recoverable or not, W-2 or 1099. Everything downstream depends on those two answers.
B13: 2. Build the checking cushion to $2,000 before funding anything else. You are at $395.40 with $865.84 due inside a week.
B14: 3. Open the Roth IRA and the separate ring/travel savings account. Both are $0 today because neither exists yet.
B15: 4. Start a mileage log today. At 12,000 miles a year it is worth roughly $8,400 in deductions if you are 1099 - far more than the fuel costs you.
B16: 5. Check your HYSA rate against the certificate's 3.687%. If savings pays more, stop the auto-roll.

Sheet Inputs
A1: CONTROL PANEL — every number in this workbook traces back to this sheet
A2: Edit BLUE cells only. YELLOW = you must confirm this number. Everything else is a formula.
A4: 1. WHO / WHEN (the clock the whole model runs on)
B5: Name | C5: Derek Smith
B6: Current age | C6: 25 | D6: years
B7: MODEL DATE ("today" for every calculation) | C7: 46275 | D7: date | E7: Hardcoded on purpose so results are reproducible. Change it when you refresh the model.
B8: Date you started at Baxter | C8: 46112 | D8: date
B9: Date of your FIRST draw | C9: 46112 | D9: date | E9: Per Derek: first draw landed 3/31/26, the day you started.
B10: Draws received to date | C10: 11 | D10: checks | E10: Confirmed against your 11 actual pay dates (3/31 through 8/28). Next draw: 9/15/26.
A11: 2. COMPENSATION (the two structures you asked me to model)
B12: Draw per pay period | C12: 1231.58 | D12: $ | E12: Your bi-weekly draw.
B13: Draw pay day #1 of each month | C13: 15 | D13: day of mo | E13: Draw #1 is the 15th. Draw #2 is the LAST DAY of the month (handled automatically). Verified against your actual dates: 3/31, 4/15, 4/30, 5/15, 5/29, 6/15, 6/30, 7/16, 7/30, 8/14, 8/28.
B14: Shift a weekend payday back to Friday? | C14: Yes | D14: Yes/No | E14: Your 5/29 and 8/14 draws both moved off a weekend. Payroll also drifts a day either way now and then (7/16, 7/30) - noise, not a rule, so your 11 past dates are entered as actuals in column R of 'Draw Recovery'.
B15: YOUR commission | C15: 0.0075 | D15: of loan amt | E15: 75 bps. Fixed to you regardless of what the company charges.
B16: Company standard fee | C16: 0.0275 | D16: of loan amt | E16: 275 bps standard; drops to 200 or 150 to win a deal. Your 75 bps does not change.
B17: Is the draw RECOVERABLE? | C17: Yes | D17: Yes/No | E17: *** CONFIRM IN WRITING WITH THE OWNER. *** Recoverable = an advance you repay out of commissions. Non-recoverable = yours to keep. This single word is worth $13,547 today.
B18: How commission pays alongside the draw | C18: Recapture | D18: mode | E18: Recapture = commission first repays the draw balance (normal for recoverable). GreaterOf = you get the larger of draw or commission (normal for non-recoverable). Stacked = draw + full commission.
B19: How marketing is funded | C19: Self-funded | D19: mode | E19: Self-funded = out of your pocket. Recoverable = owner advances it, you repay from commissions. CompanyPaid = owner eats it (non-recoverable).
B20: Tax status | C20: 1099 | D20: W-2 / 1099 | E20: *** CONFIRM. *** 1099 = you owe ~30% and every mile/marketing dollar is deductible. W-2 = taxes withheld, almost nothing deductible. Worth thousands either way.
B21: Draws per year | C21: 24 | D21: checks/yr | E21: *** CORRECTED - A REAL FINDING. *** 24 draws/yr, not 26. Your own dates prove it: 3/31, 4/15, 4/30, 5/15, 5/29, 6/15, 6/30, 7/16, 7/30, 8/14, 8/28 = mid-month + month-end = SEMI-MONTHLY. True bi-weekly would have paid 12 checks by today, not 11. Annualized: $29,557.92, NOT $32,021.08. Budgeting on 26 checks overstates your floor by $2,463.16/yr.
B22: Annualized draw (the floor) | C22: =C12*C21 | D22: $/yr
B23: Draw per month (average) | C23: =C22/12 | D23: $/mo | E23: Average. Actual months vary: two months a year carry three checks.
B24: Draw dollars received to date | C24: =C12*C10 | D24: $ | E24: This is the number at risk if the draw is recoverable.
B25: Draws SCHEDULED by the model date | C25: =COUNTIFS('Draw Recovery'!$B$9:$B$116,"<="&C7) | D25: checks | E25: Counted straight off the pay calendar on 'Draw Recovery'.
B26: = Variance vs. your count | C26: =C25-C10 | D26: checks | E26: Reconciles to zero against the 11 actual dates in column R of 'Draw Recovery'. Next draw: 9/15/26.
A27: 3. FIXED MONTHLY OBLIGATIONS (contractual - these hit whether you close a loan or not)
B28: Car payment | C28: 475.69 | D28: $/mo
B29: ...due on day of month | C29: 14 | D29: day
B30: Gym membership (per charge) | C30: 31.99 | D30: $/charge
B31: ...charges per month | C31: 2 | D31: x/mo | E31: Semi-monthly (mid-month + last day) = 24 charges/yr = $767.76. Same cadence as your draw - you use 'bi-weekly' to mean twice a month, which is how this model reads it throughout.
B32: Amazon Prime | C32: 15 | D32: $/mo
B33: ...due on day of month | C33: 1 | D33: day
B34: Marketing spend | C34: 1000 | D34: $/mo | E34: Your target. Tracked against closed loans on 'Marketing ROI'.
B35: Auto insurance | C35: 165 | D35: $/mo | E35: YOU DID NOT LIST THIS. Your lender requires full coverage on a $25k loan, so it exists. Maine average for a 25-yr-old male, full coverage. Replace with your actual premium.
B36: Phone | C36: 60 | D36: $/mo | E36: NOT LISTED. Placeholder - replace with actual (or $0 if on a family plan).
B37: Health insurance | C37: 0 | D37: $/mo | E37: NOT LISTED. $0 only if you are on a parent's plan - you can stay until age 26, which for you ends within ~1 year. Budget $350-500/mo starting then. THIS IS A CLIFF.
B38: Other fixed (subscriptions, etc.) | C38: 0 | D38: $/mo
A39: 4. VARIABLE / DRIVER-BASED SPENDING
B40: Business + personal miles driven | C40: 1000 | D40: mi/mo | E40: Your estimate. Also drives your mileage tax deduction - log them.
B41: Gas price | C41: 4.1 | D41: $/gal
B42: Vehicle MPG | C42: 19 | D42: mpg | E42: Midpoint of the 18-20 you gave. Sensitivity for 18 and 20 is on 'Sensitivity'.
B43: = Fuel cost | C43: =C40/C42*C41 | D43: $/mo
B44: Aroma Joe's per visit | C44: 6 | D44: $/visit
B45: ...visits per week | C45: 4 | D45: x/wk | E45: Set your real number. Each daily visit (7/wk) costs $2,190/yr.
B46: = Coffee cost | C46: =C44*C45*52/12 | D46: $/mo
B47: Groceries / eating out | C47: 400 | D47: $/mo | E47: NOT LISTED. You live at home so groceries may be covered - but client lunches and road food are real. Set your number.
B48: Personal / entertainment / clothes | C48: 250 | D48: $/mo | E48: NOT LISTED. Placeholder.
B49: Car maintenance + tires reserve | C49: 90 | D49: $/mo | E49: NOT LISTED. 12,000 mi/yr of Maine driving = tires, brakes, oil, and winter tires. Set aside monthly so it is never a surprise.
A50: 5. ACCOUNTS (opening balances at the model date)
B51: Checking | C51: 395.4 | D51: $
B52: ...minimum cushion to keep in checking | C52: 2000 | D52: $ | E52: RECOMMENDATION: one month of fixed bills. You are at $395 with $866 of bills due in the next 7 days. This is the single most urgent fix in the model.
B53: High-yield savings | C53: 8398.9 | D53: $
B54: ...HYSA rate (APY) | C54: 0.04 | D54: APY | E54: CONFIRM YOUR ACTUAL RATE. If it is above 3.687% your certificate is losing you money - see 'Certificate Ladder'.
B55: Shared certificate | C55: 6522.71 | D55: $
B56: ...certificate rate | C56: 0.03687 | D56: APY
B57: ...next maturity / roll date | C57: 46323 | D57: date
B58: ...term length | C58: 3 | D58: months | E58: Rolls every 3 months.
B59: ...auto-transfer from savings each roll | C59: 1250 | D59: $/roll | E59: =$416.67/mo pulled out of your HYSA automatically. It is a real cash outflow and IS budgeted on 'Cash Flow 24M'.
B60: Special savings (ring / travel) | C60: 0 | D60: $ | E60: Account does not exist yet. Open it - see 'Recommendations'.
B61: Roth IRA | C61: 0 | D61: $ | E61: Account does not exist yet. This is the biggest long-term miss in your setup.
A62: 6. DEBT
B63: Auto loan balance | C63: 25092.02 | D63: $
B64: ...auto loan APR | C64: 0.0749 | D64: APR | E64: NOT PROVIDED. 7.49% is a typical 2025-26 used-car rate. Pull the real rate off your statement - the payoff schedule on 'Car Loan' is only as good as this cell.
B65: Credit card balance now | C65: 390.15 | D65: $
B66: ...statement due day | C66: 7 | D66: day
B67: ...credit limit | C67: 5000 | D67: $ | E67: NOT PROVIDED. Drives your utilization %, which is 30% of your FICO score. Enter the real limit.
B68: ...APR | C68: 0.2699 | D68: APR | E68: Only matters if you ever carry a balance. Don't.
B69: Total open credit lines | C69: 2 | D69: lines | E69: Auto loan + 1 card. Thin. See 'Credit Builder'.
A70: 7. TAXES (only bites if you are 1099 - confirm section 2)
B71: Self-employment tax rate | C71: 0.153 | D71: of 92.35% of net | E71: 12.4% Social Security + 2.9% Medicare. 1099 only.
B72: Federal effective income tax rate | C72: 0.12 | D72: eff. | E72: Estimate for a single filer around $80-110k gross after the standard deduction and QBI. Not marginal - effective. Have a CPA confirm.
B73: Maine effective income tax rate | C73: 0.055 | D73: eff. | E73: Maine brackets run 5.8%/6.75%/7.15%. ~5.5% effective at your income. Confirm with a CPA.
B74: % of every commission to park for taxes | C74: 0.3 | D74: of gross | E74: RECOMMENDATION: 30% off the top of EVERY commission check into a separate account, on the day it lands, before you look at the number. If W-2, set to 0%.
B75: IRS standard mileage rate | C75: 0.7 | D75: $/mi | E75: ~$0.70/mi for 2025; the IRS re-sets it every January - verify the 2026 figure. 1099 only. See 'Tax Reserve' - this deduction is worth more than your actual gas.
A76: 8. GOALS
B77: Emergency fund target | C77: 9 | D77: months | E77: RECOMMENDATION: 9 months, not the usual 3-6. Your income is commission-lumpy AND your draw may be clawable. Two risks stacked.
B78: Ring + proposal budget | C78: 12000 | D78: $ | E78: Placeholder - set your real number. Includes ring, photographer, trip.
B79: Target proposal date | C79: 46997 | D79: date | E79: 'In 2 years' from today.
B80: Annual travel budget | C80: 3000 | D80: $/yr
B81: Target home purchase price | C81: 400000 | D81: $ | E81: Near the Maine median. Adjust for your market.
B82: ...down payment | C82: 0.05 | D82: % | E82: 5% conventional. FHA 3.5% and 0% VA/USDA modeled on 'Home Purchase'.
B83: ...closing costs + prepaids | C83: 0.03 | D83: % of price
B84: Target home purchase date | C84: 47178 | D84: date | E84: NOT 2 years. See 'Home Purchase': lenders need a 2-year history of variable income, which for you starts ~Mar 2028. Buying and proposing in the same 12 months is the core conflict in this plan.
A85: 9. SURPLUS ALLOCATION (how every leftover dollar gets split - must total 100%)
B86: -> Emergency fund (HYSA) | C86: 0.3 | D86: %
B87: -> Roth IRA | C87: 0.15 | D87: %
B88: -> Ring / special savings | C88: 0.2 | D88: %
B89: -> House down payment | C89: 0.25 | D89: %
B90: -> Extra principal on car | C90: 0.05 | D90: %
B91: -> Guilt-free spending | C91: 0.05 | D91: %
B92: TOTAL (must equal 100%) | C92: =SUM(C86:C91) | D92: % | E92: If this is not 100.0% the Allocation Engine is wrong. The waterfall on 'Allocation Engine' overrides these percentages until the emergency fund is full.
A93: 10. FORECAST ASSUMPTIONS (drives the 24-month projection)
B94: Average loan size | C94: 300000 | D94: $ | E94: Set from your actual pipeline. At 75 bps a $300k loan pays you $2,250.
B95: Loans closed / month - BASE case | C95: 2 | D95: loans/mo
B96: Loans closed / month - SLOW case | C96: 0.8 | D96: loans/mo
B97: Loans closed / month - STRONG case | C97: 4 | D97: loans/mo
B98: ACTIVE SCENARIO for the 24-month forecast | C98: Base | D98: case | E98: Switch this one cell and the entire workbook re-forecasts.
B99: = Active units/month | C99: =IF(C98="Slow",C96,IF(C98="Strong",C97,C95)) | D99: loans/mo
B100: = Active monthly volume | C100: =C99*C94 | D100: $/mo
B101: = Active monthly commission | C101: =C100*C15 | D101: $/mo

Sheet Deal Log
A1: DEAL LOG — log every transaction here. This sheet feeds the entire workbook.
A2: Enter columns A-F, I, J, M, N (blue). Green columns calculate themselves. Your 75 bps is paid on the loan amount regardless of the company's fee.
A3: TOTALS (Funded only): | B3: Funded count -> | C3: =COUNTIFS($I$8:$I$257,"Funded") | D3: =SUMIFS(D8:D257,$I$8:$I$257,"Funded") | G3: =SUMIFS(G8:G257,$I$8:$I$257,"Funded") | H3: =SUMIFS(H8:H257,$I$8:$I$257,"Funded") | J3: Weighted pipeline -> | K3: =SUMIFS(K8:K257,$I$8:$I$257,"Funded")+SUMIFS(K8:K257,$I$8:$I$257,"Locked")+SUMIFS(K8:K257,$I$8:$I$257,"Pre-App")
A5: !! ROWS 8-10 ARE EXAMPLES so you can see the model working end-to-end. DELETE THEM before you trust a single number. !!
A6: Examples still in the file: | D6: =COUNTIFS($C$8:$C$257,"EXAMPLE*")
A7: Date Funded | B7: Client / Deal | C7: Loan Type | D7: Loan Amount | E7: Co. bps | F7: My bps | G7: MY COMMISSION | H7: Company Revenue | I7: Status | J7: Prob. % | K7: Weighted to Me | L7: Month Key | M7: Referral Source | N7: Notes
A8: 46164 | B8: Sample - Hartley purchase | C8: EXAMPLE - Conv 30yr | D8: 312000 | E8: 0.0275 | F8: =IF($A8="","",Inputs!$C$15) | G8: =IF($A8="","",$D8*$F8) | H8: =IF($A8="","",$D8*$E8) | I8: Funded | J8: 1 | K8: =IF($A8="","",$G8*$J8) | L8: =IF($A8="","",EOMONTH($A8,0)) | M8: Realtor - J. Poulin | N8: Delete this row
A9: 46213 | B9: Sample - Nadeau refi | C9: EXAMPLE - FHA Streamline | D9: 244500 | E9: 0.02 | F9: =IF($A9="","",Inputs!$C$15) | G9: =IF($A9="","",$D9*$F9) | H9: =IF($A9="","",$D9*$E9) | I9: Funded | J9: 1 | K9: =IF($A9="","",$G9*$J9) | L9: =IF($A9="","",EOMONTH($A9,0)) | M9: Past client | N9: Rate cut to 200 bps to win it - your 75 bps did not change
A10: 46310 | B10: Sample - Belanger purchase | C10: EXAMPLE - MaineHousing FHL | D10: 288000 | E10: 0.015 | F10: =IF($A10="","",Inputs!$C$15) | G10: =IF($A10="","",$D10*$F10) | H10: =IF($A10="","",$D10*$E10) | I10: Locked | J10: 0.85 | K10: =IF($A10="","",$G10*$J10) | L10: =IF($A10="","",EOMONTH($A10,0)) | M10: Realtor - K. Dube | N10: Delete this row
F11: =IF($A11="","",Inputs!$C$15) | G11: =IF($A11="","",$D11*$F11) | H11: =IF($A11="","",$D11*$E11) | K11: =IF($A11="","",$G11*$J11) | L11: =IF($A11="","",EOMONTH($A11,0))
F12: =IF($A12="","",Inputs!$C$15) | G12: =IF($A12="","",$D12*$F12) | H12: =IF($A12="","",$D12*$E12) | K12: =IF($A12="","",$G12*$J12) | L12: =IF($A12="","",EOMONTH($A12,0))
F13: =IF($A13="","",Inputs!$C$15) | G13: =IF($A13="","",$D13*$F13) | H13: =IF($A13="","",$D13*$E13) | K13: =IF($A13="","",$G13*$J13) | L13: =IF($A13="","",EOMONTH($A13,0))
F14: =IF($A14="","",Inputs!$C$15) | G14: =IF($A14="","",$D14*$F14) | H14: =IF($A14="","",$D14*$E14) | K14: =IF($A14="","",$G14*$J14) | L14: =IF($A14="","",EOMONTH($A14,0))
F15: =IF($A15="","",Inputs!$C$15) | G15: =IF($A15="","",$D15*$F15) | H15: =IF($A15="","",$D15*$E15) | K15: =IF($A15="","",$G15*$J15) | L15: =IF($A15="","",EOMONTH($A15,0))
F16: =IF($A16="","",Inputs!$C$15) | G16: =IF($A16="","",$D16*$F16) | H16: =IF($A16="","",$D16*$E16) | K16: =IF($A16="","",$G16*$J16) | L16: =IF($A16="","",EOMONTH($A16,0))
F17: =IF($A17="","",Inputs!$C$15) | G17: =IF($A17="","",$D17*$F17) | H17: =IF($A17="","",$D17*$E17) | K17: =IF($A17="","",$G17*$J17) | L17: =IF($A17="","",EOMONTH($A17,0))
F18: =IF($A18="","",Inputs!$C$15) | G18: =IF($A18="","",$D18*$F18) | H18: =IF($A18="","",$D18*$E18) | K18: =IF($A18="","",$G18*$J18) | L18: =IF($A18="","",EOMONTH($A18,0))
F19: =IF($A19="","",Inputs!$C$15) | G19: =IF($A19="","",$D19*$F19) | H19: =IF($A19="","",$D19*$E19) | K19: =IF($A19="","",$G19*$J19) | L19: =IF($A19="","",EOMONTH($A19,0))
F20: =IF($A20="","",Inputs!$C$15) | G20: =IF($A20="","",$D20*$F20) | H20: =IF($A20="","",$D20*$E20) | K20: =IF($A20="","",$G20*$J20) | L20: =IF($A20="","",EOMONTH($A20,0))
F21: =IF($A21="","",Inputs!$C$15) | G21: =IF($A21="","",$D21*$F21) | H21: =IF($A21="","",$D21*$E21) | K21: =IF($A21="","",$G21*$J21) | L21: =IF($A21="","",EOMONTH($A21,0))
F22: =IF($A22="","",Inputs!$C$15) | G22: =IF($A22="","",$D22*$F22) | H22: =IF($A22="","",$D22*$E22) | K22: =IF($A22="","",$G22*$J22) | L22: =IF($A22="","",EOMONTH($A22,0))
... F257: =IF($A257="","",Inputs!$C$15) | G257: =IF($A257="","",$D257*$F257) | H257: =IF($A257="","",$D257*$E257) | K257: =IF($A257="","",$G257*$J257) | L257: =IF($A257="","",EOMONTH($A257,0))

Sheet Draw Recovery
A1: DRAW RECOVERY ENGINE — what you actually take home under each comp structure
A2: Every SEMI-MONTHLY pay period (15th + month-end) from your first draw forward. Column R holds your 11 real dates; clear one and the formula takes over. The three NET CASH columns (M, N, O) are the whole point: same deals, three very different outcomes.
A4: Advance balance owed TODAY (recoverable case): | F4: =INDEX($L$9:$L$116,MATCH(Inputs!$C$7,$B$9:$B$116,1)) | G4: <- if the draw is recoverable, this is what you owe the owner before you earn a dollar of your own.
A5: Month you break even (advance hits zero): | F5: =IFERROR(INDEX($B$9:$B$116,MATCH(0,$L$9:$L$116,0)),"Not within 3 yrs") | G5: <- drive this earlier by logging more funded deals, or by getting the draw reclassified as non-recoverable.
A8: # | B8: Pay Date | C8: Month | D8: Draw Advanced | E8: Marketing Advanced | F8: Total Advanced | G8: Cumulative Advanced | H8: Commission Earned | I8: Cumulative Commission | J8: Opening Advance Bal | K8: Recapture Applied | L8: Closing Advance Bal | M8: NET CASH Recoverable | N8: NET CASH Greater-Of | O8: NET CASH Stacked | P8: ACTIVE (per toggle) | Q8: Paid? | R8: ACTUAL date (override)
A9: 1 | B9: =IF(R9="",Inputs!$C$9,R9) | C9: =EOMONTH(B9,0) | D9: =Inputs!$C$12 | E9: =IF(Inputs!$C$19="Recoverable",Inputs!$C$34*12/Inputs!$C$21,0) | F9: =D9+E9 | G9: =F9 | H9: =SUMIFS('Deal Log'!$G$8:$G$257,'Deal Log'!$A$8:$A$257,">"&0,'Deal Log'!$A$8:$A$257,"<="&B9,'Deal Log'!$I$8:$I$257,"Funded") | I9: =H9 | J9: =0 | K9: =MIN(J9+F9,H9) | L9: =MAX(0,J9+F9-H9) | M9: =D9+MAX(0,H9-(J9+F9)) | N9: =MAX(D9,H9) | O9: =D9+H9 | P9: =IF(Inputs!$C$17="Yes",M9,IF(Inputs!$C$18="Stacked",O9,N9)) | Q9: =IF(B9<=Inputs!$C$7,"paid","future") | R9: 46112
A10: 2 | B10: =IF(R10="",IF(DAY(B9)<=20,(EOMONTH(B9,0)-IF(Inputs!$C$14="Yes",MAX(0,WEEKDAY(EOMONTH(B9,0),2)-5),0)),(DATE(YEAR(B9),MONTH(B9)+1,Inputs!$C$13)-IF(Inputs!$C$14="Yes",MAX(0,WEEKDAY(DATE(YEAR(B9),MONTH(B9)+1,Inputs!$C$13),2)-5),0))),R10) | C10: =EOMONTH(B10,0) | D10: =Inputs!$C$12 | E10: =IF(Inputs!$C$19="Recoverable",Inputs!$C$34*12/Inputs!$C$21,0) | F10: =D10+E10 | G10: =G9+F10 | H10: =SUMIFS('Deal Log'!$G$8:$G$257,'Deal Log'!$A$8:$A$257,">"&B9,'Deal Log'!$A$8:$A$257,"<="&B10,'Deal Log'!$I$8:$I$257,"Funded") | I10: =I9+H10 | J10: =L9 | K10: =MIN(J10+F10,H10) | L10: =MAX(0,J10+F10-H10) | M10: =D10+MAX(0,H10-(J10+F10)) | N10: =MAX(D10,H10) | O10: =D10+H10 | P10: =IF(Inputs!$C$17="Yes",M10,IF(Inputs!$C$18="Stacked",O10,N10)) | Q10: =IF(B10<=Inputs!$C$7,"paid","future") | R10: 46127
A11: 3 | B11: =IF(R11="",IF(DAY(B10)<=20,(EOMONTH(B10,0)-IF(Inputs!$C$14="Yes",MAX(0,WEEKDAY(EOMONTH(B10,0),2)-5),0)),(DATE(YEAR(B10),MONTH(B10)+1,Inputs!$C$13)-IF(Inputs!$C$14="Yes",MAX(0,WEEKDAY(DATE(YEAR(B10),MONTH(B10)+1,Inputs!$C$13),2)-5),0))),R11) | C11: =EOMONTH(B11,0) | D11: =Inputs!$C$12 | E11: =IF(Inputs!$C$19="Recoverable",Inputs!$C$34*12/Inputs!$C$21,0) | F11: =D11+E11 | G11: =G10+F11 | H11: =SUMIFS('Deal Log'!$G$8:$G$257,'Deal Log'!$A$8:$A$257,">"&B10,'Deal Log'!$A$8:$A$257,"<="&B11,'Deal Log'!$I$8:$I$257,"Funded") | I11: =I10+H11 | J11: =L10 | K11: =MIN(J11+F11,H11) | L11: =MAX(0,J11+F11-H11) | M11: =D11+MAX(0,H11-(J11+F11)) | N11: =MAX(D11,H11) | O11: =D11+H11 | P11: =IF(Inputs!$C$17="Yes",M11,IF(Inputs!$C$18="Stacked",O11,N11)) | Q11: =IF(B11<=Inputs!$C$7,"paid","future") | R11: 46142
A12: 4 | B12: =IF(R12="",IF(DAY(B11)<=20,(EOMONTH(B11,0)-IF(Inputs!$C$14="Yes",MAX(0,WEEKDAY(EOMONTH(B11,0),2)-5),0)),(DATE(YEAR(B11),MONTH(B11)+1,Inputs!$C$13)-IF(Inputs!$C$14="Yes",MAX(0,WEEKDAY(DATE(YEAR(B11),MONTH(B11)+1,Inputs!$C$13),2)-5),0))),R12) | C12: =EOMONTH(B12,0) | D12: =Inputs!$C$12 | E12: =IF(Inputs!$C$19="Recoverable",Inputs!$C$34*12/Inputs!$C$21,0) | F12: =D12+E12 | G12: =G11+F12 | H12: =SUMIFS('Deal Log'!$G$8:$G$257,'Deal Log'!$A$8:$A$257,">"&B11,'Deal Log'!$A$8:$A$257,"<="&B12,'Deal Log'!$I$8:$I$257,"Funded") | I12: =I11+H12 | J12: =L11 | K12: =MIN(J12+F12,H12) | L12: =MAX(0,J12+F12-H12) | M12: =D12+MAX(0,H12-(J12+F12)) | N12: =MAX(D12,H12) | O12: =D12+H12 | P12: =IF(Inputs!$C$17="Yes",M12,IF(Inputs!$C$18="Stacked",O12,N12)) | Q12: =IF(B12<=Inputs!$C$7,"paid","future") | R12: 46157
A13: 5 | B13: =IF(R13="",IF(DAY(B12)<=20,(EOMONTH(B12,0)-IF(Inputs!$C$14="Yes",MAX(0,WEEKDAY(EOMONTH(B12,0),2)-5),0)),(DATE(YEAR(B12),MONTH(B12)+1,Inputs!$C$13)-IF(Inputs!$C$14="Yes",MAX(0,WEEKDAY(DATE(YEAR(B12),MONTH(B12)+1,Inputs!$C$13),2)-5),0))),R13) | C13: =EOMONTH(B13,0) | D13: =Inputs!$C$12 | E13: =IF(Inputs!$C$19="Recoverable",Inputs!$C$34*12/Inputs!$C$21,0) | F13: =D13+E13 | G13: =G12+F13 | H13: =SUMIFS('Deal Log'!$G$8:$G$257,'Deal Log'!$A$8:$A$257,">"&B12,'Deal Log'!$A$8:$A$257,"<="&B13,'Deal Log'!$I$8:$I$257,"Funded") | I13: =I12+H13 | J13: =L12 | K13: =MIN(J13+F13,H13) | L13: =MAX(0,J13+F13-H13) | M13: =D13+MAX(0,H13-(J13+F13)) | N13: =MAX(D13,H13) | O13: =D13+H13 | P13: =IF(Inputs!$C$17="Yes",M13,IF(Inputs!$C$18="Stacked",O13,N13)) | Q13: =IF(B13<=Inputs!$C$7,"paid","future") | R13: 46171
A14: 6 | B14: =IF(R14="",IF(DAY(B13)<=20,(EOMONTH(B13,0)-IF(Inputs!$C$14="Yes",MAX(0,WEEKDAY(EOMONTH(B13,0),2)-5),0)),(DATE(YEAR(B13),MONTH(B13)+1,Inputs!$C$13)-IF(Inputs!$C$14="Yes",MAX(0,WEEKDAY(DATE(YEAR(B13),MONTH(B13)+1,Inputs!$C$13),2)-5),0))),R14) | C14: =EOMONTH(B14,0) | D14: =Inputs!$C$12 | E14: =IF(Inputs!$C$19="Recoverable",Inputs!$C$34*12/Inputs!$C$21,0) | F14: =D14+E14 | G14: =G13+F14 | H14: =SUMIFS('Deal Log'!$G$8:$G$257,'Deal Log'!$A$8:$A$257,">"&B13,'Deal Log'!$A$8:$A$257,"<="&B14,'Deal Log'!$I$8:$I$257,"Funded") | I14: =I13+H14 | J14: =L13 | K14: =MIN(J14+F14,H14) | L14: =MAX(0,J14+F14-H14) | M14: =D14+MAX(0,H14-(J14+F14)) | N14: =MAX(D14,H14) | O14: =D14+H14 | P14: =IF(Inputs!$C$17="Yes",M14,IF(Inputs!$C$18="Stacked",O14,N14)) | Q14: =IF(B14<=Inputs!$C$7,"paid","future") | R14: 46188
A15: 7 | B15: =IF(R15="",IF(DAY(B14)<=20,(EOMONTH(B14,0)-IF(Inputs!$C$14="Yes",MAX(0,WEEKDAY(EOMONTH(B14,0),2)-5),0)),(DATE(YEAR(B14),MONTH(B14)+1,Inputs!$C$13)-IF(Inputs!$C$14="Yes",MAX(0,WEEKDAY(DATE(YEAR(B14),MONTH(B14)+1,Inputs!$C$13),2)-5),0))),R15) | C15: =EOMONTH(B15,0) | D15: =Inputs!$C$12 | E15: =IF(Inputs!$C$19="Recoverable",Inputs!$C$34*12/Inputs!$C$21,0) | F15: =D15+E15 | G15: =G14+F15 | H15: =SUMIFS('Deal Log'!$G$8:$G$257,'Deal Log'!$A$8:$A$257,">"&B14,'Deal Log'!$A$8:$A$257,"<="&B15,'Deal Log'!$I$8:$I$257,"Funded") | I15: =I14+H15 | J15: =L14 | K15: =MIN(J15+F15,H15) | L15: =MAX(0,J15+F15-H15) | M15: =D15+MAX(0,H15-(J15+F15)) | N15: =MAX(D15,H15) | O15: =D15+H15 | P15: =IF(Inputs!$C$17="Yes",M15,IF(Inputs!$C$18="Stacked",O15,N15)) | Q15: =IF(B15<=Inputs!$C$7,"paid","future") | R15: 46203
A16: 8 | B16: =IF(R16="",IF(DAY(B15)<=20,(EOMONTH(B15,0)-IF(Inputs!$C$14="Yes",MAX(0,WEEKDAY(EOMONTH(B15,0),2)-5),0)),(DATE(YEAR(B15),MONTH(B15)+1,Inputs!$C$13)-IF(Inputs!$C$14="Yes",MAX(0,WEEKDAY(DATE(YEAR(B15),MONTH(B15)+1,Inputs!$C$13),2)-5),0))),R16) | C16: =EOMONTH(B16,0) | D16: =Inputs!$C$12 | E16: =IF(Inputs!$C$19="Recoverable",Inputs!$C$34*12/Inputs!$C$21,0) | F16: =D16+E16 | G16: =G15+F16 | H16: =SUMIFS('Deal Log'!$G$8:$G$257,'Deal Log'!$A$8:$A$257,">"&B15,'Deal Log'!$A$8:$A$257,"<="&B16,'Deal Log'!$I$8:$I$257,"Funded") | I16: =I15+H16 | J16: =L15 | K16: =MIN(J16+F16,H16) | L16: =MAX(0,J16+F16-H16) | M16: =D16+MAX(0,H16-(J16+F16)) | N16: =MAX(D16,H16) | O16: =D16+H16 | P16: =IF(Inputs!$C$17="Yes",M16,IF(Inputs!$C$18="Stacked",O16,N16)) | Q16: =IF(B16<=Inputs!$C$7,"paid","future") | R16: 46219
A17: 9 | B17: =IF(R17="",IF(DAY(B16)<=20,(EOMONTH(B16,0)-IF(Inputs!$C$14="Yes",MAX(0,WEEKDAY(EOMONTH(B16,0),2)-5),0)),(DATE(YEAR(B16),MONTH(B16)+1,Inputs!$C$13)-IF(Inputs!$C$14="Yes",MAX(0,WEEKDAY(DATE(YEAR(B16),MONTH(B16)+1,Inputs!$C$13),2)-5),0))),R17) | C17: =EOMONTH(B17,0) | D17: =Inputs!$C$12 | E17: =IF(Inputs!$C$19="Recoverable",Inputs!$C$34*12/Inputs!$C$21,0) | F17: =D17+E17 | G17: =G16+F17 | H17: =SUMIFS('Deal Log'!$G$8:$G$257,'Deal Log'!$A$8:$A$257,">"&B16,'Deal Log'!$A$8:$A$257,"<="&B17,'Deal Log'!$I$8:$I$257,"Funded") | I17: =I16+H17 | J17: =L16 | K17: =MIN(J17+F17,H17) | L17: =MAX(0,J17+F17-H17) | M17: =D17+MAX(0,H17-(J17+F17)) | N17: =MAX(D17,H17) | O17: =D17+H17 | P17: =IF(Inputs!$C$17="Yes",M17,IF(Inputs!$C$18="Stacked",O17,N17)) | Q17: =IF(B17<=Inputs!$C$7,"paid","future") | R17: 46233
A18: 10 | B18: =IF(R18="",IF(DAY(B17)<=20,(EOMONTH(B17,0)-IF(Inputs!$C$14="Yes",MAX(0,WEEKDAY(EOMONTH(B17,0),2)-5),0)),(DATE(YEAR(B17),MONTH(B17)+1,Inputs!$C$13)-IF(Inputs!$C$14="Yes",MAX(0,WEEKDAY(DATE(YEAR(B17),MONTH(B17)+1,Inputs!$C$13),2)-5),0))),R18) | C18: =EOMONTH(B18,0) | D18: =Inputs!$C$12 | E18: =IF(Inputs!$C$19="Recoverable",Inputs!$C$34*12/Inputs!$C$21,0) | F18: =D18+E18 | G18: =G17+F18 | H18: =SUMIFS('Deal Log'!$G$8:$G$257,'Deal Log'!$A$8:$A$257,">"&B17,'Deal Log'!$A$8:$A$257,"<="&B18,'Deal Log'!$I$8:$I$257,"Funded") | I18: =I17+H18 | J18: =L17 | K18: =MIN(J18+F18,H18) | L18: =MAX(0,J18+F18-H18) | M18: =D18+MAX(0,H18-(J18+F18)) | N18: =MAX(D18,H18) | O18: =D18+H18 | P18: =IF(Inputs!$C$17="Yes",M18,IF(Inputs!$C$18="Stacked",O18,N18)) | Q18: =IF(B18<=Inputs!$C$7,"paid","future") | R18: 46248
A19: 11 | B19: =IF(R19="",IF(DAY(B18)<=20,(EOMONTH(B18,0)-IF(Inputs!$C$14="Yes",MAX(0,WEEKDAY(EOMONTH(B18,0),2)-5),0)),(DATE(YEAR(B18),MONTH(B18)+1,Inputs!$C$13)-IF(Inputs!$C$14="Yes",MAX(0,WEEKDAY(DATE(YEAR(B18),MONTH(B18)+1,Inputs!$C$13),2)-5),0))),R19) | C19: =EOMONTH(B19,0) | D19: =Inputs!$C$12 | E19: =IF(Inputs!$C$19="Recoverable",Inputs!$C$34*12/Inputs!$C$21,0) | F19: =D19+E19 | G19: =G18+F19 | H19: =SUMIFS('Deal Log'!$G$8:$G$257,'Deal Log'!$A$8:$A$257,">"&B18,'Deal Log'!$A$8:$A$257,"<="&B19,'Deal Log'!$I$8:$I$257,"Funded") | I19: =I18+H19 | J19: =L18 | K19: =MIN(J19+F19,H19) | L19: =MAX(0,J19+F19-H19) | M19: =D19+MAX(0,H19-(J19+F19)) | N19: =MAX(D19,H19) | O19: =D19+H19 | P19: =IF(Inputs!$C$17="Yes",M19,IF(Inputs!$C$18="Stacked",O19,N19)) | Q19: =IF(B19<=Inputs!$C$7,"paid","future") | R19: 46262
A20: 12 | B20: =IF(R20="",IF(DAY(B19)<=20,(EOMONTH(B19,0)-IF(Inputs!$C$14="Yes",MAX(0,WEEKDAY(EOMONTH(B19,0),2)-5),0)),(DATE(YEAR(B19),MONTH(B19)+1,Inputs!$C$13)-IF(Inputs!$C$14="Yes",MAX(0,WEEKDAY(DATE(YEAR(B19),MONTH(B19)+1,Inputs!$C$13),2)-5),0))),R20) | C20: =EOMONTH(B20,0) | D20: =Inputs!$C$12 | E20: =IF(Inputs!$C$19="Recoverable",Inputs!$C$34*12/Inputs!$C$21,0) | F20: =D20+E20 | G20: =G19+F20 | H20: =SUMIFS('Deal Log'!$G$8:$G$257,'Deal Log'!$A$8:$A$257,">"&B19,'Deal Log'!$A$8:$A$257,"<="&B20,'Deal Log'!$I$8:$I$257,"Funded") | I20: =I19+H20 | J20: =L19 | K20: =MIN(J20+F20,H20) | L20: =MAX(0,J20+F20-H20) | M20: =D20+MAX(0,H20-(J20+F20)) | N20: =MAX(D20,H20) | O20: =D20+H20 | P20: =IF(Inputs!$C$17="Yes",M20,IF(Inputs!$C$18="Stacked",O20,N20)) | Q20: =IF(B20<=Inputs!$C$7,"paid","future")
A21: 13 | B21: =IF(R21="",IF(DAY(B20)<=20,(EOMONTH(B20,0)-IF(Inputs!$C$14="Yes",MAX(0,WEEKDAY(EOMONTH(B20,0),2)-5),0)),(DATE(YEAR(B20),MONTH(B20)+1,Inputs!$C$13)-IF(Inputs!$C$14="Yes",MAX(0,WEEKDAY(DATE(YEAR(B20),MONTH(B20)+1,Inputs!$C$13),2)-5),0))),R21) | C21: =EOMONTH(B21,0) | D21: =Inputs!$C$12 | E21: =IF(Inputs!$C$19="Recoverable",Inputs!$C$34*12/Inputs!$C$21,0) | F21: =D21+E21 | G21: =G20+F21 | H21: =SUMIFS('Deal Log'!$G$8:$G$257,'Deal Log'!$A$8:$A$257,">"&B20,'Deal Log'!$A$8:$A$257,"<="&B21,'Deal Log'!$I$8:$I$257,"Funded") | I21: =I20+H21 | J21: =L20 | K21: =MIN(J21+F21,H21) | L21: =MAX(0,J21+F21-H21) | M21: =D21+MAX(0,H21-(J21+F21)) | N21: =MAX(D21,H21) | O21: =D21+H21 | P21: =IF(Inputs!$C$17="Yes",M21,IF(Inputs!$C$18="Stacked",O21,N21)) | Q21: =IF(B21<=Inputs!$C$7,"paid","future")
A22: 14 | B22: =IF(R22="",IF(DAY(B21)<=20,(EOMONTH(B21,0)-IF(Inputs!$C$14="Yes",MAX(0,WEEKDAY(EOMONTH(B21,0),2)-5),0)),(DATE(YEAR(B21),MONTH(B21)+1,Inputs!$C$13)-IF(Inputs!$C$14="Yes",MAX(0,WEEKDAY(DATE(YEAR(B21),MONTH(B21)+1,Inputs!$C$13),2)-5),0))),R22) | C22: =EOMONTH(B22,0) | D22: =Inputs!$C$12 | E22: =IF(Inputs!$C$19="Recoverable",Inputs!$C$34*12/Inputs!$C$21,0) | F22: =D22+E22 | G22: =G21+F22 | H22: =SUMIFS('Deal Log'!$G$8:$G$257,'Deal Log'!$A$8:$A$257,">"&B21,'Deal Log'!$A$8:$A$257,"<="&B22,'Deal Log'!$I$8:$I$257,"Funded") | I22: =I21+H22 | J22: =L21 | K22: =MIN(J22+F22,H22) | L22: =MAX(0,J22+F22-H22) | M22: =D22+MAX(0,H22-(J22+F22)) | N22: =MAX(D22,H22) | O22: =D22+H22 | P22: =IF(Inputs!$C$17="Yes",M22,IF(Inputs!$C$18="Stacked",O22,N22)) | Q22: =IF(B22<=Inputs!$C$7,"paid","future")
A23: 15 | B23: =IF(R23="",IF(DAY(B22)<=20,(EOMONTH(B22,0)-IF(Inputs!$C$14="Yes",MAX(0,WEEKDAY(EOMONTH(B22,0),2)-5),0)),(DATE(YEAR(B22),MONTH(B22)+1,Inputs!$C$13)-IF(Inputs!$C$14="Yes",MAX(0,WEEKDAY(DATE(YEAR(B22),MONTH(B22)+1,Inputs!$C$13),2)-5),0))),R23) | C23: =EOMONTH(B23,0) | D23: =Inputs!$C$12 | E23: =IF(Inputs!$C$19="Recoverable",Inputs!$C$34*12/Inputs!$C$21,0) | F23: =D23+E23 | G23: =G22+F23 | H23: =SUMIFS('Deal Log'!$G$8:$G$257,'Deal Log'!$A$8:$A$257,">"&B22,'Deal Log'!$A$8:$A$257,"<="&B23,'Deal Log'!$I$8:$I$257,"Funded") | I23: =I22+H23 | J23: =L22 | K23: =MIN(J23+F23,H23) | L23: =MAX(0,J23+F23-H23) | M23: =D23+MAX(0,H23-(J23+F23)) | N23: =MAX(D23,H23) | O23: =D23+H23 | P23: =IF(Inputs!$C$17="Yes",M23,IF(Inputs!$C$18="Stacked",O23,N23)) | Q23: =IF(B23<=Inputs!$C$7,"paid","future")
A24: 16 | B24: =IF(R24="",IF(DAY(B23)<=20,(EOMONTH(B23,0)-IF(Inputs!$C$14="Yes",MAX(0,WEEKDAY(EOMONTH(B23,0),2)-5),0)),(DATE(YEAR(B23),MONTH(B23)+1,Inputs!$C$13)-IF(Inputs!$C$14="Yes",MAX(0,WEEKDAY(DATE(YEAR(B23),MONTH(B23)+1,Inputs!$C$13),2)-5),0))),R24) | C24: =EOMONTH(B24,0) | D24: =Inputs!$C$12 | E24: =IF(Inputs!$C$19="Recoverable",Inputs!$C$34*12/Inputs!$C$21,0) | F24: =D24+E24 | G24: =G23+F24 | H24: =SUMIFS('Deal Log'!$G$8:$G$257,'Deal Log'!$A$8:$A$257,">"&B23,'Deal Log'!$A$8:$A$257,"<="&B24,'Deal Log'!$I$8:$I$257,"Funded") | I24: =I23+H24 | J24: =L23 | K24: =MIN(J24+F24,H24) | L24: =MAX(0,J24+F24-H24) | M24: =D24+MAX(0,H24-(J24+F24)) | N24: =MAX(D24,H24) | O24: =D24+H24 | P24: =IF(Inputs!$C$17="Yes",M24,IF(Inputs!$C$18="Stacked",O24,N24)) | Q24: =IF(B24<=Inputs!$C$7,"paid","future")
A25: 17 | B25: =IF(R25="",IF(DAY(B24)<=20,(EOMONTH(B24,0)-IF(Inputs!$C$14="Yes",MAX(0,WEEKDAY(EOMONTH(B24,0),2)-5),0)),(DATE(YEAR(B24),MONTH(B24)+1,Inputs!$C$13)-IF(Inputs!$C$14="Yes",MAX(0,WEEKDAY(DATE(YEAR(B24),MONTH(B24)+1,Inputs!$C$13),2)-5),0))),R25) | C25: =EOMONTH(B25,0) | D25: =Inputs!$C$12 | E25: =IF(Inputs!$C$19="Recoverable",Inputs!$C$34*12/Inputs!$C$21,0) | F25: =D25+E25 | G25: =G24+F25 | H25: =SUMIFS('Deal Log'!$G$8:$G$257,'Deal Log'!$A$8:$A$257,">"&B24,'Deal Log'!$A$8:$A$257,"<="&B25,'Deal Log'!$I$8:$I$257,"Funded") | I25: =I24+H25 | J25: =L24 | K25: =MIN(J25+F25,H25) | L25: =MAX(0,J25+F25-H25) | M25: =D25+MAX(0,H25-(J25+F25)) | N25: =MAX(D25,H25) | O25: =D25+H25 | P25: =IF(Inputs!$C$17="Yes",M25,IF(Inputs!$C$18="Stacked",O25,N25)) | Q25: =IF(B25<=Inputs!$C$7,"paid","future")
A26: 18 | B26: =IF(R26="",IF(DAY(B25)<=20,(EOMONTH(B25,0)-IF(Inputs!$C$14="Yes",MAX(0,WEEKDAY(EOMONTH(B25,0),2)-5),0)),(DATE(YEAR(B25),MONTH(B25)+1,Inputs!$C$13)-IF(Inputs!$C$14="Yes",MAX(0,WEEKDAY(DATE(YEAR(B25),MONTH(B25)+1,Inputs!$C$13),2)-5),0))),R26) | C26: =EOMONTH(B26,0) | D26: =Inputs!$C$12 | E26: =IF(Inputs!$C$19="Recoverable",Inputs!$C$34*12/Inputs!$C$21,0) | F26: =D26+E26 | G26: =G25+F26 | H26: =SUMIFS('Deal Log'!$G$8:$G$257,'Deal Log'!$A$8:$A$257,">"&B25,'Deal Log'!$A$8:$A$257,"<="&B26,'Deal Log'!$I$8:$I$257,"Funded") | I26: =I25+H26 | J26: =L25 | K26: =MIN(J26+F26,H26) | L26: =MAX(0,J26+F26-H26) | M26: =D26+MAX(0,H26-(J26+F26)) | N26: =MAX(D26,H26) | O26: =D26+H26 | P26: =IF(Inputs!$C$17="Yes",M26,IF(Inputs!$C$18="Stacked",O26,N26)) | Q26: =IF(B26<=Inputs!$C$7,"paid","future")
A27: 19 | B27: =IF(R27="",IF(DAY(B26)<=20,(EOMONTH(B26,0)-IF(Inputs!$C$14="Yes",MAX(0,WEEKDAY(EOMONTH(B26,0),2)-5),0)),(DATE(YEAR(B26),MONTH(B26)+1,Inputs!$C$13)-IF(Inputs!$C$14="Yes",MAX(0,WEEKDAY(DATE(YEAR(B26),MONTH(B26)+1,Inputs!$C$13),2)-5),0))),R27) | C27: =EOMONTH(B27,0) | D27: =Inputs!$C$12 | E27: =IF(Inputs!$C$19="Recoverable",Inputs!$C$34*12/Inputs!$C$21,0) | F27: =D27+E27 | G27: =G26+F27 | H27: =SUMIFS('Deal Log'!$G$8:$G$257,'Deal Log'!$A$8:$A$257,">"&B26,'Deal Log'!$A$8:$A$257,"<="&B27,'Deal Log'!$I$8:$I$257,"Funded") | I27: =I26+H27 | J27: =L26 | K27: =MIN(J27+F27,H27) | L27: =MAX(0,J27+F27-H27) | M27: =D27+MAX(0,H27-(J27+F27)) | N27: =MAX(D27,H27) | O27: =D27+H27 | P27: =IF(Inputs!$C$17="Yes",M27,IF(Inputs!$C$18="Stacked",O27,N27)) | Q27: =IF(B27<=Inputs!$C$7,"paid","future")
A28: 20 | B28: =IF(R28="",IF(DAY(B27)<=20,(EOMONTH(B27,0)-IF(Inputs!$C$14="Yes",MAX(0,WEEKDAY(EOMONTH(B27,0),2)-5),0)),(DATE(YEAR(B27),MONTH(B27)+1,Inputs!$C$13)-IF(Inputs!$C$14="Yes",MAX(0,WEEKDAY(DATE(YEAR(B27),MONTH(B27)+1,Inputs!$C$13),2)-5),0))),R28) | C28: =EOMONTH(B28,0) | D28: =Inputs!$C$12 | E28: =IF(Inputs!$C$19="Recoverable",Inputs!$C$34*12/Inputs!$C$21,0) | F28: =D28+E28 | G28: =G27+F28 | H28: =SUMIFS('Deal Log'!$G$8:$G$257,'Deal Log'!$A$8:$A$257,">"&B27,'Deal Log'!$A$8:$A$257,"<="&B28,'Deal Log'!$I$8:$I$257,"Funded") | I28: =I27+H28 | J28: =L27 | K28: =MIN(J28+F28,H28) | L28: =MAX(0,J28+F28-H28) | M28: =D28+MAX(0,H28-(J28+F28)) | N28: =MAX(D28,H28) | O28: =D28+H28 | P28: =IF(Inputs!$C$17="Yes",M28,IF(Inputs!$C$18="Stacked",O28,N28)) | Q28: =IF(B28<=Inputs!$C$7,"paid","future")
A29: 21 | B29: =IF(R29="",IF(DAY(B28)<=20,(EOMONTH(B28,0)-IF(Inputs!$C$14="Yes",MAX(0,WEEKDAY(EOMONTH(B28,0),2)-5),0)),(DATE(YEAR(B28),MONTH(B28)+1,Inputs!$C$13)-IF(Inputs!$C$14="Yes",MAX(0,WEEKDAY(DATE(YEAR(B28),MONTH(B28)+1,Inputs!$C$13),2)-5),0))),R29) | C29: =EOMONTH(B29,0) | D29: =Inputs!$C$12 | E29: =IF(Inputs!$C$19="Recoverable",Inputs!$C$34*12/Inputs!$C$21,0) | F29: =D29+E29 | G29: =G28+F29 | H29: =SUMIFS('Deal Log'!$G$8:$G$257,'Deal Log'!$A$8:$A$257,">"&B28,'Deal Log'!$A$8:$A$257,"<="&B29,'Deal Log'!$I$8:$I$257,"Funded") | I29: =I28+H29 | J29: =L28 | K29: =MIN(J29+F29,H29) | L29: =MAX(0,J29+F29-H29) | M29: =D29+MAX(0,H29-(J29+F29)) | N29: =MAX(D29,H29) | O29: =D29+H29 | P29: =IF(Inputs!$C$17="Yes",M29,IF(Inputs!$C$18="Stacked",O29,N29)) | Q29: =IF(B29<=Inputs!$C$7,"paid","future")
A30: 22 | B30: =IF(R30="",IF(DAY(B29)<=20,(EOMONTH(B29,0)-IF(Inputs!$C$14="Yes",MAX(0,WEEKDAY(EOMONTH(B29,0),2)-5),0)),(DATE(YEAR(B29),MONTH(B29)+1,Inputs!$C$13)-IF(Inputs!$C$14="Yes",MAX(0,WEEKDAY(DATE(YEAR(B29),MONTH(B29)+1,Inputs!$C$13),2)-5),0))),R30) | C30: =EOMONTH(B30,0) | D30: =Inputs!$C$12 | E30: =IF(Inputs!$C$19="Recoverable",Inputs!$C$34*12/Inputs!$C$21,0) | F30: =D30+E30 | G30: =G29+F30 | H30: =SUMIFS('Deal Log'!$G$8:$G$257,'Deal Log'!$A$8:$A$257,">"&B29,'Deal Log'!$A$8:$A$257,"<="&B30,'Deal Log'!$I$8:$I$257,"Funded") | I30: =I29+H30 | J30: =L29 | K30: =MIN(J30+F30,H30) | L30: =MAX(0,J30+F30-H30) | M30: =D30+MAX(0,H30-(J30+F30)) | N30: =MAX(D30,H30) | O30: =D30+H30 | P30: =IF(Inputs!$C$17="Yes",M30,IF(Inputs!$C$18="Stacked",O30,N30)) | Q30: =IF(B30<=Inputs!$C$7,"paid","future")
A31: 23 | B31: =IF(R31="",IF(DAY(B30)<=20,(EOMONTH(B30,0)-IF(Inputs!$C$14="Yes",MAX(0,WEEKDAY(EOMONTH(B30,0),2)-5),0)),(DATE(YEAR(B30),MONTH(B30)+1,Inputs!$C$13)-IF(Inputs!$C$14="Yes",MAX(0,WEEKDAY(DATE(YEAR(B30),MONTH(B30)+1,Inputs!$C$13),2)-5),0))),R31) | C31: =EOMONTH(B31,0) | D31: =Inputs!$C$12 | E31: =IF(Inputs!$C$19="Recoverable",Inputs!$C$34*12/Inputs!$C$21,0) | F31: =D31+E31 | G31: =G30+F31 | H31: =SUMIFS('Deal Log'!$G$8:$G$257,'Deal Log'!$A$8:$A$257,">"&B30,'Deal Log'!$A$8:$A$257,"<="&B31,'Deal Log'!$I$8:$I$257,"Funded") | I31: =I30+H31 | J31: =L30 | K31: =MIN(J31+F31,H31) | L31: =MAX(0,J31+F31-H31) | M31: =D31+MAX(0,H31-(J31+F31)) | N31: =MAX(D31,H31) | O31: =D31+H31 | P31: =IF(Inputs!$C$17="Yes",M31,IF(Inputs!$C$18="Stacked",O31,N31)) | Q31: =IF(B31<=Inputs!$C$7,"paid","future")
... A116: 108 | B116: =IF(R116="",IF(DAY(B115)<=20,(EOMONTH(B115,0)-IF(Inputs!$C$14="Yes",MAX(0,WEEKDAY(EOMONTH(B115,0),2)-5),0)),(DATE(YEAR(B115),MONTH(B115)+1,Inputs!$C$13)-IF(Inputs!$C$14="Yes",MAX(0,WEEKDAY(DATE(YEAR(B115),MONTH(B115)+1,Inputs!$C$13),2)-5),0))),R116) | C116: =EOMONTH(B116,0) | D116: =Inputs!$C$12 | E116: =IF(Inputs!$C$19="Recoverable",Inputs!$C$34*12/Inputs!$C$21,0) | F116: =D116+E116 | G116: =G115+F116 | H116: =SUMIFS('Deal Log'!$G$8:$G$257,'Deal Log'!$A$8:$A$257,">"&B115,'Deal Log'!$A$8:$A$257,"<="&B116,'Deal Log'!$I$8:$I$257,"Funded") | I116: =I115+H116 | J116: =L115 | K116: =MIN(J116+F116,H116) | L116: =MAX(0,J116+F116-H116) | M116: =D116+MAX(0,H116-(J116+F116)) | N116: =MAX(D116,H116) | O116: =D116+H116 | P116: =IF(Inputs!$C$17="Yes",M116,IF(Inputs!$C$18="Stacked",O116,N116)) | Q116: =IF(B116<=Inputs!$C$7,"paid","future")
B117: 3-YEAR TOTALS | D117: =SUM(D$9:D$116) | E117: =SUM(E$9:E$116) | F117: =SUM(F$9:F$116) | H117: =SUM(H$9:H$116) | M117: =SUM(M$9:M$116) | N117: =SUM(N$9:N$116) | O117: =SUM(O$9:O$116) | P117: =SUM(P$9:P$116)
B119: Cost of the wrong comp structure over 3 years (Stacked minus Recoverable): | M119: =O117-M117

Sheet Break-Even
A1: BREAK-EVEN & PROFIT — how much do you have to close to actually get paid?
A2: Four comp structures, side by side, on identical costs. Column C is the structure your Inputs toggles are set to.
A5: A. THE COST STACK (per month)
B6: Component | C6: Amount | H6: What it means
B7: Fixed obligations | C7: ='Monthly Budget'!C14 | H7: Pulled straight from 'Monthly Budget'. Change spending there, not here.
B8: Variable / lifestyle | C8: ='Monthly Budget'!C23
B9: Marketing (if self-funded) | C9: ='Monthly Budget'!C27
B10: =CASH BURN before tax | C10: =SUM(C7:C9)
A12: B. BREAK-EVEN VOLUME UNDER EACH COMP STRUCTURE
B13: Metric | C13: ACTIVE (your toggles) | D13: Recoverable draw | E13: Non-recov Greater-Of | F13: Non-recov Stacked | H13: Notes
B14: Draw income counted toward your bills | C14: =IF(Inputs!$C$17="Yes",D14,IF(Inputs!$C$18="Stacked",F14,E14)) | D14: =Inputs!$C$23 | E14: =Inputs!$C$23 | F14: =Inputs!$C$23 | H14: Under every structure you receive the draw in cash each month.
B15: Does commission ADD to the draw? | C15: =IF(Inputs!$C$17="Yes",D15,IF(Inputs!$C$18="Stacked",F15,E15)) | D15: ="No - repays advance first" | E15: ="No - you get the greater" | F15: ="Yes - fully additive" | H15: This single row is why the structures diverge.
B16: Advance balance to clear first | C16: =IF(Inputs!$C$17="Yes",D16,IF(Inputs!$C$18="Stacked",F16,E16)) | D16: =Inputs!$C$24 | E16: =0 | F16: =0 | H16: 11 draws x $1,231.58 already taken. Only the recoverable structure claws this back.
B17: Monthly commission needed to COVER YOUR LIFE | C17: =IF(Inputs!$C$17="Yes",D17,IF(Inputs!$C$18="Stacked",F17,E17)) | D17: =MAX(0,C10-Inputs!$C$23)+Inputs!$C$23 | E17: =MAX(0,C10) | F17: =MAX(0,C10-Inputs!$C$23) | H17: Recoverable is brutal: every commission dollar first repays the draw, so to net your burn you must earn the burn PLUS replace the draw you are repaying.
B18: = LOAN VOLUME needed / month | C18: =IF(Inputs!$C$17="Yes",D18,IF(Inputs!$C$18="Stacked",F18,E18)) | D18: =D17/Inputs!$C$15 | E18: =E17/Inputs!$C$15 | F18: =F17/Inputs!$C$15 | H18: At 75 bps.
B19: = LOANS / month at your average size | C19: =IF(Inputs!$C$17="Yes",D19,IF(Inputs!$C$18="Stacked",F19,E19)) | D19: =IFERROR(D18/Inputs!$C$94,0) | E19: =IFERROR(E18/Inputs!$C$94,0) | F19: =IFERROR(F18/Inputs!$C$94,0) | H19: The number that actually matters day to day.
B20: Volume to CLEAR THE ADVANCE within 12 months | C20: =IF(Inputs!$C$17="Yes",D20,IF(Inputs!$C$18="Stacked",F20,E20)) | D20: =(Inputs!$C$23+Inputs!$C$24/12+IF(Inputs!$C$19="Recoverable",Inputs!$C$34,0))/Inputs!$C$15 | E20: =0 | F20: =0 | H20: Recoverable only: you must out-earn the NEW draw accruing each month AND chip at the $13,547 already owed.
B21: = loans / month to clear it in 12 months | C21: =IF(Inputs!$C$17="Yes",D21,IF(Inputs!$C$18="Stacked",F21,E21)) | D21: =IFERROR(D20/Inputs!$C$94,0) | E21: =0 | F21: =0
A23: C. PROFIT LADDER (non-recoverable / Greater-Of basis - your realistic target structure)
B24: If you want to bank this much per month... | C24: Commission needed | D24: Loan volume needed | E24: Loans/mo needed | F24: Annual volume | H24: Reality check
B25: $0 / mo surplus — Just break even - bills paid, nothing saved | C25: =C10+0 | D25: =C25/Inputs!$C$15 | E25: =IFERROR(D25/Inputs!$C$94,0) | F25: =D25*12 | H25: Read column E. That is your monthly closing target - the only number worth taping to your monitor.
B26: $500 / mo surplus — Bare-minimum saving | C26: =C10+500 | D26: =C26/Inputs!$C$15 | E26: =IFERROR(D26/Inputs!$C$94,0) | F26: =D26*12
B27: $1,500 / mo surplus — Roth IRA maxed + real progress on the ring | C27: =C10+1500 | D27: =C27/Inputs!$C$15 | E27: =IFERROR(D27/Inputs!$C$94,0) | F27: =D27*12
B28: $3,000 / mo surplus — Ring in 2 yrs AND house down payment on track | C28: =C10+3000 | D28: =C28/Inputs!$C$15 | E28: =IFERROR(D28/Inputs!$C$94,0) | F28: =D28*12
B29: $5,000 / mo surplus — Top-producer pace | C29: =C10+5000 | D29: =C29/Inputs!$C$15 | E29: =IFERROR(D29/Inputs!$C$94,0) | F29: =D29*12
A32: D. SENSITIVITY — ANNUAL net cash to you (Greater-Of basis, after tax reserve, after all living costs)
B34: Avg loan size \ Loans per month | C34: 1 | D34: 2 | E34: 3 | F34: 4 | G34: 5
B35: 200000 | C35: =(MAX(Inputs!$C$23,$B35*1*Inputs!$C$15)-IF(Inputs!$C$20="1099",MAX(Inputs!$C$23,$B35*1*Inputs!$C$15)*Inputs!$C$74,0)-$C$10)*12 | D35: =(MAX(Inputs!$C$23,$B35*2*Inputs!$C$15)-IF(Inputs!$C$20="1099",MAX(Inputs!$C$23,$B35*2*Inputs!$C$15)*Inputs!$C$74,0)-$C$10)*12 | E35: =(MAX(Inputs!$C$23,$B35*3*Inputs!$C$15)-IF(Inputs!$C$20="1099",MAX(Inputs!$C$23,$B35*3*Inputs!$C$15)*Inputs!$C$74,0)-$C$10)*12 | F35: =(MAX(Inputs!$C$23,$B35*4*Inputs!$C$15)-IF(Inputs!$C$20="1099",MAX(Inputs!$C$23,$B35*4*Inputs!$C$15)*Inputs!$C$74,0)-$C$10)*12 | G35: =(MAX(Inputs!$C$23,$B35*5*Inputs!$C$15)-IF(Inputs!$C$20="1099",MAX(Inputs!$C$23,$B35*5*Inputs!$C$15)*Inputs!$C$74,0)-$C$10)*12
B36: 250000 | C36: =(MAX(Inputs!$C$23,$B36*1*Inputs!$C$15)-IF(Inputs!$C$20="1099",MAX(Inputs!$C$23,$B36*1*Inputs!$C$15)*Inputs!$C$74,0)-$C$10)*12 | D36: =(MAX(Inputs!$C$23,$B36*2*Inputs!$C$15)-IF(Inputs!$C$20="1099",MAX(Inputs!$C$23,$B36*2*Inputs!$C$15)*Inputs!$C$74,0)-$C$10)*12 | E36: =(MAX(Inputs!$C$23,$B36*3*Inputs!$C$15)-IF(Inputs!$C$20="1099",MAX(Inputs!$C$23,$B36*3*Inputs!$C$15)*Inputs!$C$74,0)-$C$10)*12 | F36: =(MAX(Inputs!$C$23,$B36*4*Inputs!$C$15)-IF(Inputs!$C$20="1099",MAX(Inputs!$C$23,$B36*4*Inputs!$C$15)*Inputs!$C$74,0)-$C$10)*12 | G36: =(MAX(Inputs!$C$23,$B36*5*Inputs!$C$15)-IF(Inputs!$C$20="1099",MAX(Inputs!$C$23,$B36*5*Inputs!$C$15)*Inputs!$C$74,0)-$C$10)*12
B37: 300000 | C37: =(MAX(Inputs!$C$23,$B37*1*Inputs!$C$15)-IF(Inputs!$C$20="1099",MAX(Inputs!$C$23,$B37*1*Inputs!$C$15)*Inputs!$C$74,0)-$C$10)*12 | D37: =(MAX(Inputs!$C$23,$B37*2*Inputs!$C$15)-IF(Inputs!$C$20="1099",MAX(Inputs!$C$23,$B37*2*Inputs!$C$15)*Inputs!$C$74,0)-$C$10)*12 | E37: =(MAX(Inputs!$C$23,$B37*3*Inputs!$C$15)-IF(Inputs!$C$20="1099",MAX(Inputs!$C$23,$B37*3*Inputs!$C$15)*Inputs!$C$74,0)-$C$10)*12 | F37: =(MAX(Inputs!$C$23,$B37*4*Inputs!$C$15)-IF(Inputs!$C$20="1099",MAX(Inputs!$C$23,$B37*4*Inputs!$C$15)*Inputs!$C$74,0)-$C$10)*12 | G37: =(MAX(Inputs!$C$23,$B37*5*Inputs!$C$15)-IF(Inputs!$C$20="1099",MAX(Inputs!$C$23,$B37*5*Inputs!$C$15)*Inputs!$C$74,0)-$C$10)*12
B38: 350000 | C38: =(MAX(Inputs!$C$23,$B38*1*Inputs!$C$15)-IF(Inputs!$C$20="1099",MAX(Inputs!$C$23,$B38*1*Inputs!$C$15)*Inputs!$C$74,0)-$C$10)*12 | D38: =(MAX(Inputs!$C$23,$B38*2*Inputs!$C$15)-IF(Inputs!$C$20="1099",MAX(Inputs!$C$23,$B38*2*Inputs!$C$15)*Inputs!$C$74,0)-$C$10)*12 | E38: =(MAX(Inputs!$C$23,$B38*3*Inputs!$C$15)-IF(Inputs!$C$20="1099",MAX(Inputs!$C$23,$B38*3*Inputs!$C$15)*Inputs!$C$74,0)-$C$10)*12 | F38: =(MAX(Inputs!$C$23,$B38*4*Inputs!$C$15)-IF(Inputs!$C$20="1099",MAX(Inputs!$C$23,$B38*4*Inputs!$C$15)*Inputs!$C$74,0)-$C$10)*12 | G38: =(MAX(Inputs!$C$23,$B38*5*Inputs!$C$15)-IF(Inputs!$C$20="1099",MAX(Inputs!$C$23,$B38*5*Inputs!$C$15)*Inputs!$C$74,0)-$C$10)*12
B39: 400000 | C39: =(MAX(Inputs!$C$23,$B39*1*Inputs!$C$15)-IF(Inputs!$C$20="1099",MAX(Inputs!$C$23,$B39*1*Inputs!$C$15)*Inputs!$C$74,0)-$C$10)*12 | D39: =(MAX(Inputs!$C$23,$B39*2*Inputs!$C$15)-IF(Inputs!$C$20="1099",MAX(Inputs!$C$23,$B39*2*Inputs!$C$15)*Inputs!$C$74,0)-$C$10)*12 | E39: =(MAX(Inputs!$C$23,$B39*3*Inputs!$C$15)-IF(Inputs!$C$20="1099",MAX(Inputs!$C$23,$B39*3*Inputs!$C$15)*Inputs!$C$74,0)-$C$10)*12 | F39: =(MAX(Inputs!$C$23,$B39*4*Inputs!$C$15)-IF(Inputs!$C$20="1099",MAX(Inputs!$C$23,$B39*4*Inputs!$C$15)*Inputs!$C$74,0)-$C$10)*12 | G39: =(MAX(Inputs!$C$23,$B39*5*Inputs!$C$15)-IF(Inputs!$C$20="1099",MAX(Inputs!$C$23,$B39*5*Inputs!$C$15)*Inputs!$C$74,0)-$C$10)*12
B40: 500000 | C40: =(MAX(Inputs!$C$23,$B40*1*Inputs!$C$15)-IF(Inputs!$C$20="1099",MAX(Inputs!$C$23,$B40*1*Inputs!$C$15)*Inputs!$C$74,0)-$C$10)*12 | D40: =(MAX(Inputs!$C$23,$B40*2*Inputs!$C$15)-IF(Inputs!$C$20="1099",MAX(Inputs!$C$23,$B40*2*Inputs!$C$15)*Inputs!$C$74,0)-$C$10)*12 | E40: =(MAX(Inputs!$C$23,$B40*3*Inputs!$C$15)-IF(Inputs!$C$20="1099",MAX(Inputs!$C$23,$B40*3*Inputs!$C$15)*Inputs!$C$74,0)-$C$10)*12 | F40: =(MAX(Inputs!$C$23,$B40*4*Inputs!$C$15)-IF(Inputs!$C$20="1099",MAX(Inputs!$C$23,$B40*4*Inputs!$C$15)*Inputs!$C$74,0)-$C$10)*12 | G40: =(MAX(Inputs!$C$23,$B40*5*Inputs!$C$15)-IF(Inputs!$C$20="1099",MAX(Inputs!$C$23,$B40*5*Inputs!$C$15)*Inputs!$C$74,0)-$C$10)*12
B42: Green = you are building wealth. Red = you are going backwards and living on the draw.

Sheet Monthly Budget
A1: MONTHLY BUDGET — what it costs to be you, every month
A2: Every amount is pulled from Inputs. To change a number, change it there. Yellow rows are costs you did not list and must confirm.
A5: A. FIXED OBLIGATIONS (contractual - they hit whether you close a loan or not)
B6: Line item | C6: Per month | D6: Per year | E6: Due day | F6: Type | G6: Notes
B7: Auto loan payment | C7: =Inputs!$C$28 | D7: =C7*12 | E7: ==Inputs!$C$29 | F7: Fixed | G7: Balance $25,092.02. Amortization and payoff on 'Car Loan'.
B8: Auto insurance | C8: =Inputs!$C$35 | D8: =C8*12 | E8: ="varies" | F8: Fixed | G8: NOT LISTED BY YOU - estimated. Your lienholder requires full coverage, so this bill exists.
B9: Gym membership | C9: =Inputs!$C$30*Inputs!$C$31 | D9: =C9*12 | E9: ="14 & EOM" | F9: Fixed | G9: $31.99 x 2/mo, same cadence as your draw.
B10: Amazon Prime | C10: =Inputs!$C$32 | D10: =C10*12 | E10: ==Inputs!$C$33 | F10: Fixed | G10: Annual plan is ~$139/yr = $11.58/mo. Switching saves $41/yr.
B11: Phone | C11: =Inputs!$C$36 | D11: =C11*12 | E11: ="varies" | F11: Fixed | G11: NOT LISTED - confirm or set to 0 if on a family plan.
B12: Health insurance | C12: =Inputs!$C$37 | D12: =C12*12 | E12: ="varies" | F12: Fixed | G12: NOT LISTED. $0 only while on a parent's plan. You age off at 26 - budget $350-500/mo from then. Plan for it now.
B13: Other fixed | C13: =Inputs!$C$38 | D13: =C13*12 | E13: ="varies" | F13: Fixed | G13: Streaming, storage, anything recurring you have not listed.
B14: TOTAL FIXED | C14: =SUM(C7:C13) | D14: =C14*12
A16: B. VARIABLE / DRIVER-BASED (scale with how hard you work)
B17: Line item | C17: Per month | D17: Per year | E17: Driver | F17: Type | G17: Notes
B18: Fuel | C18: =Inputs!$C$43 | D18: =C18*12 | E18: ="1,000 mi @ 19mpg" | F18: Variable | G18: 1,000 mi/mo at $4.10 and 19 mpg. If 1099, these miles are worth FAR more as a deduction than they cost - see 'Tax Reserve'.
B19: Aroma Joe's | C19: =Inputs!$C$46 | D19: =C19*12 | E19: ="$6 x 4/wk" | F19: Variable | G19: Set your real visit count on Inputs. Every extra visit per week costs $312/yr.
B20: Car maintenance reserve | C20: =Inputs!$C$49 | D20: =C20*12 | E20: ="12k mi/yr" | F20: Variable | G20: NOT LISTED. Maine winter driving: tires, brakes, oil. Set it aside monthly so it is never a surprise.
B21: Groceries / eating out | C21: =Inputs!$C$47 | D21: =C21*12 | E21: ="lifestyle" | F21: Variable | G21: NOT LISTED. You live at home so this may be low - but client lunches and road food are real.
B22: Personal / entertainment | C22: =Inputs!$C$48 | D22: =C22*12 | E22: ="lifestyle" | F22: Variable | G22: NOT LISTED. Placeholder.
B23: TOTAL VARIABLE | C23: =SUM(C18:C22) | D23: =C23*12
A25: C. BUSINESS (only a personal cost if you are self-funding it)
B26: Line item | C26: Per month | D26: Per year | E26: Driver | F26: Type | G26: Notes
B27: Marketing | C27: =IF(Inputs!$C$19="Self-funded",Inputs!$C$34,0) | D27: =C27*12 | E27: =Inputs!$C$19 | F27: Business | G27: $0 here if the owner funds it. If it is a RECOVERABLE advance it is not a monthly bill - it is added to your advance balance on 'Draw Recovery' and repaid from commission.
A29: D. BOTTOM LINE
B30: TOTAL COST OF LIVING (fixed + variable) | C30: =C14+C23 | D30: =C30*12 | G30: This is your personal survival number. It does not include taxes or marketing.
B31: + Marketing (if self-funded) | C31: =C27 | D31: =C31*12
B32: =TOTAL MONTHLY CASH BURN | C32: =C14+C23+C27 | D32: =C32*12 | G32: Every dollar that must leave your accounts in an average month.
B33: Draw income (semi-monthly x 24/yr) | C33: =Inputs!$C$23 | D33: =C33*12 | G33: $1,231.58 x 24 / 12. This is the floor you can count on.
B34: SURPLUS / (SHORTFALL) on the draw alone | C34: =C33-C32 | D34: =C34*12 | G34: If negative, the draw alone does not cover your life and every month without a closing digs a hole.
B35: Commission needed to break even (per month) | C35: =MAX(0,C32-C33) | D35: =C35*12
B36: = loan volume needed | C36: =C35/Inputs!$C$15 | G36: At 75 bps.
B37: = loans per month | C37: =IFERROR(C36/Inputs!$C$94,0) | G37: At your average loan size.

Sheet Cash Flow
A1: 36-MONTH CASH FLOW — Sept 2026 through Aug 2029
A2: Past/current months use your Deal Log. Future months use the ACTIVE SCENARIO on Inputs. Logged pipeline always overrides the forecast for that month.
A4: Opening advance balance owed (recoverable case): | E4: =IF(Inputs!$C$17="Yes",MAX(0,Inputs!$C$24-SUMIFS('Deal Log'!$G$8:$G$257,'Deal Log'!$A$8:$A$257,"<="&Inputs!$C$7,'Deal Log'!$I$8:$I$257,"Funded")),0) | F4: =draws taken to date less commissions already credited. Zero if the draw is non-recoverable.
A5: Active scenario: | C5: =Inputs!$C$98 | D5: =Inputs!$C$99&" loans/mo x $"&TEXT(Inputs!$C$94,"#,##0")&" = "&TEXT(Inputs!$C$101,"$#,##0")&"/mo commission"
A8: Month | B8: Draws in mo | C8: Draw income | D8: Commission (actual/fcst) | E8: Opening advance | F8: Advance added | G8: Recapture | H8: Closing advance | I8: NET CASH INCOME | J8: Tax reserve | K8: After-tax cash in | L8: Fixed costs | M8: Variable costs | N8: Marketing | O8: TOTAL OUT | P8: NET SURPLUS | Q8: CUMULATIVE SURPLUS | R8: Cert auto transfer
A9: =EOMONTH(Inputs!$C$7,0) | B9: =COUNTIFS('Draw Recovery'!$B$9:$B$116,">="&EOMONTH(A9,-1)+1,'Draw Recovery'!$B$9:$B$116,"<="&A9) | C9: =B9*Inputs!$C$12 | D9: =IF(SUMIFS('Deal Log'!$G$8:$G$257,'Deal Log'!$L$8:$L$257,A9,'Deal Log'!$I$8:$I$257,"Funded")+SUMIFS('Deal Log'!$K$8:$K$257,'Deal Log'!$L$8:$L$257,A9,'Deal Log'!$I$8:$I$257,"Locked")+SUMIFS('Deal Log'!$K$8:$K$257,'Deal Log'!$L$8:$L$257,A9,'Deal Log'!$I$8:$I$257,"Pre-App")>0,SUMIFS('Deal Log'!$G$8:$G$257,'Deal Log'!$L$8:$L$257,A9,'Deal Log'!$I$8:$I$257,"Funded")+SUMIFS('Deal Log'!$K$8:$K$257,'Deal Log'!$L$8:$L$257,A9,'Deal Log'!$I$8:$I$257,"Locked")+SUMIFS('Deal Log'!$K$8:$K$257,'Deal Log'!$L$8:$L$257,A9,'Deal Log'!$I$8:$I$257,"Pre-App"),Inputs!$C$101) | E9: =$E$4 | F9: =IF(Inputs!$C$17="Yes",C9,0)+IF(Inputs!$C$19="Recoverable",Inputs!$C$34,0) | G9: =MIN(E9+F9,D9) | H9: =MAX(0,E9+F9-D9) | I9: =IF(Inputs!$C$17="Yes",C9+MAX(0,D9-(E9+F9)),IF(Inputs!$C$18="Stacked",C9+D9,MAX(C9,D9))) | J9: =IF(Inputs!$C$20="1099",I9*Inputs!$C$74,0) | K9: =I9-J9 | L9: ='Monthly Budget'!$C$14 | M9: ='Monthly Budget'!$C$23 | N9: ='Monthly Budget'!$C$27 | O9: =L9+M9+N9 | P9: =K9-O9 | Q9: =P9 | R9: =IF(COUNTIFS('Certificate Ladder'!$B$8:$B$40,">="&EOMONTH(A9,-1)+1,'Certificate Ladder'!$B$8:$B$40,"<="&A9)>0,Inputs!$C$59,0)
A10: =EOMONTH(A9,1) | B10: =COUNTIFS('Draw Recovery'!$B$9:$B$116,">="&EOMONTH(A10,-1)+1,'Draw Recovery'!$B$9:$B$116,"<="&A10) | C10: =B10*Inputs!$C$12 | D10: =IF(SUMIFS('Deal Log'!$G$8:$G$257,'Deal Log'!$L$8:$L$257,A10,'Deal Log'!$I$8:$I$257,"Funded")+SUMIFS('Deal Log'!$K$8:$K$257,'Deal Log'!$L$8:$L$257,A10,'Deal Log'!$I$8:$I$257,"Locked")+SUMIFS('Deal Log'!$K$8:$K$257,'Deal Log'!$L$8:$L$257,A10,'Deal Log'!$I$8:$I$257,"Pre-App")>0,SUMIFS('Deal Log'!$G$8:$G$257,'Deal Log'!$L$8:$L$257,A10,'Deal Log'!$I$8:$I$257,"Funded")+SUMIFS('Deal Log'!$K$8:$K$257,'Deal Log'!$L$8:$L$257,A10,'Deal Log'!$I$8:$I$257,"Locked")+SUMIFS('Deal Log'!$K$8:$K$257,'Deal Log'!$L$8:$L$257,A10,'Deal Log'!$I$8:$I$257,"Pre-App"),Inputs!$C$101) | E10: =H9 | F10: =IF(Inputs!$C$17="Yes",C10,0)+IF(Inputs!$C$19="Recoverable",Inputs!$C$34,0) | G10: =MIN(E10+F10,D10) | H10: =MAX(0,E10+F10-D10) | I10: =IF(Inputs!$C$17="Yes",C10+MAX(0,D10-(E10+F10)),IF(Inputs!$C$18="Stacked",C10+D10,MAX(C10,D10))) | J10: =IF(Inputs!$C$20="1099",I10*Inputs!$C$74,0) | K10: =I10-J10 | L10: ='Monthly Budget'!$C$14 | M10: ='Monthly Budget'!$C$23 | N10: ='Monthly Budget'!$C$27 | O10: =L10+M10+N10 | P10: =K10-O10 | Q10: =Q9+P10 | R10: =IF(COUNTIFS('Certificate Ladder'!$B$8:$B$40,">="&EOMONTH(A10,-1)+1,'Certificate Ladder'!$B$8:$B$40,"<="&A10)>0,Inputs!$C$59,0)
A11: =EOMONTH(A10,1) | B11: =COUNTIFS('Draw Recovery'!$B$9:$B$116,">="&EOMONTH(A11,-1)+1,'Draw Recovery'!$B$9:$B$116,"<="&A11) | C11: =B11*Inputs!$C$12 | D11: =IF(SUMIFS('Deal Log'!$G$8:$G$257,'Deal Log'!$L$8:$L$257,A11,'Deal Log'!$I$8:$I$257,"Funded")+SUMIFS('Deal Log'!$K$8:$K$257,'Deal Log'!$L$8:$L$257,A11,'Deal Log'!$I$8:$I$257,"Locked")+SUMIFS('Deal Log'!$K$8:$K$257,'Deal Log'!$L$8:$L$257,A11,'Deal Log'!$I$8:$I$257,"Pre-App")>0,SUMIFS('Deal Log'!$G$8:$G$257,'Deal Log'!$L$8:$L$257,A11,'Deal Log'!$I$8:$I$257,"Funded")+SUMIFS('Deal Log'!$K$8:$K$257,'Deal Log'!$L$8:$L$257,A11,'Deal Log'!$I$8:$I$257,"Locked")+SUMIFS('Deal Log'!$K$8:$K$257,'Deal Log'!$L$8:$L$257,A11,'Deal Log'!$I$8:$I$257,"Pre-App"),Inputs!$C$101) | E11: =H10 | F11: =IF(Inputs!$C$17="Yes",C11,0)+IF(Inputs!$C$19="Recoverable",Inputs!$C$34,0) | G11: =MIN(E11+F11,D11) | H11: =MAX(0,E11+F11-D11) | I11: =IF(Inputs!$C$17="Yes",C11+MAX(0,D11-(E11+F11)),IF(Inputs!$C$18="Stacked",C11+D11,MAX(C11,D11))) | J11: =IF(Inputs!$C$20="1099",I11*Inputs!$C$74,0) | K11: =I11-J11 | L11: ='Monthly Budget'!$C$14 | M11: ='Monthly Budget'!$C$23 | N11: ='Monthly Budget'!$C$27 | O11: =L11+M11+N11 | P11: =K11-O11 | Q11: =Q10+P11 | R11: =IF(COUNTIFS('Certificate Ladder'!$B$8:$B$40,">="&EOMONTH(A11,-1)+1,'Certificate Ladder'!$B$8:$B$40,"<="&A11)>0,Inputs!$C$59,0)
A12: =EOMONTH(A11,1) | B12: =COUNTIFS('Draw Recovery'!$B$9:$B$116,">="&EOMONTH(A12,-1)+1,'Draw Recovery'!$B$9:$B$116,"<="&A12) | C12: =B12*Inputs!$C$12 | D12: =IF(SUMIFS('Deal Log'!$G$8:$G$257,'Deal Log'!$L$8:$L$257,A12,'Deal Log'!$I$8:$I$257,"Funded")+SUMIFS('Deal Log'!$K$8:$K$257,'Deal Log'!$L$8:$L$257,A12,'Deal Log'!$I$8:$I$257,"Locked")+SUMIFS('Deal Log'!$K$8:$K$257,'Deal Log'!$L$8:$L$257,A12,'Deal Log'!$I$8:$I$257,"Pre-App")>0,SUMIFS('Deal Log'!$G$8:$G$257,'Deal Log'!$L$8:$L$257,A12,'Deal Log'!$I$8:$I$257,"Funded")+SUMIFS('Deal Log'!$K$8:$K$257,'Deal Log'!$L$8:$L$257,A12,'Deal Log'!$I$8:$I$257,"Locked")+SUMIFS('Deal Log'!$K$8:$K$257,'Deal Log'!$L$8:$L$257,A12,'Deal Log'!$I$8:$I$257,"Pre-App"),Inputs!$C$101) | E12: =H11 | F12: =IF(Inputs!$C$17="Yes",C12,0)+IF(Inputs!$C$19="Recoverable",Inputs!$C$34,0) | G12: =MIN(E12+F12,D12) | H12: =MAX(0,E12+F12-D12) | I12: =IF(Inputs!$C$17="Yes",C12+MAX(0,D12-(E12+F12)),IF(Inputs!$C$18="Stacked",C12+D12,MAX(C12,D12))) | J12: =IF(Inputs!$C$20="1099",I12*Inputs!$C$74,0) | K12: =I12-J12 | L12: ='Monthly Budget'!$C$14 | M12: ='Monthly Budget'!$C$23 | N12: ='Monthly Budget'!$C$27 | O12: =L12+M12+N12 | P12: =K12-O12 | Q12: =Q11+P12 | R12: =IF(COUNTIFS('Certificate Ladder'!$B$8:$B$40,">="&EOMONTH(A12,-1)+1,'Certificate Ladder'!$B$8:$B$40,"<="&A12)>0,Inputs!$C$59,0)
A13: =EOMONTH(A12,1) | B13: =COUNTIFS('Draw Recovery'!$B$9:$B$116,">="&EOMONTH(A13,-1)+1,'Draw Recovery'!$B$9:$B$116,"<="&A13) | C13: =B13*Inputs!$C$12 | D13: =IF(SUMIFS('Deal Log'!$G$8:$G$257,'Deal Log'!$L$8:$L$257,A13,'Deal Log'!$I$8:$I$257,"Funded")+SUMIFS('Deal Log'!$K$8:$K$257,'Deal Log'!$L$8:$L$257,A13,'Deal Log'!$I$8:$I$257,"Locked")+SUMIFS('Deal Log'!$K$8:$K$257,'Deal Log'!$L$8:$L$257,A13,'Deal Log'!$I$8:$I$257,"Pre-App")>0,SUMIFS('Deal Log'!$G$8:$G$257,'Deal Log'!$L$8:$L$257,A13,'Deal Log'!$I$8:$I$257,"Funded")+SUMIFS('Deal Log'!$K$8:$K$257,'Deal Log'!$L$8:$L$257,A13,'Deal Log'!$I$8:$I$257,"Locked")+SUMIFS('Deal Log'!$K$8:$K$257,'Deal Log'!$L$8:$L$257,A13,'Deal Log'!$I$8:$I$257,"Pre-App"),Inputs!$C$101) | E13: =H12 | F13: =IF(Inputs!$C$17="Yes",C13,0)+IF(Inputs!$C$19="Recoverable",Inputs!$C$34,0) | G13: =MIN(E13+F13,D13) | H13: =MAX(0,E13+F13-D13) | I13: =IF(Inputs!$C$17="Yes",C13+MAX(0,D13-(E13+F13)),IF(Inputs!$C$18="Stacked",C13+D13,MAX(C13,D13))) | J13: =IF(Inputs!$C$20="1099",I13*Inputs!$C$74,0) | K13: =I13-J13 | L13: ='Monthly Budget'!$C$14 | M13: ='Monthly Budget'!$C$23 | N13: ='Monthly Budget'!$C$27 | O13: =L13+M13+N13 | P13: =K13-O13 | Q13: =Q12+P13 | R13: =IF(COUNTIFS('Certificate Ladder'!$B$8:$B$40,">="&EOMONTH(A13,-1)+1,'Certificate Ladder'!$B$8:$B$40,"<="&A13)>0,Inputs!$C$59,0)
A14: =EOMONTH(A13,1) | B14: =COUNTIFS('Draw Recovery'!$B$9:$B$116,">="&EOMONTH(A14,-1)+1,'Draw Recovery'!$B$9:$B$116,"<="&A14) | C14: =B14*Inputs!$C$12 | D14: =IF(SUMIFS('Deal Log'!$G$8:$G$257,'Deal Log'!$L$8:$L$257,A14,'Deal Log'!$I$8:$I$257,"Funded")+SUMIFS('Deal Log'!$K$8:$K$257,'Deal Log'!$L$8:$L$257,A14,'Deal Log'!$I$8:$I$257,"Locked")+SUMIFS('Deal Log'!$K$8:$K$257,'Deal Log'!$L$8:$L$257,A14,'Deal Log'!$I$8:$I$257,"Pre-App")>0,SUMIFS('Deal Log'!$G$8:$G$257,'Deal Log'!$L$8:$L$257,A14,'Deal Log'!$I$8:$I$257,"Funded")+SUMIFS('Deal Log'!$K$8:$K$257,'Deal Log'!$L$8:$L$257,A14,'Deal Log'!$I$8:$I$257,"Locked")+SUMIFS('Deal Log'!$K$8:$K$257,'Deal Log'!$L$8:$L$257,A14,'Deal Log'!$I$8:$I$257,"Pre-App"),Inputs!$C$101) | E14: =H13 | F14: =IF(Inputs!$C$17="Yes",C14,0)+IF(Inputs!$C$19="Recoverable",Inputs!$C$34,0) | G14: =MIN(E14+F14,D14) | H14: =MAX(0,E14+F14-D14) | I14: =IF(Inputs!$C$17="Yes",C14+MAX(0,D14-(E14+F14)),IF(Inputs!$C$18="Stacked",C14+D14,MAX(C14,D14))) | J14: =IF(Inputs!$C$20="1099",I14*Inputs!$C$74,0) | K14: =I14-J14 | L14: ='Monthly Budget'!$C$14 | M14: ='Monthly Budget'!$C$23 | N14: ='Monthly Budget'!$C$27 | O14: =L14+M14+N14 | P14: =K14-O14 | Q14: =Q13+P14 | R14: =IF(COUNTIFS('Certificate Ladder'!$B$8:$B$40,">="&EOMONTH(A14,-1)+1,'Certificate Ladder'!$B$8:$B$40,"<="&A14)>0,Inputs!$C$59,0)
A15: =EOMONTH(A14,1) | B15: =COUNTIFS('Draw Recovery'!$B$9:$B$116,">="&EOMONTH(A15,-1)+1,'Draw Recovery'!$B$9:$B$116,"<="&A15) | C15: =B15*Inputs!$C$12 | D15: =IF(SUMIFS('Deal Log'!$G$8:$G$257,'Deal Log'!$L$8:$L$257,A15,'Deal Log'!$I$8:$I$257,"Funded")+SUMIFS('Deal Log'!$K$8:$K$257,'Deal Log'!$L$8:$L$257,A15,'Deal Log'!$I$8:$I$257,"Locked")+SUMIFS('Deal Log'!$K$8:$K$257,'Deal Log'!$L$8:$L$257,A15,'Deal Log'!$I$8:$I$257,"Pre-App")>0,SUMIFS('Deal Log'!$G$8:$G$257,'Deal Log'!$L$8:$L$257,A15,'Deal Log'!$I$8:$I$257,"Funded")+SUMIFS('Deal Log'!$K$8:$K$257,'Deal Log'!$L$8:$L$257,A15,'Deal Log'!$I$8:$I$257,"Locked")+SUMIFS('Deal Log'!$K$8:$K$257,'Deal Log'!$L$8:$L$257,A15,'Deal Log'!$I$8:$I$257,"Pre-App"),Inputs!$C$101) | E15: =H14 | F15: =IF(Inputs!$C$17="Yes",C15,0)+IF(Inputs!$C$19="Recoverable",Inputs!$C$34,0) | G15: =MIN(E15+F15,D15) | H15: =MAX(0,E15+F15-D15) | I15: =IF(Inputs!$C$17="Yes",C15+MAX(0,D15-(E15+F15)),IF(Inputs!$C$18="Stacked",C15+D15,MAX(C15,D15))) | J15: =IF(Inputs!$C$20="1099",I15*Inputs!$C$74,0) | K15: =I15-J15 | L15: ='Monthly Budget'!$C$14 | M15: ='Monthly Budget'!$C$23 | N15: ='Monthly Budget'!$C$27 | O15: =L15+M15+N15 | P15: =K15-O15 | Q15: =Q14+P15 | R15: =IF(COUNTIFS('Certificate Ladder'!$B$8:$B$40,">="&EOMONTH(A15,-1)+1,'Certificate Ladder'!$B$8:$B$40,"<="&A15)>0,Inputs!$C$59,0)
A16: =EOMONTH(A15,1) | B16: =COUNTIFS('Draw Recovery'!$B$9:$B$116,">="&EOMONTH(A16,-1)+1,'Draw Recovery'!$B$9:$B$116,"<="&A16) | C16: =B16*Inputs!$C$12 | D16: =IF(SUMIFS('Deal Log'!$G$8:$G$257,'Deal Log'!$L$8:$L$257,A16,'Deal Log'!$I$8:$I$257,"Funded")+SUMIFS('Deal Log'!$K$8:$K$257,'Deal Log'!$L$8:$L$257,A16,'Deal Log'!$I$8:$I$257,"Locked")+SUMIFS('Deal Log'!$K$8:$K$257,'Deal Log'!$L$8:$L$257,A16,'Deal Log'!$I$8:$I$257,"Pre-App")>0,SUMIFS('Deal Log'!$G$8:$G$257,'Deal Log'!$L$8:$L$257,A16,'Deal Log'!$I$8:$I$257,"Funded")+SUMIFS('Deal Log'!$K$8:$K$257,'Deal Log'!$L$8:$L$257,A16,'Deal Log'!$I$8:$I$257,"Locked")+SUMIFS('Deal Log'!$K$8:$K$257,'Deal Log'!$L$8:$L$257,A16,'Deal Log'!$I$8:$I$257,"Pre-App"),Inputs!$C$101) | E16: =H15 | F16: =IF(Inputs!$C$17="Yes",C16,0)+IF(Inputs!$C$19="Recoverable",Inputs!$C$34,0) | G16: =MIN(E16+F16,D16) | H16: =MAX(0,E16+F16-D16) | I16: =IF(Inputs!$C$17="Yes",C16+MAX(0,D16-(E16+F16)),IF(Inputs!$C$18="Stacked",C16+D16,MAX(C16,D16))) | J16: =IF(Inputs!$C$20="1099",I16*Inputs!$C$74,0) | K16: =I16-J16 | L16: ='Monthly Budget'!$C$14 | M16: ='Monthly Budget'!$C$23 | N16: ='Monthly Budget'!$C$27 | O16: =L16+M16+N16 | P16: =K16-O16 | Q16: =Q15+P16 | R16: =IF(COUNTIFS('Certificate Ladder'!$B$8:$B$40,">="&EOMONTH(A16,-1)+1,'Certificate Ladder'!$B$8:$B$40,"<="&A16)>0,Inputs!$C$59,0)
A17: =EOMONTH(A16,1) | B17: =COUNTIFS('Draw Recovery'!$B$9:$B$116,">="&EOMONTH(A17,-1)+1,'Draw Recovery'!$B$9:$B$116,"<="&A17) | C17: =B17*Inputs!$C$12 | D17: =IF(SUMIFS('Deal Log'!$G$8:$G$257,'Deal Log'!$L$8:$L$257,A17,'Deal Log'!$I$8:$I$257,"Funded")+SUMIFS('Deal Log'!$K$8:$K$257,'Deal Log'!$L$8:$L$257,A17,'Deal Log'!$I$8:$I$257,"Locked")+SUMIFS('Deal Log'!$K$8:$K$257,'Deal Log'!$L$8:$L$257,A17,'Deal Log'!$I$8:$I$257,"Pre-App")>0,SUMIFS('Deal Log'!$G$8:$G$257,'Deal Log'!$L$8:$L$257,A17,'Deal Log'!$I$8:$I$257,"Funded")+SUMIFS('Deal Log'!$K$8:$K$257,'Deal Log'!$L$8:$L$257,A17,'Deal Log'!$I$8:$I$257,"Locked")+SUMIFS('Deal Log'!$K$8:$K$257,'Deal Log'!$L$8:$L$257,A17,'Deal Log'!$I$8:$I$257,"Pre-App"),Inputs!$C$101) | E17: =H16 | F17: =IF(Inputs!$C$17="Yes",C17,0)+IF(Inputs!$C$19="Recoverable",Inputs!$C$34,0) | G17: =MIN(E17+F17,D17) | H17: =MAX(0,E17+F17-D17) | I17: =IF(Inputs!$C$17="Yes",C17+MAX(0,D17-(E17+F17)),IF(Inputs!$C$18="Stacked",C17+D17,MAX(C17,D17))) | J17: =IF(Inputs!$C$20="1099",I17*Inputs!$C$74,0) | K17: =I17-J17 | L17: ='Monthly Budget'!$C$14 | M17: ='Monthly Budget'!$C$23 | N17: ='Monthly Budget'!$C$27 | O17: =L17+M17+N17 | P17: =K17-O17 | Q17: =Q16+P17 | R17: =IF(COUNTIFS('Certificate Ladder'!$B$8:$B$40,">="&EOMONTH(A17,-1)+1,'Certificate Ladder'!$B$8:$B$40,"<="&A17)>0,Inputs!$C$59,0)
A18: =EOMONTH(A17,1) | B18: =COUNTIFS('Draw Recovery'!$B$9:$B$116,">="&EOMONTH(A18,-1)+1,'Draw Recovery'!$B$9:$B$116,"<="&A18) | C18: =B18*Inputs!$C$12 | D18: =IF(SUMIFS('Deal Log'!$G$8:$G$257,'Deal Log'!$L$8:$L$257,A18,'Deal Log'!$I$8:$I$257,"Funded")+SUMIFS('Deal Log'!$K$8:$K$257,'Deal Log'!$L$8:$L$257,A18,'Deal Log'!$I$8:$I$257,"Locked")+SUMIFS('Deal Log'!$K$8:$K$257,'Deal Log'!$L$8:$L$257,A18,'Deal Log'!$I$8:$I$257,"Pre-App")>0,SUMIFS('Deal Log'!$G$8:$G$257,'Deal Log'!$L$8:$L$257,A18,'Deal Log'!$I$8:$I$257,"Funded")+SUMIFS('Deal Log'!$K$8:$K$257,'Deal Log'!$L$8:$L$257,A18,'Deal Log'!$I$8:$I$257,"Locked")+SUMIFS('Deal Log'!$K$8:$K$257,'Deal Log'!$L$8:$L$257,A18,'Deal Log'!$I$8:$I$257,"Pre-App"),Inputs!$C$101) | E18: =H17 | F18: =IF(Inputs!$C$17="Yes",C18,0)+IF(Inputs!$C$19="Recoverable",Inputs!$C$34,0) | G18: =MIN(E18+F18,D18) | H18: =MAX(0,E18+F18-D18) | I18: =IF(Inputs!$C$17="Yes",C18+MAX(0,D18-(E18+F18)),IF(Inputs!$C$18="Stacked",C18+D18,MAX(C18,D18))) | J18: =IF(Inputs!$C$20="1099",I18*Inputs!$C$74,0) | K18: =I18-J18 | L18: ='Monthly Budget'!$C$14 | M18: ='Monthly Budget'!$C$23 | N18: ='Monthly Budget'!$C$27 | O18: =L18+M18+N18 | P18: =K18-O18 | Q18: =Q17+P18 | R18: =IF(COUNTIFS('Certificate Ladder'!$B$8:$B$40,">="&EOMONTH(A18,-1)+1,'Certificate Ladder'!$B$8:$B$40,"<="&A18)>0,Inputs!$C$59,0)
A19: =EOMONTH(A18,1) | B19: =COUNTIFS('Draw Recovery'!$B$9:$B$116,">="&EOMONTH(A19,-1)+1,'Draw Recovery'!$B$9:$B$116,"<="&A19) | C19: =B19*Inputs!$C$12 | D19: =IF(SUMIFS('Deal Log'!$G$8:$G$257,'Deal Log'!$L$8:$L$257,A19,'Deal Log'!$I$8:$I$257,"Funded")+SUMIFS('Deal Log'!$K$8:$K$257,'Deal Log'!$L$8:$L$257,A19,'Deal Log'!$I$8:$I$257,"Locked")+SUMIFS('Deal Log'!$K$8:$K$257,'Deal Log'!$L$8:$L$257,A19,'Deal Log'!$I$8:$I$257,"Pre-App")>0,SUMIFS('Deal Log'!$G$8:$G$257,'Deal Log'!$L$8:$L$257,A19,'Deal Log'!$I$8:$I$257,"Funded")+SUMIFS('Deal Log'!$K$8:$K$257,'Deal Log'!$L$8:$L$257,A19,'Deal Log'!$I$8:$I$257,"Locked")+SUMIFS('Deal Log'!$K$8:$K$257,'Deal Log'!$L$8:$L$257,A19,'Deal Log'!$I$8:$I$257,"Pre-App"),Inputs!$C$101) | E19: =H18 | F19: =IF(Inputs!$C$17="Yes",C19,0)+IF(Inputs!$C$19="Recoverable",Inputs!$C$34,0) | G19: =MIN(E19+F19,D19) | H19: =MAX(0,E19+F19-D19) | I19: =IF(Inputs!$C$17="Yes",C19+MAX(0,D19-(E19+F19)),IF(Inputs!$C$18="Stacked",C19+D19,MAX(C19,D19))) | J19: =IF(Inputs!$C$20="1099",I19*Inputs!$C$74,0) | K19: =I19-J19 | L19: ='Monthly Budget'!$C$14 | M19: ='Monthly Budget'!$C$23 | N19: ='Monthly Budget'!$C$27 | O19: =L19+M19+N19 | P19: =K19-O19 | Q19: =Q18+P19 | R19: =IF(COUNTIFS('Certificate Ladder'!$B$8:$B$40,">="&EOMONTH(A19,-1)+1,'Certificate Ladder'!$B$8:$B$40,"<="&A19)>0,Inputs!$C$59,0)
A20: =EOMONTH(A19,1) | B20: =COUNTIFS('Draw Recovery'!$B$9:$B$116,">="&EOMONTH(A20,-1)+1,'Draw Recovery'!$B$9:$B$116,"<="&A20) | C20: =B20*Inputs!$C$12 | D20: =IF(SUMIFS('Deal Log'!$G$8:$G$257,'Deal Log'!$L$8:$L$257,A20,'Deal Log'!$I$8:$I$257,"Funded")+SUMIFS('Deal Log'!$K$8:$K$257,'Deal Log'!$L$8:$L$257,A20,'Deal Log'!$I$8:$I$257,"Locked")+SUMIFS('Deal Log'!$K$8:$K$257,'Deal Log'!$L$8:$L$257,A20,'Deal Log'!$I$8:$I$257,"Pre-App")>0,SUMIFS('Deal Log'!$G$8:$G$257,'Deal Log'!$L$8:$L$257,A20,'Deal Log'!$I$8:$I$257,"Funded")+SUMIFS('Deal Log'!$K$8:$K$257,'Deal Log'!$L$8:$L$257,A20,'Deal Log'!$I$8:$I$257,"Locked")+SUMIFS('Deal Log'!$K$8:$K$257,'Deal Log'!$L$8:$L$257,A20,'Deal Log'!$I$8:$I$257,"Pre-App"),Inputs!$C$101) | E20: =H19 | F20: =IF(Inputs!$C$17="Yes",C20,0)+IF(Inputs!$C$19="Recoverable",Inputs!$C$34,0) | G20: =MIN(E20+F20,D20) | H20: =MAX(0,E20+F20-D20) | I20: =IF(Inputs!$C$17="Yes",C20+MAX(0,D20-(E20+F20)),IF(Inputs!$C$18="Stacked",C20+D20,MAX(C20,D20))) | J20: =IF(Inputs!$C$20="1099",I20*Inputs!$C$74,0) | K20: =I20-J20 | L20: ='Monthly Budget'!$C$14 | M20: ='Monthly Budget'!$C$23 | N20: ='Monthly Budget'!$C$27 | O20: =L20+M20+N20 | P20: =K20-O20 | Q20: =Q19+P20 | R20: =IF(COUNTIFS('Certificate Ladder'!$B$8:$B$40,">="&EOMONTH(A20,-1)+1,'Certificate Ladder'!$B$8:$B$40,"<="&A20)>0,Inputs!$C$59,0)
A21: =EOMONTH(A20,1) | B21: =COUNTIFS('Draw Recovery'!$B$9:$B$116,">="&EOMONTH(A21,-1)+1,'Draw Recovery'!$B$9:$B$116,"<="&A21) | C21: =B21*Inputs!$C$12 | D21: =IF(SUMIFS('Deal Log'!$G$8:$G$257,'Deal Log'!$L$8:$L$257,A21,'Deal Log'!$I$8:$I$257,"Funded")+SUMIFS('Deal Log'!$K$8:$K$257,'Deal Log'!$L$8:$L$257,A21,'Deal Log'!$I$8:$I$257,"Locked")+SUMIFS('Deal Log'!$K$8:$K$257,'Deal Log'!$L$8:$L$257,A21,'Deal Log'!$I$8:$I$257,"Pre-App")>0,SUMIFS('Deal Log'!$G$8:$G$257,'Deal Log'!$L$8:$L$257,A21,'Deal Log'!$I$8:$I$257,"Funded")+SUMIFS('Deal Log'!$K$8:$K$257,'Deal Log'!$L$8:$L$257,A21,'Deal Log'!$I$8:$I$257,"Locked")+SUMIFS('Deal Log'!$K$8:$K$257,'Deal Log'!$L$8:$L$257,A21,'Deal Log'!$I$8:$I$257,"Pre-App"),Inputs!$C$101) | E21: =H20 | F21: =IF(Inputs!$C$17="Yes",C21,0)+IF(Inputs!$C$19="Recoverable",Inputs!$C$34,0) | G21: =MIN(E21+F21,D21) | H21: =MAX(0,E21+F21-D21) | I21: =IF(Inputs!$C$17="Yes",C21+MAX(0,D21-(E21+F21)),IF(Inputs!$C$18="Stacked",C21+D21,MAX(C21,D21))) | J21: =IF(Inputs!$C$20="1099",I21*Inputs!$C$74,0) | K21: =I21-J21 | L21: ='Monthly Budget'!$C$14 | M21: ='Monthly Budget'!$C$23 | N21: ='Monthly Budget'!$C$27 | O21: =L21+M21+N21 | P21: =K21-O21 | Q21: =Q20+P21 | R21: =IF(COUNTIFS('Certificate Ladder'!$B$8:$B$40,">="&EOMONTH(A21,-1)+1,'Certificate Ladder'!$B$8:$B$40,"<="&A21)>0,Inputs!$C$59,0)
... A44: =EOMONTH(A43,1) | B44: =COUNTIFS('Draw Recovery'!$B$9:$B$116,">="&EOMONTH(A44,-1)+1,'Draw Recovery'!$B$9:$B$116,"<="&A44) | C44: =B44*Inputs!$C$12 | D44: =IF(SUMIFS('Deal Log'!$G$8:$G$257,'Deal Log'!$L$8:$L$257,A44,'Deal Log'!$I$8:$I$257,"Funded")+SUMIFS('Deal Log'!$K$8:$K$257,'Deal Log'!$L$8:$L$257,A44,'Deal Log'!$I$8:$I$257,"Locked")+SUMIFS('Deal Log'!$K$8:$K$257,'Deal Log'!$L$8:$L$257,A44,'Deal Log'!$I$8:$I$257,"Pre-App")>0,SUMIFS('Deal Log'!$G$8:$G$257,'Deal Log'!$L$8:$L$257,A44,'Deal Log'!$I$8:$I$257,"Funded")+SUMIFS('Deal Log'!$K$8:$K$257,'Deal Log'!$L$8:$L$257,A44,'Deal Log'!$I$8:$I$257,"Locked")+SUMIFS('Deal Log'!$K$8:$K$257,'Deal Log'!$L$8:$L$257,A44,'Deal Log'!$I$8:$I$257,"Pre-App"),Inputs!$C$101) | E44: =H43 | F44: =IF(Inputs!$C$17="Yes",C44,0)+IF(Inputs!$C$19="Recoverable",Inputs!$C$34,0) | G44: =MIN(E44+F44,D44) | H44: =MAX(0,E44+F44-D44) | I44: =IF(Inputs!$C$17="Yes",C44+MAX(0,D44-(E44+F44)),IF(Inputs!$C$18="Stacked",C44+D44,MAX(C44,D44))) | J44: =IF(Inputs!$C$20="1099",I44*Inputs!$C$74,0) | K44: =I44-J44 | L44: ='Monthly Budget'!$C$14 | M44: ='Monthly Budget'!$C$23 | N44: ='Monthly Budget'!$C$27 | O44: =L44+M44+N44 | P44: =K44-O44 | Q44: =Q43+P44 | R44: =IF(COUNTIFS('Certificate Ladder'!$B$8:$B$40,">="&EOMONTH(A44,-1)+1,'Certificate Ladder'!$B$8:$B$40,"<="&A44)>0,Inputs!$C$59,0)
A45: 36-MO TOTAL | C45: =SUM(C$9:C$44) | D45: =SUM(D$9:D$44) | I45: =SUM(I$9:I$44) | J45: =SUM(J$9:J$44) | K45: =SUM(K$9:K$44) | L45: =SUM(L$9:L$44) | M45: =SUM(M$9:M$44) | N45: =SUM(N$9:N$44) | O45: =SUM(O$9:O$44) | P45: =SUM(P$9:P$44) | R45: =SUM(R$9:R$44)

Sheet Bill Calendar
A1: BILL CALENDAR — a typical month, day by day
A2: Your draws land on the 15th and the last day. Your bills cluster on the 1st, 7th and 14th. This sheet shows the squeeze that creates.
A4: Starting checking balance: | C4: =Inputs!$C$51 | D4: Lowest point in the month -> | F4: =MIN(F9:F39)
A5: !! The gap that hurts: the month-end draw has to carry Prime (1st), the credit card (7th) and the car payment (14th) before the next draw arrives on the 15th.
A6: ="Those three bills total "&TEXT(Inputs!$C$32+Inputs!$C$65+Inputs!$C$28,"$#,##0.00")&" against a single draw of "&TEXT(Inputs!$C$12,"$#,##0.00")&" - leaving "&TEXT(Inputs!$C$12-Inputs!$C$32-Inputs!$C$65-Inputs!$C$28,"$#,##0.00")&" for fuel, food and everything else for two weeks."
A8: Day | B8: Event | C8: Money in | D8: Money out | E8: Running balance | F8: Cumulative out | G8: Note
A9: 1 | B9: Amazon Prime | D9: =Inputs!$C$32+(Inputs!$C$43+Inputs!$C$46+Inputs!$C$47+Inputs!$C$48+Inputs!$C$49+Inputs!$C$35+Inputs!$C$36+Inputs!$C$37+Inputs!$C$38)/30 | E9: =$C$4+C9-D9 | F9: =D9 | G9: Switch to the annual plan and this becomes ~$11.58/mo.
A10: 2 | B10: (daily living) | D10: =(Inputs!$C$43+Inputs!$C$46+Inputs!$C$47+Inputs!$C$48+Inputs!$C$49+Inputs!$C$35+Inputs!$C$36+Inputs!$C$37+Inputs!$C$38)/30 | E10: =E9+C10-D10 | F10: =F9+D10
A11: 3 | B11: (daily living) | D11: =(Inputs!$C$43+Inputs!$C$46+Inputs!$C$47+Inputs!$C$48+Inputs!$C$49+Inputs!$C$35+Inputs!$C$36+Inputs!$C$37+Inputs!$C$38)/30 | E11: =E10+C11-D11 | F11: =F10+D11
A12: 4 | B12: (daily living) | D12: =(Inputs!$C$43+Inputs!$C$46+Inputs!$C$47+Inputs!$C$48+Inputs!$C$49+Inputs!$C$35+Inputs!$C$36+Inputs!$C$37+Inputs!$C$38)/30 | E12: =E11+C12-D12 | F12: =F11+D12
A13: 5 | B13: (daily living) | D13: =(Inputs!$C$43+Inputs!$C$46+Inputs!$C$47+Inputs!$C$48+Inputs!$C$49+Inputs!$C$35+Inputs!$C$36+Inputs!$C$37+Inputs!$C$38)/30 | E13: =E12+C13-D13 | F13: =F12+D13
A14: 6 | B14: (daily living) | D14: =(Inputs!$C$43+Inputs!$C$46+Inputs!$C$47+Inputs!$C$48+Inputs!$C$49+Inputs!$C$35+Inputs!$C$36+Inputs!$C$37+Inputs!$C$38)/30 | E14: =E13+C14-D14 | F14: =F13+D14
A15: 7 | B15: Credit card payment (full) | D15: =Inputs!$C$65+(Inputs!$C$43+Inputs!$C$46+Inputs!$C$47+Inputs!$C$48+Inputs!$C$49+Inputs!$C$35+Inputs!$C$36+Inputs!$C$37+Inputs!$C$38)/30 | E15: =E14+C15-D15 | F15: =F14+D15 | G15: Pay the FULL statement balance. Never the minimum, never a partial.
A16: 8 | B16: (daily living) | D16: =(Inputs!$C$43+Inputs!$C$46+Inputs!$C$47+Inputs!$C$48+Inputs!$C$49+Inputs!$C$35+Inputs!$C$36+Inputs!$C$37+Inputs!$C$38)/30 | E16: =E15+C16-D16 | F16: =F15+D16
A17: 9 | B17: (daily living) | D17: =(Inputs!$C$43+Inputs!$C$46+Inputs!$C$47+Inputs!$C$48+Inputs!$C$49+Inputs!$C$35+Inputs!$C$36+Inputs!$C$37+Inputs!$C$38)/30 | E17: =E16+C17-D17 | F17: =F16+D17
A18: 10 | B18: (daily living) | D18: =(Inputs!$C$43+Inputs!$C$46+Inputs!$C$47+Inputs!$C$48+Inputs!$C$49+Inputs!$C$35+Inputs!$C$36+Inputs!$C$37+Inputs!$C$38)/30 | E18: =E17+C18-D18 | F18: =F17+D18
A19: 11 | B19: (daily living) | D19: =(Inputs!$C$43+Inputs!$C$46+Inputs!$C$47+Inputs!$C$48+Inputs!$C$49+Inputs!$C$35+Inputs!$C$36+Inputs!$C$37+Inputs!$C$38)/30 | E19: =E18+C19-D19 | F19: =F18+D19
A20: 12 | B20: (daily living) | D20: =(Inputs!$C$43+Inputs!$C$46+Inputs!$C$47+Inputs!$C$48+Inputs!$C$49+Inputs!$C$35+Inputs!$C$36+Inputs!$C$37+Inputs!$C$38)/30 | E20: =E19+C20-D20 | F20: =F19+D20
A21: 13 | B21: (daily living) | D21: =(Inputs!$C$43+Inputs!$C$46+Inputs!$C$47+Inputs!$C$48+Inputs!$C$49+Inputs!$C$35+Inputs!$C$36+Inputs!$C$37+Inputs!$C$38)/30 | E21: =E20+C21-D21 | F21: =F20+D21
A22: 14 | B22: Auto loan payment | D22: =Inputs!$C$28+(Inputs!$C$43+Inputs!$C$46+Inputs!$C$47+Inputs!$C$48+Inputs!$C$49+Inputs!$C$35+Inputs!$C$36+Inputs!$C$37+Inputs!$C$38)/30 | E22: =E21+C22-D22 | F22: =F21+D22 | G22: The big one, and it lands the day BEFORE your draw.
A23: 15 | B23: DRAW #1 + Gym (mid-month) | C23: =Inputs!$C$12 | D23: =Inputs!$C$30+(Inputs!$C$43+Inputs!$C$46+Inputs!$C$47+Inputs!$C$48+Inputs!$C$49+Inputs!$C$35+Inputs!$C$36+Inputs!$C$37+Inputs!$C$38)/30 | E23: =E22+C23-D23 | F23: =F22+D23 | G23: Semi-monthly. Shifts back to Friday if the 15th is a weekend.
A24: 16 | B24: (daily living) | D24: =(Inputs!$C$43+Inputs!$C$46+Inputs!$C$47+Inputs!$C$48+Inputs!$C$49+Inputs!$C$35+Inputs!$C$36+Inputs!$C$37+Inputs!$C$38)/30 | E24: =E23+C24-D24 | F24: =F23+D24
A25: 17 | B25: (daily living) | D25: =(Inputs!$C$43+Inputs!$C$46+Inputs!$C$47+Inputs!$C$48+Inputs!$C$49+Inputs!$C$35+Inputs!$C$36+Inputs!$C$37+Inputs!$C$38)/30 | E25: =E24+C25-D25 | F25: =F24+D25
A26: 18 | B26: (daily living) | D26: =(Inputs!$C$43+Inputs!$C$46+Inputs!$C$47+Inputs!$C$48+Inputs!$C$49+Inputs!$C$35+Inputs!$C$36+Inputs!$C$37+Inputs!$C$38)/30 | E26: =E25+C26-D26 | F26: =F25+D26
A27: 19 | B27: (daily living) | D27: =(Inputs!$C$43+Inputs!$C$46+Inputs!$C$47+Inputs!$C$48+Inputs!$C$49+Inputs!$C$35+Inputs!$C$36+Inputs!$C$37+Inputs!$C$38)/30 | E27: =E26+C27-D27 | F27: =F26+D27
A28: 20 | B28: (daily living) | D28: =(Inputs!$C$43+Inputs!$C$46+Inputs!$C$47+Inputs!$C$48+Inputs!$C$49+Inputs!$C$35+Inputs!$C$36+Inputs!$C$37+Inputs!$C$38)/30 | E28: =E27+C28-D28 | F28: =F27+D28
A29: 21 | B29: (daily living) | D29: =(Inputs!$C$43+Inputs!$C$46+Inputs!$C$47+Inputs!$C$48+Inputs!$C$49+Inputs!$C$35+Inputs!$C$36+Inputs!$C$37+Inputs!$C$38)/30 | E29: =E28+C29-D29 | F29: =F28+D29
A30: 22 | B30: (daily living) | D30: =(Inputs!$C$43+Inputs!$C$46+Inputs!$C$47+Inputs!$C$48+Inputs!$C$49+Inputs!$C$35+Inputs!$C$36+Inputs!$C$37+Inputs!$C$38)/30 | E30: =E29+C30-D30 | F30: =F29+D30
A31: 23 | B31: (daily living) | D31: =(Inputs!$C$43+Inputs!$C$46+Inputs!$C$47+Inputs!$C$48+Inputs!$C$49+Inputs!$C$35+Inputs!$C$36+Inputs!$C$37+Inputs!$C$38)/30 | E31: =E30+C31-D31 | F31: =F30+D31
A32: 24 | B32: (daily living) | D32: =(Inputs!$C$43+Inputs!$C$46+Inputs!$C$47+Inputs!$C$48+Inputs!$C$49+Inputs!$C$35+Inputs!$C$36+Inputs!$C$37+Inputs!$C$38)/30 | E32: =E31+C32-D32 | F32: =F31+D32
A33: 25 | B33: (daily living) | D33: =(Inputs!$C$43+Inputs!$C$46+Inputs!$C$47+Inputs!$C$48+Inputs!$C$49+Inputs!$C$35+Inputs!$C$36+Inputs!$C$37+Inputs!$C$38)/30 | E33: =E32+C33-D33 | F33: =F32+D33
A34: 26 | B34: (daily living) | D34: =(Inputs!$C$43+Inputs!$C$46+Inputs!$C$47+Inputs!$C$48+Inputs!$C$49+Inputs!$C$35+Inputs!$C$36+Inputs!$C$37+Inputs!$C$38)/30 | E34: =E33+C34-D34 | F34: =F33+D34
A35: 27 | B35: (daily living) | D35: =(Inputs!$C$43+Inputs!$C$46+Inputs!$C$47+Inputs!$C$48+Inputs!$C$49+Inputs!$C$35+Inputs!$C$36+Inputs!$C$37+Inputs!$C$38)/30 | E35: =E34+C35-D35 | F35: =F34+D35
... A37: 29 | B37: (daily living) | D37: =(Inputs!$C$43+Inputs!$C$46+Inputs!$C$47+Inputs!$C$48+Inputs!$C$49+Inputs!$C$35+Inputs!$C$36+Inputs!$C$37+Inputs!$C$38)/30 | E37: =E36+C37-D37 | F37: =F36+D37
A38: 30 | B38: DRAW #2 (last day of month) + Gym (month-end) | C38: =Inputs!$C$12 | D38: =Inputs!$C$30+(Inputs!$C$43+Inputs!$C$46+Inputs!$C$47+Inputs!$C$48+Inputs!$C$49+Inputs!$C$35+Inputs!$C$36+Inputs!$C$37+Inputs!$C$38)/30 | E38: =E37+C38-D38 | F38: =F37+D38 | G38: Month-end draw. This is the one that has to stretch across the 1st, 7th and 14th.
B40: Red in the running-balance column means you overdraft. If you see red, the fix is on 'Recommendations' item #1: build the checking cushion first.

Sheet Allocation Engine
A1: ALLOCATION ENGINE — "a commission check just hit. Where does it go?"
A2: Type the gross commission in the blue cell. The sheet splits it for you using the live state of your accounts.
B5: GROSS COMMISSION RECEIVED | C5: 2250 | D5: <- type here | F5: Example: a $300,000 loan at 75 bps.
A7: STEP 1 — OFF THE TOP, BEFORE YOU LOOK AT THE NUMBER
B8: Taxes (separate account, same day) | C8: =IF(Inputs!$C$20="1099",$C$5*Inputs!$C$74,0) | F8: 1099 only. This money was never yours. The single most common way commission earners blow up is spending the IRS's share in Q1 and finding out in April.
B9: Advance repayment withheld by the owner | C9: =IF(Inputs!$C$17="Yes",MIN($C$5-C9,'Cash Flow'!$E$4),0) | F9: If the draw is recoverable this is taken before you see the check. Shown here so the number on your deposit slip is not a surprise.
B10: =NET LANDING IN YOUR ACCOUNT | C10: =$C$5-C9-C10
A12: STEP 2 — THE WATERFALL (in this order, every time)
B13: Priority | C13: Amount | D13: Running remainder | F13: Why this order
B14: 1. Top checking back up to its cushion | C14: =MIN($C$10,MAX(0,Inputs!$C$52-Inputs!$C$51)) | D14: =$C$10-C14 | F14: You are at $395.40 with $865.84 of bills due in the next week. Fix this first, every time.
B15: 2. Fill the emergency fund to target | C15: =MIN(D14,MAX(0,$C$5*0+'Accounts'!$C$5-Inputs!$C$53)) | D15: =D14-C15 | F15: 9 months of burn. Nothing below this line gets a dollar until this is full - your income is lumpy and your draw may be clawable.
B16: 3. Roth IRA (to the annual limit) | C16: =MIN(D15,D15*Inputs!$C$87/(Inputs!$C$87+Inputs!$C$88+Inputs!$C$89+Inputs!$C$90+Inputs!$C$91)) | D16: =D15-C16 | F16: You are 25 with $0 invested. Every year you skip is the most expensive year you will ever skip - see 'Retirement'.
B17: 4. Ring / special savings | C17: =D16*Inputs!$C$88/(Inputs!$C$87+Inputs!$C$88+Inputs!$C$89+Inputs!$C$90+Inputs!$C$91) | D17: =D16-C17 | F17: Dated goal, ~24 months out. Keep it in cash - never invest money you need inside 3 years.
B18: 5. House down payment fund | C18: =D17*Inputs!$C$89/(Inputs!$C$87+Inputs!$C$88+Inputs!$C$89+Inputs!$C$90+Inputs!$C$91) | D18: =D17-C18 | F18: Separate from the ring so you can see both clocks at once.
B19: 6. Extra principal on the car | C19: =D18*Inputs!$C$90/(Inputs!$C$87+Inputs!$C$88+Inputs!$C$89+Inputs!$C$90+Inputs!$C$91) | D19: =D18-C19 | F19: Only worth it if the auto APR beats your savings APY. Check both on Inputs.
B20: 7. Guilt-free spending | C20: =D19*Inputs!$C$91/(Inputs!$C$87+Inputs!$C$88+Inputs!$C$89+Inputs!$C$90+Inputs!$C$91) | D20: =D19-C20 | F20: Non-negotiable. A budget with no fun in it gets abandoned in about six weeks.
B21: TOTAL ALLOCATED | C21: =SUM(C14:C20) | D21: =IF(ROUND(C21-$C$10,2)=0,"balanced","CHECK - does not tie")

Sheet Accounts
A1: ACCOUNT ROLL-FORWARD — where every dollar of surplus actually lands, month by month
A2: The waterfall: top up checking to its cushion -> fill the emergency fund -> then split by the percentages on Inputs. Interest is credited monthly.
A4: THE WATERFALL: | C4: 1) Checking back to its cushion -> 2) Emergency fund to full (nothing else gets funded until it is) -> 3) split the rest: Roth / Ring / House / Car / Fun
A5: Emergency fund target: | C5: =Inputs!$C$77*'Monthly Budget'!C32 | D5: =Inputs!$C$77&" months of total burn. Held in the HYSA."
C7: CHECKING | H7: HYSA / EMERGENCY FUND | M7: CERTIFICATE | Q7: ROTH IRA | U7: RING / SPECIAL | X7: HOUSE FUND | AA7: OTHER | AC7: TOTALS
A8: Month | B8: Net surplus | C8: Chk open | D8: Chk flow | E8: Chk close | F8: Allocatable | G8: EF target | H8: Open | I8: Interest | J8: EF contrib | K8: Cert transfer | L8: Close | M8: Open | N8: Interest | O8: Roll-in | P8: Close | Q8: Open | R8: Contrib | S8: Growth | T8: Close | U8: Open | V8: Contrib | W8: Close | X8: Open | Y8: Contrib | Z8: Close | AA8: Car extra principal | AB8: Fun money | AC8: TOTAL SAVED & INVESTED | AD8: Auto loan balance | AE8: NET WORTH (liquid)
A9: ='Cash Flow'!A9 | B9: ='Cash Flow'!P9 | C9: =Inputs!$C$51 | D9: =IF(B9<0,B9,MAX(0,MIN(B9,Inputs!$C$52-C9))) | E9: =C9+D9 | F9: =MAX(0,B9-D9) | G9: =$C$5 | H9: =Inputs!$C$53 | I9: =H9*Inputs!$C$54/12 | J9: =IF(H9+I9<G9,MIN(F9,G9-H9-I9),F9*Inputs!$C$86) | K9: ='Cash Flow'!R9 | L9: =MAX(0,H9+I9+J9-K9) | M9: =Inputs!$C$55 | N9: =M9*Inputs!$C$56/12 | O9: =K9 | P9: =M9+N9+O9 | Q9: =Inputs!$C$61 | R9: =IFERROR(MAX(0,F9-J9)*Inputs!$C$87/(Inputs!$C$87+Inputs!$C$88+Inputs!$C$89+Inputs!$C$90+Inputs!$C$91),0) | S9: =Q9*'Retirement'!$C$5/12 | T9: =Q9+R9+S9 | U9: =Inputs!$C$60 | V9: =IFERROR(MAX(0,F9-J9)*Inputs!$C$88/(Inputs!$C$87+Inputs!$C$88+Inputs!$C$89+Inputs!$C$90+Inputs!$C$91),0) | W9: =U9*(1+Inputs!$C$54/12)+V9 | X9: =0 | Y9: =IFERROR(MAX(0,F9-J9)*Inputs!$C$89/(Inputs!$C$87+Inputs!$C$88+Inputs!$C$89+Inputs!$C$90+Inputs!$C$91),0) | Z9: =X9*(1+Inputs!$C$54/12)+Y9 | AA9: =IFERROR(MAX(0,F9-J9)*Inputs!$C$90/(Inputs!$C$87+Inputs!$C$88+Inputs!$C$89+Inputs!$C$90+Inputs!$C$91),0) | AB9: =IFERROR(MAX(0,F9-J9)*Inputs!$C$91/(Inputs!$C$87+Inputs!$C$88+Inputs!$C$89+Inputs!$C$90+Inputs!$C$91),0) | AC9: =E9+L9+P9+T9+W9+Z9 | AD9: ='Car Loan'!H10 | AE9: =AC9-AD9
A10: ='Cash Flow'!A10 | B10: ='Cash Flow'!P10 | C10: =E9 | D10: =IF(B10<0,B10,MAX(0,MIN(B10,Inputs!$C$52-C10))) | E10: =C10+D10 | F10: =MAX(0,B10-D10) | G10: =$C$5 | H10: =L9 | I10: =H10*Inputs!$C$54/12 | J10: =IF(H10+I10<G10,MIN(F10,G10-H10-I10),F10*Inputs!$C$86) | K10: ='Cash Flow'!R10 | L10: =MAX(0,H10+I10+J10-K10) | M10: =P9 | N10: =M10*Inputs!$C$56/12 | O10: =K10 | P10: =M10+N10+O10 | Q10: =T9 | R10: =IFERROR(MAX(0,F10-J10)*Inputs!$C$87/(Inputs!$C$87+Inputs!$C$88+Inputs!$C$89+Inputs!$C$90+Inputs!$C$91),0) | S10: =Q10*'Retirement'!$C$5/12 | T10: =Q10+R10+S10 | U10: =W9 | V10: =IFERROR(MAX(0,F10-J10)*Inputs!$C$88/(Inputs!$C$87+Inputs!$C$88+Inputs!$C$89+Inputs!$C$90+Inputs!$C$91),0) | W10: =U10*(1+Inputs!$C$54/12)+V10 | X10: =Z9 | Y10: =IFERROR(MAX(0,F10-J10)*Inputs!$C$89/(Inputs!$C$87+Inputs!$C$88+Inputs!$C$89+Inputs!$C$90+Inputs!$C$91),0) | Z10: =X10*(1+Inputs!$C$54/12)+Y10 | AA10: =IFERROR(MAX(0,F10-J10)*Inputs!$C$90/(Inputs!$C$87+Inputs!$C$88+Inputs!$C$89+Inputs!$C$90+Inputs!$C$91),0) | AB10: =IFERROR(MAX(0,F10-J10)*Inputs!$C$91/(Inputs!$C$87+Inputs!$C$88+Inputs!$C$89+Inputs!$C$90+Inputs!$C$91),0) | AC10: =E10+L10+P10+T10+W10+Z10 | AD10: ='Car Loan'!H11 | AE10: =AC10-AD10
A11: ='Cash Flow'!A11 | B11: ='Cash Flow'!P11 | C11: =E10 | D11: =IF(B11<0,B11,MAX(0,MIN(B11,Inputs!$C$52-C11))) | E11: =C11+D11 | F11: =MAX(0,B11-D11) | G11: =$C$5 | H11: =L10 | I11: =H11*Inputs!$C$54/12 | J11: =IF(H11+I11<G11,MIN(F11,G11-H11-I11),F11*Inputs!$C$86) | K11: ='Cash Flow'!R11 | L11: =MAX(0,H11+I11+J11-K11) | M11: =P10 | N11: =M11*Inputs!$C$56/12 | O11: =K11 | P11: =M11+N11+O11 | Q11: =T10 | R11: =IFERROR(MAX(0,F11-J11)*Inputs!$C$87/(Inputs!$C$87+Inputs!$C$88+Inputs!$C$89+Inputs!$C$90+Inputs!$C$91),0) | S11: =Q11*'Retirement'!$C$5/12 | T11: =Q11+R11+S11 | U11: =W10 | V11: =IFERROR(MAX(0,F11-J11)*Inputs!$C$88/(Inputs!$C$87+Inputs!$C$88+Inputs!$C$89+Inputs!$C$90+Inputs!$C$91),0) | W11: =U11*(1+Inputs!$C$54/12)+V11 | X11: =Z10 | Y11: =IFERROR(MAX(0,F11-J11)*Inputs!$C$89/(Inputs!$C$87+Inputs!$C$88+Inputs!$C$89+Inputs!$C$90+Inputs!$C$91),0) | Z11: =X11*(1+Inputs!$C$54/12)+Y11 | AA11: =IFERROR(MAX(0,F11-J11)*Inputs!$C$90/(Inputs!$C$87+Inputs!$C$88+Inputs!$C$89+Inputs!$C$90+Inputs!$C$91),0) | AB11: =IFERROR(MAX(0,F11-J11)*Inputs!$C$91/(Inputs!$C$87+Inputs!$C$88+Inputs!$C$89+Inputs!$C$90+Inputs!$C$91),0) | AC11: =E11+L11+P11+T11+W11+Z11 | AD11: ='Car Loan'!H12 | AE11: =AC11-AD11
A12: ='Cash Flow'!A12 | B12: ='Cash Flow'!P12 | C12: =E11 | D12: =IF(B12<0,B12,MAX(0,MIN(B12,Inputs!$C$52-C12))) | E12: =C12+D12 | F12: =MAX(0,B12-D12) | G12: =$C$5 | H12: =L11 | I12: =H12*Inputs!$C$54/12 | J12: =IF(H12+I12<G12,MIN(F12,G12-H12-I12),F12*Inputs!$C$86) | K12: ='Cash Flow'!R12 | L12: =MAX(0,H12+I12+J12-K12) | M12: =P11 | N12: =M12*Inputs!$C$56/12 | O12: =K12 | P12: =M12+N12+O12 | Q12: =T11 | R12: =IFERROR(MAX(0,F12-J12)*Inputs!$C$87/(Inputs!$C$87+Inputs!$C$88+Inputs!$C$89+Inputs!$C$90+Inputs!$C$91),0) | S12: =Q12*'Retirement'!$C$5/12 | T12: =Q12+R12+S12 | U12: =W11 | V12: =IFERROR(MAX(0,F12-J12)*Inputs!$C$88/(Inputs!$C$87+Inputs!$C$88+Inputs!$C$89+Inputs!$C$90+Inputs!$C$91),0) | W12: =U12*(1+Inputs!$C$54/12)+V12 | X12: =Z11 | Y12: =IFERROR(MAX(0,F12-J12)*Inputs!$C$89/(Inputs!$C$87+Inputs!$C$88+Inputs!$C$89+Inputs!$C$90+Inputs!$C$91),0) | Z12: =X12*(1+Inputs!$C$54/12)+Y12 | AA12: =IFERROR(MAX(0,F12-J12)*Inputs!$C$90/(Inputs!$C$87+Inputs!$C$88+Inputs!$C$89+Inputs!$C$90+Inputs!$C$91),0) | AB12: =IFERROR(MAX(0,F12-J12)*Inputs!$C$91/(Inputs!$C$87+Inputs!$C$88+Inputs!$C$89+Inputs!$C$90+Inputs!$C$91),0) | AC12: =E12+L12+P12+T12+W12+Z12 | AD12: ='Car Loan'!H13 | AE12: =AC12-AD12
A13: ='Cash Flow'!A13 | B13: ='Cash Flow'!P13 | C13: =E12 | D13: =IF(B13<0,B13,MAX(0,MIN(B13,Inputs!$C$52-C13))) | E13: =C13+D13 | F13: =MAX(0,B13-D13) | G13: =$C$5 | H13: =L12 | I13: =H13*Inputs!$C$54/12 | J13: =IF(H13+I13<G13,MIN(F13,G13-H13-I13),F13*Inputs!$C$86) | K13: ='Cash Flow'!R13 | L13: =MAX(0,H13+I13+J13-K13) | M13: =P12 | N13: =M13*Inputs!$C$56/12 | O13: =K13 | P13: =M13+N13+O13 | Q13: =T12 | R13: =IFERROR(MAX(0,F13-J13)*Inputs!$C$87/(Inputs!$C$87+Inputs!$C$88+Inputs!$C$89+Inputs!$C$90+Inputs!$C$91),0) | S13: =Q13*'Retirement'!$C$5/12 | T13: =Q13+R13+S13 | U13: =W12 | V13: =IFERROR(MAX(0,F13-J13)*Inputs!$C$88/(Inputs!$C$87+Inputs!$C$88+Inputs!$C$89+Inputs!$C$90+Inputs!$C$91),0) | W13: =U13*(1+Inputs!$C$54/12)+V13 | X13: =Z12 | Y13: =IFERROR(MAX(0,F13-J13)*Inputs!$C$89/(Inputs!$C$87+Inputs!$C$88+Inputs!$C$89+Inputs!$C$90+Inputs!$C$91),0) | Z13: =X13*(1+Inputs!$C$54/12)+Y13 | AA13: =IFERROR(MAX(0,F13-J13)*Inputs!$C$90/(Inputs!$C$87+Inputs!$C$88+Inputs!$C$89+Inputs!$C$90+Inputs!$C$91),0) | AB13: =IFERROR(MAX(0,F13-J13)*Inputs!$C$91/(Inputs!$C$87+Inputs!$C$88+Inputs!$C$89+Inputs!$C$90+Inputs!$C$91),0) | AC13: =E13+L13+P13+T13+W13+Z13 | AD13: ='Car Loan'!H14 | AE13: =AC13-AD13
A14: ='Cash Flow'!A14 | B14: ='Cash Flow'!P14 | C14: =E13 | D14: =IF(B14<0,B14,MAX(0,MIN(B14,Inputs!$C$52-C14))) | E14: =C14+D14 | F14: =MAX(0,B14-D14) | G14: =$C$5 | H14: =L13 | I14: =H14*Inputs!$C$54/12 | J14: =IF(H14+I14<G14,MIN(F14,G14-H14-I14),F14*Inputs!$C$86) | K14: ='Cash Flow'!R14 | L14: =MAX(0,H14+I14+J14-K14) | M14: =P13 | N14: =M14*Inputs!$C$56/12 | O14: =K14 | P14: =M14+N14+O14 | Q14: =T13 | R14: =IFERROR(MAX(0,F14-J14)*Inputs!$C$87/(Inputs!$C$87+Inputs!$C$88+Inputs!$C$89+Inputs!$C$90+Inputs!$C$91),0) | S14: =Q14*'Retirement'!$C$5/12 | T14: =Q14+R14+S14 | U14: =W13 | V14: =IFERROR(MAX(0,F14-J14)*Inputs!$C$88/(Inputs!$C$87+Inputs!$C$88+Inputs!$C$89+Inputs!$C$90+Inputs!$C$91),0) | W14: =U14*(1+Inputs!$C$54/12)+V14 | X14: =Z13 | Y14: =IFERROR(MAX(0,F14-J14)*Inputs!$C$89/(Inputs!$C$87+Inputs!$C$88+Inputs!$C$89+Inputs!$C$90+Inputs!$C$91),0) | Z14: =X14*(1+Inputs!$C$54/12)+Y14 | AA14: =IFERROR(MAX(0,F14-J14)*Inputs!$C$90/(Inputs!$C$87+Inputs!$C$88+Inputs!$C$89+Inputs!$C$90+Inputs!$C$91),0) | AB14: =IFERROR(MAX(0,F14-J14)*Inputs!$C$91/(Inputs!$C$87+Inputs!$C$88+Inputs!$C$89+Inputs!$C$90+Inputs!$C$91),0) | AC14: =E14+L14+P14+T14+W14+Z14 | AD14: ='Car Loan'!H15 | AE14: =AC14-AD14
A15: ='Cash Flow'!A15 | B15: ='Cash Flow'!P15 | C15: =E14 | D15: =IF(B15<0,B15,MAX(0,MIN(B15,Inputs!$C$52-C15))) | E15: =C15+D15 | F15: =MAX(0,B15-D15) | G15: =$C$5 | H15: =L14 | I15: =H15*Inputs!$C$54/12 | J15: =IF(H15+I15<G15,MIN(F15,G15-H15-I15),F15*Inputs!$C$86) | K15: ='Cash Flow'!R15 | L15: =MAX(0,H15+I15+J15-K15) | M15: =P14 | N15: =M15*Inputs!$C$56/12 | O15: =K15 | P15: =M15+N15+O15 | Q15: =T14 | R15: =IFERROR(MAX(0,F15-J15)*Inputs!$C$87/(Inputs!$C$87+Inputs!$C$88+Inputs!$C$89+Inputs!$C$90+Inputs!$C$91),0) | S15: =Q15*'Retirement'!$C$5/12 | T15: =Q15+R15+S15 | U15: =W14 | V15: =IFERROR(MAX(0,F15-J15)*Inputs!$C$88/(Inputs!$C$87+Inputs!$C$88+Inputs!$C$89+Inputs!$C$90+Inputs!$C$91),0) | W15: =U15*(1+Inputs!$C$54/12)+V15 | X15: =Z14 | Y15: =IFERROR(MAX(0,F15-J15)*Inputs!$C$89/(Inputs!$C$87+Inputs!$C$88+Inputs!$C$89+Inputs!$C$90+Inputs!$C$91),0) | Z15: =X15*(1+Inputs!$C$54/12)+Y15 | AA15: =IFERROR(MAX(0,F15-J15)*Inputs!$C$90/(Inputs!$C$87+Inputs!$C$88+Inputs!$C$89+Inputs!$C$90+Inputs!$C$91),0) | AB15: =IFERROR(MAX(0,F15-J15)*Inputs!$C$91/(Inputs!$C$87+Inputs!$C$88+Inputs!$C$89+Inputs!$C$90+Inputs!$C$91),0) | AC15: =E15+L15+P15+T15+W15+Z15 | AD15: ='Car Loan'!H16 | AE15: =AC15-AD15
A16: ='Cash Flow'!A16 | B16: ='Cash Flow'!P16 | C16: =E15 | D16: =IF(B16<0,B16,MAX(0,MIN(B16,Inputs!$C$52-C16))) | E16: =C16+D16 | F16: =MAX(0,B16-D16) | G16: =$C$5 | H16: =L15 | I16: =H16*Inputs!$C$54/12 | J16: =IF(H16+I16<G16,MIN(F16,G16-H16-I16),F16*Inputs!$C$86) | K16: ='Cash Flow'!R16 | L16: =MAX(0,H16+I16+J16-K16) | M16: =P15 | N16: =M16*Inputs!$C$56/12 | O16: =K16 | P16: =M16+N16+O16 | Q16: =T15 | R16: =IFERROR(MAX(0,F16-J16)*Inputs!$C$87/(Inputs!$C$87+Inputs!$C$88+Inputs!$C$89+Inputs!$C$90+Inputs!$C$91),0) | S16: =Q16*'Retirement'!$C$5/12 | T16: =Q16+R16+S16 | U16: =W15 | V16: =IFERROR(MAX(0,F16-J16)*Inputs!$C$88/(Inputs!$C$87+Inputs!$C$88+Inputs!$C$89+Inputs!$C$90+Inputs!$C$91),0) | W16: =U16*(1+Inputs!$C$54/12)+V16 | X16: =Z15 | Y16: =IFERROR(MAX(0,F16-J16)*Inputs!$C$89/(Inputs!$C$87+Inputs!$C$88+Inputs!$C$89+Inputs!$C$90+Inputs!$C$91),0) | Z16: =X16*(1+Inputs!$C$54/12)+Y16 | AA16: =IFERROR(MAX(0,F16-J16)*Inputs!$C$90/(Inputs!$C$87+Inputs!$C$88+Inputs!$C$89+Inputs!$C$90+Inputs!$C$91),0) | AB16: =IFERROR(MAX(0,F16-J16)*Inputs!$C$91/(Inputs!$C$87+Inputs!$C$88+Inputs!$C$89+Inputs!$C$90+Inputs!$C$91),0) | AC16: =E16+L16+P16+T16+W16+Z16 | AD16: ='Car Loan'!H17 | AE16: =AC16-AD16
A17: ='Cash Flow'!A17 | B17: ='Cash Flow'!P17 | C17: =E16 | D17: =IF(B17<0,B17,MAX(0,MIN(B17,Inputs!$C$52-C17))) | E17: =C17+D17 | F17: =MAX(0,B17-D17) | G17: =$C$5 | H17: =L16 | I17: =H17*Inputs!$C$54/12 | J17: =IF(H17+I17<G17,MIN(F17,G17-H17-I17),F17*Inputs!$C$86) | K17: ='Cash Flow'!R17 | L17: =MAX(0,H17+I17+J17-K17) | M17: =P16 | N17: =M17*Inputs!$C$56/12 | O17: =K17 | P17: =M17+N17+O17 | Q17: =T16 | R17: =IFERROR(MAX(0,F17-J17)*Inputs!$C$87/(Inputs!$C$87+Inputs!$C$88+Inputs!$C$89+Inputs!$C$90+Inputs!$C$91),0) | S17: =Q17*'Retirement'!$C$5/12 | T17: =Q17+R17+S17 | U17: =W16 | V17: =IFERROR(MAX(0,F17-J17)*Inputs!$C$88/(Inputs!$C$87+Inputs!$C$88+Inputs!$C$89+Inputs!$C$90+Inputs!$C$91),0) | W17: =U17*(1+Inputs!$C$54/12)+V17 | X17: =Z16 | Y17: =IFERROR(MAX(0,F17-J17)*Inputs!$C$89/(Inputs!$C$87+Inputs!$C$88+Inputs!$C$89+Inputs!$C$90+Inputs!$C$91),0) | Z17: =X17*(1+Inputs!$C$54/12)+Y17 | AA17: =IFERROR(MAX(0,F17-J17)*Inputs!$C$90/(Inputs!$C$87+Inputs!$C$88+Inputs!$C$89+Inputs!$C$90+Inputs!$C$91),0) | AB17: =IFERROR(MAX(0,F17-J17)*Inputs!$C$91/(Inputs!$C$87+Inputs!$C$88+Inputs!$C$89+Inputs!$C$90+Inputs!$C$91),0) | AC17: =E17+L17+P17+T17+W17+Z17 | AD17: ='Car Loan'!H18 | AE17: =AC17-AD17
A18: ='Cash Flow'!A18 | B18: ='Cash Flow'!P18 | C18: =E17 | D18: =IF(B18<0,B18,MAX(0,MIN(B18,Inputs!$C$52-C18))) | E18: =C18+D18 | F18: =MAX(0,B18-D18) | G18: =$C$5 | H18: =L17 | I18: =H18*Inputs!$C$54/12 | J18: =IF(H18+I18<G18,MIN(F18,G18-H18-I18),F18*Inputs!$C$86) | K18: ='Cash Flow'!R18 | L18: =MAX(0,H18+I18+J18-K18) | M18: =P17 | N18: =M18*Inputs!$C$56/12 | O18: =K18 | P18: =M18+N18+O18 | Q18: =T17 | R18: =IFERROR(MAX(0,F18-J18)*Inputs!$C$87/(Inputs!$C$87+Inputs!$C$88+Inputs!$C$89+Inputs!$C$90+Inputs!$C$91),0) | S18: =Q18*'Retirement'!$C$5/12 | T18: =Q18+R18+S18 | U18: =W17 | V18: =IFERROR(MAX(0,F18-J18)*Inputs!$C$88/(Inputs!$C$87+Inputs!$C$88+Inputs!$C$89+Inputs!$C$90+Inputs!$C$91),0) | W18: =U18*(1+Inputs!$C$54/12)+V18 | X18: =Z17 | Y18: =IFERROR(MAX(0,F18-J18)*Inputs!$C$89/(Inputs!$C$87+Inputs!$C$88+Inputs!$C$89+Inputs!$C$90+Inputs!$C$91),0) | Z18: =X18*(1+Inputs!$C$54/12)+Y18 | AA18: =IFERROR(MAX(0,F18-J18)*Inputs!$C$90/(Inputs!$C$87+Inputs!$C$88+Inputs!$C$89+Inputs!$C$90+Inputs!$C$91),0) | AB18: =IFERROR(MAX(0,F18-J18)*Inputs!$C$91/(Inputs!$C$87+Inputs!$C$88+Inputs!$C$89+Inputs!$C$90+Inputs!$C$91),0) | AC18: =E18+L18+P18+T18+W18+Z18 | AD18: ='Car Loan'!H19 | AE18: =AC18-AD18
A19: ='Cash Flow'!A19 | B19: ='Cash Flow'!P19 | C19: =E18 | D19: =IF(B19<0,B19,MAX(0,MIN(B19,Inputs!$C$52-C19))) | E19: =C19+D19 | F19: =MAX(0,B19-D19) | G19: =$C$5 | H19: =L18 | I19: =H19*Inputs!$C$54/12 | J19: =IF(H19+I19<G19,MIN(F19,G19-H19-I19),F19*Inputs!$C$86) | K19: ='Cash Flow'!R19 | L19: =MAX(0,H19+I19+J19-K19) | M19: =P18 | N19: =M19*Inputs!$C$56/12 | O19: =K19 | P19: =M19+N19+O19 | Q19: =T18 | R19: =IFERROR(MAX(0,F19-J19)*Inputs!$C$87/(Inputs!$C$87+Inputs!$C$88+Inputs!$C$89+Inputs!$C$90+Inputs!$C$91),0) | S19: =Q19*'Retirement'!$C$5/12 | T19: =Q19+R19+S19 | U19: =W18 | V19: =IFERROR(MAX(0,F19-J19)*Inputs!$C$88/(Inputs!$C$87+Inputs!$C$88+Inputs!$C$89+Inputs!$C$90+Inputs!$C$91),0) | W19: =U19*(1+Inputs!$C$54/12)+V19 | X19: =Z18 | Y19: =IFERROR(MAX(0,F19-J19)*Inputs!$C$89/(Inputs!$C$87+Inputs!$C$88+Inputs!$C$89+Inputs!$C$90+Inputs!$C$91),0) | Z19: =X19*(1+Inputs!$C$54/12)+Y19 | AA19: =IFERROR(MAX(0,F19-J19)*Inputs!$C$90/(Inputs!$C$87+Inputs!$C$88+Inputs!$C$89+Inputs!$C$90+Inputs!$C$91),0) | AB19: =IFERROR(MAX(0,F19-J19)*Inputs!$C$91/(Inputs!$C$87+Inputs!$C$88+Inputs!$C$89+Inputs!$C$90+Inputs!$C$91),0) | AC19: =E19+L19+P19+T19+W19+Z19 | AD19: ='Car Loan'!H20 | AE19: =AC19-AD19
A20: ='Cash Flow'!A20 | B20: ='Cash Flow'!P20 | C20: =E19 | D20: =IF(B20<0,B20,MAX(0,MIN(B20,Inputs!$C$52-C20))) | E20: =C20+D20 | F20: =MAX(0,B20-D20) | G20: =$C$5 | H20: =L19 | I20: =H20*Inputs!$C$54/12 | J20: =IF(H20+I20<G20,MIN(F20,G20-H20-I20),F20*Inputs!$C$86) | K20: ='Cash Flow'!R20 | L20: =MAX(0,H20+I20+J20-K20) | M20: =P19 | N20: =M20*Inputs!$C$56/12 | O20: =K20 | P20: =M20+N20+O20 | Q20: =T19 | R20: =IFERROR(MAX(0,F20-J20)*Inputs!$C$87/(Inputs!$C$87+Inputs!$C$88+Inputs!$C$89+Inputs!$C$90+Inputs!$C$91),0) | S20: =Q20*'Retirement'!$C$5/12 | T20: =Q20+R20+S20 | U20: =W19 | V20: =IFERROR(MAX(0,F20-J20)*Inputs!$C$88/(Inputs!$C$87+Inputs!$C$88+Inputs!$C$89+Inputs!$C$90+Inputs!$C$91),0) | W20: =U20*(1+Inputs!$C$54/12)+V20 | X20: =Z19 | Y20: =IFERROR(MAX(0,F20-J20)*Inputs!$C$89/(Inputs!$C$87+Inputs!$C$88+Inputs!$C$89+Inputs!$C$90+Inputs!$C$91),0) | Z20: =X20*(1+Inputs!$C$54/12)+Y20 | AA20: =IFERROR(MAX(0,F20-J20)*Inputs!$C$90/(Inputs!$C$87+Inputs!$C$88+Inputs!$C$89+Inputs!$C$90+Inputs!$C$91),0) | AB20: =IFERROR(MAX(0,F20-J20)*Inputs!$C$91/(Inputs!$C$87+Inputs!$C$88+Inputs!$C$89+Inputs!$C$90+Inputs!$C$91),0) | AC20: =E20+L20+P20+T20+W20+Z20 | AD20: ='Car Loan'!H21 | AE20: =AC20-AD20
A21: ='Cash Flow'!A21 | B21: ='Cash Flow'!P21 | C21: =E20 | D21: =IF(B21<0,B21,MAX(0,MIN(B21,Inputs!$C$52-C21))) | E21: =C21+D21 | F21: =MAX(0,B21-D21) | G21: =$C$5 | H21: =L20 | I21: =H21*Inputs!$C$54/12 | J21: =IF(H21+I21<G21,MIN(F21,G21-H21-I21),F21*Inputs!$C$86) | K21: ='Cash Flow'!R21 | L21: =MAX(0,H21+I21+J21-K21) | M21: =P20 | N21: =M21*Inputs!$C$56/12 | O21: =K21 | P21: =M21+N21+O21 | Q21: =T20 | R21: =IFERROR(MAX(0,F21-J21)*Inputs!$C$87/(Inputs!$C$87+Inputs!$C$88+Inputs!$C$89+Inputs!$C$90+Inputs!$C$91),0) | S21: =Q21*'Retirement'!$C$5/12 | T21: =Q21+R21+S21 | U21: =W20 | V21: =IFERROR(MAX(0,F21-J21)*Inputs!$C$88/(Inputs!$C$87+Inputs!$C$88+Inputs!$C$89+Inputs!$C$90+Inputs!$C$91),0) | W21: =U21*(1+Inputs!$C$54/12)+V21 | X21: =Z20 | Y21: =IFERROR(MAX(0,F21-J21)*Inputs!$C$89/(Inputs!$C$87+Inputs!$C$88+Inputs!$C$89+Inputs!$C$90+Inputs!$C$91),0) | Z21: =X21*(1+Inputs!$C$54/12)+Y21 | AA21: =IFERROR(MAX(0,F21-J21)*Inputs!$C$90/(Inputs!$C$87+Inputs!$C$88+Inputs!$C$89+Inputs!$C$90+Inputs!$C$91),0) | AB21: =IFERROR(MAX(0,F21-J21)*Inputs!$C$91/(Inputs!$C$87+Inputs!$C$88+Inputs!$C$89+Inputs!$C$90+Inputs!$C$91),0) | AC21: =E21+L21+P21+T21+W21+Z21 | AD21: ='Car Loan'!H22 | AE21: =AC21-AD21
... A44: ='Cash Flow'!A44 | B44: ='Cash Flow'!P44 | C44: =E43 | D44: =IF(B44<0,B44,MAX(0,MIN(B44,Inputs!$C$52-C44))) | E44: =C44+D44 | F44: =MAX(0,B44-D44) | G44: =$C$5 | H44: =L43 | I44: =H44*Inputs!$C$54/12 | J44: =IF(H44+I44<G44,MIN(F44,G44-H44-I44),F44*Inputs!$C$86) | K44: ='Cash Flow'!R44 | L44: =MAX(0,H44+I44+J44-K44) | M44: =P43 | N44: =M44*Inputs!$C$56/12 | O44: =K44 | P44: =M44+N44+O44 | Q44: =T43 | R44: =IFERROR(MAX(0,F44-J44)*Inputs!$C$87/(Inputs!$C$87+Inputs!$C$88+Inputs!$C$89+Inputs!$C$90+Inputs!$C$91),0) | S44: =Q44*'Retirement'!$C$5/12 | T44: =Q44+R44+S44 | U44: =W43 | V44: =IFERROR(MAX(0,F44-J44)*Inputs!$C$88/(Inputs!$C$87+Inputs!$C$88+Inputs!$C$89+Inputs!$C$90+Inputs!$C$91),0) | W44: =U44*(1+Inputs!$C$54/12)+V44 | X44: =Z43 | Y44: =IFERROR(MAX(0,F44-J44)*Inputs!$C$89/(Inputs!$C$87+Inputs!$C$88+Inputs!$C$89+Inputs!$C$90+Inputs!$C$91),0) | Z44: =X44*(1+Inputs!$C$54/12)+Y44 | AA44: =IFERROR(MAX(0,F44-J44)*Inputs!$C$90/(Inputs!$C$87+Inputs!$C$88+Inputs!$C$89+Inputs!$C$90+Inputs!$C$91),0) | AB44: =IFERROR(MAX(0,F44-J44)*Inputs!$C$91/(Inputs!$C$87+Inputs!$C$88+Inputs!$C$89+Inputs!$C$90+Inputs!$C$91),0) | AC44: =E44+L44+P44+T44+W44+Z44 | AD44: ='Car Loan'!H45 | AE44: =AC44-AD44

Sheet Certificate Ladder
A1: SHARED CERTIFICATE LADDER — 3-month roll, +$1,250 from savings every time
A2: Next roll 10/28/2026 at 3.687% APY. The right-hand columns answer the question that matters: is this beating your savings account?
A7: Roll | B7: Maturity / Roll date | C7: Opening balance | D7: Rate | E7: Interest earned | F7: Auto-add from savings | G7: Closing balance | H7: Cumulative interest | I7: If it had stayed in HYSA | J7: Note
A8: 1 | B8: =Inputs!$C$57 | C8: =Inputs!$C$55 | D8: =Inputs!$C$56 | E8: =C8*D8*Inputs!$C$58/12 | F8: =Inputs!$C$59 | G8: =C8+E8+F8 | H8: =E8 | I8: =Inputs!$C$55*(1+Inputs!$C$54*Inputs!$C$58/12) | J8: Column I asks: if this exact money (same $1,250 every quarter) had simply stayed in your high-yield savings at the rate on Inputs, what would it be worth? If column I beats column G, the certificate is costing you money.
A9: 2 | B9: =EDATE(B8,Inputs!$C$58) | C9: =G8 | D9: =Inputs!$C$56 | E9: =C9*D9*Inputs!$C$58/12 | F9: =Inputs!$C$59 | G9: =C9+E9+F9 | H9: =H8+E9 | I9: =(I8+Inputs!$C$59)*(1+Inputs!$C$54*Inputs!$C$58/12)
A10: 3 | B10: =EDATE(B9,Inputs!$C$58) | C10: =G9 | D10: =Inputs!$C$56 | E10: =C10*D10*Inputs!$C$58/12 | F10: =Inputs!$C$59 | G10: =C10+E10+F10 | H10: =H9+E10 | I10: =(I9+Inputs!$C$59)*(1+Inputs!$C$54*Inputs!$C$58/12)
A11: 4 | B11: =EDATE(B10,Inputs!$C$58) | C11: =G10 | D11: =Inputs!$C$56 | E11: =C11*D11*Inputs!$C$58/12 | F11: =Inputs!$C$59 | G11: =C11+E11+F11 | H11: =H10+E11 | I11: =(I10+Inputs!$C$59)*(1+Inputs!$C$54*Inputs!$C$58/12)
A12: 5 | B12: =EDATE(B11,Inputs!$C$58) | C12: =G11 | D12: =Inputs!$C$56 | E12: =C12*D12*Inputs!$C$58/12 | F12: =Inputs!$C$59 | G12: =C12+E12+F12 | H12: =H11+E12 | I12: =(I11+Inputs!$C$59)*(1+Inputs!$C$54*Inputs!$C$58/12)
A13: 6 | B13: =EDATE(B12,Inputs!$C$58) | C13: =G12 | D13: =Inputs!$C$56 | E13: =C13*D13*Inputs!$C$58/12 | F13: =Inputs!$C$59 | G13: =C13+E13+F13 | H13: =H12+E13 | I13: =(I12+Inputs!$C$59)*(1+Inputs!$C$54*Inputs!$C$58/12)
A14: 7 | B14: =EDATE(B13,Inputs!$C$58) | C14: =G13 | D14: =Inputs!$C$56 | E14: =C14*D14*Inputs!$C$58/12 | F14: =Inputs!$C$59 | G14: =C14+E14+F14 | H14: =H13+E14 | I14: =(I13+Inputs!$C$59)*(1+Inputs!$C$54*Inputs!$C$58/12)
A15: 8 | B15: =EDATE(B14,Inputs!$C$58) | C15: =G14 | D15: =Inputs!$C$56 | E15: =C15*D15*Inputs!$C$58/12 | F15: =Inputs!$C$59 | G15: =C15+E15+F15 | H15: =H14+E15 | I15: =(I14+Inputs!$C$59)*(1+Inputs!$C$54*Inputs!$C$58/12)
A16: 9 | B16: =EDATE(B15,Inputs!$C$58) | C16: =G15 | D16: =Inputs!$C$56 | E16: =C16*D16*Inputs!$C$58/12 | F16: =Inputs!$C$59 | G16: =C16+E16+F16 | H16: =H15+E16 | I16: =(I15+Inputs!$C$59)*(1+Inputs!$C$54*Inputs!$C$58/12)
A17: 10 | B17: =EDATE(B16,Inputs!$C$58) | C17: =G16 | D17: =Inputs!$C$56 | E17: =C17*D17*Inputs!$C$58/12 | F17: =Inputs!$C$59 | G17: =C17+E17+F17 | H17: =H16+E17 | I17: =(I16+Inputs!$C$59)*(1+Inputs!$C$54*Inputs!$C$58/12)
A18: 11 | B18: =EDATE(B17,Inputs!$C$58) | C18: =G17 | D18: =Inputs!$C$56 | E18: =C18*D18*Inputs!$C$58/12 | F18: =Inputs!$C$59 | G18: =C18+E18+F18 | H18: =H17+E18 | I18: =(I17+Inputs!$C$59)*(1+Inputs!$C$54*Inputs!$C$58/12)
A19: 12 | B19: =EDATE(B18,Inputs!$C$58) | C19: =G18 | D19: =Inputs!$C$56 | E19: =C19*D19*Inputs!$C$58/12 | F19: =Inputs!$C$59 | G19: =C19+E19+F19 | H19: =H18+E19 | I19: =(I18+Inputs!$C$59)*(1+Inputs!$C$54*Inputs!$C$58/12)
A20: 13 | B20: =EDATE(B19,Inputs!$C$58) | C20: =G19 | D20: =Inputs!$C$56 | E20: =C20*D20*Inputs!$C$58/12 | F20: =Inputs!$C$59 | G20: =C20+E20+F20 | H20: =H19+E20 | I20: =(I19+Inputs!$C$59)*(1+Inputs!$C$54*Inputs!$C$58/12)
... A40: 33 | B40: =EDATE(B39,Inputs!$C$58) | C40: =G39 | D40: =Inputs!$C$56 | E40: =C40*D40*Inputs!$C$58/12 | F40: =Inputs!$C$59 | G40: =C40+E40+F40 | H40: =H39+E40 | I40: =(I39+Inputs!$C$59)*(1+Inputs!$C$54*Inputs!$C$58/12)
B42: Certificate vs. HYSA after 8 years: | G42: =G40-I40 | H42: <- if NEGATIVE, the certificate is the worse account and the auto-roll should be stopped.

Sheet Car Loan
A1: AUTO LOAN — $25,092.02 outstanding, $475.69 due the 14th
A2: Enter the real APR on Inputs (it is a yellow cell - it was not provided). Then test an extra payment in the blue cell below.
A4: Extra principal per month: | C4: 0 | D4: <- change this and watch rows below
A5: Months to payoff: | C5: =IFERROR(NPER(Inputs!$C$64/12,-(Inputs!$C$28+C4),Inputs!$C$63),0) | D5: Payoff date: | E5: =EDATE(Inputs!$C$7,ROUNDUP(C5,0)) | F5: Total interest: | G5: =(Inputs!$C$28+C4)*C5-Inputs!$C$63
A6: Interest SAVED by the extra payment: | C6: =IFERROR((Inputs!$C$28)*NPER(Inputs!$C$64/12,-Inputs!$C$28,Inputs!$C$63)-Inputs!$C$63-G5,0) | D6: =IFERROR("...and you finish "&TEXT(NPER(Inputs!$C$64/12,-Inputs!$C$28,Inputs!$C$63)-C5,"0.0")&" months sooner","")
A8: Prepay only if the APR beats your savings rate. Compare Inputs auto APR against your HYSA APY - see 'Recommendations'.
A9: # | B9: Payment date | C9: Opening balance | D9: Payment | E9: Interest | F9: Principal | G9: Extra principal | H9: Closing balance | I9: Cumulative interest | J9: Note
A10: 1 | B10: =DATE(YEAR(Inputs!$C$7),MONTH(Inputs!$C$7)+1,Inputs!$C$29) | C10: =Inputs!$C$63 | D10: =IF(C10<=0,0,MIN(Inputs!$C$28,C10+E10)) | E10: =IF(C10<=0,0,C10*Inputs!$C$64/12) | F10: =IF(C10<=0,0,D10-E10) | G10: =IF(C10<=0,0,MIN($C$4,MAX(0,C10-F10))) | H10: =MAX(0,C10-F10-G10) | I10: =E10 | J10: =IF(AND(H10=0,C10>0),"<<< PAID OFF","")
A11: 2 | B11: =EDATE(B10,1) | C11: =H10 | D11: =IF(C11<=0,0,MIN(Inputs!$C$28,C11+E11)) | E11: =IF(C11<=0,0,C11*Inputs!$C$64/12) | F11: =IF(C11<=0,0,D11-E11) | G11: =IF(C11<=0,0,MIN($C$4,MAX(0,C11-F11))) | H11: =MAX(0,C11-F11-G11) | I11: =I10+E11 | J11: =IF(AND(H11=0,C11>0),"<<< PAID OFF","")
A12: 3 | B12: =EDATE(B11,1) | C12: =H11 | D12: =IF(C12<=0,0,MIN(Inputs!$C$28,C12+E12)) | E12: =IF(C12<=0,0,C12*Inputs!$C$64/12) | F12: =IF(C12<=0,0,D12-E12) | G12: =IF(C12<=0,0,MIN($C$4,MAX(0,C12-F12))) | H12: =MAX(0,C12-F12-G12) | I12: =I11+E12 | J12: =IF(AND(H12=0,C12>0),"<<< PAID OFF","")
A13: 4 | B13: =EDATE(B12,1) | C13: =H12 | D13: =IF(C13<=0,0,MIN(Inputs!$C$28,C13+E13)) | E13: =IF(C13<=0,0,C13*Inputs!$C$64/12) | F13: =IF(C13<=0,0,D13-E13) | G13: =IF(C13<=0,0,MIN($C$4,MAX(0,C13-F13))) | H13: =MAX(0,C13-F13-G13) | I13: =I12+E13 | J13: =IF(AND(H13=0,C13>0),"<<< PAID OFF","")
A14: 5 | B14: =EDATE(B13,1) | C14: =H13 | D14: =IF(C14<=0,0,MIN(Inputs!$C$28,C14+E14)) | E14: =IF(C14<=0,0,C14*Inputs!$C$64/12) | F14: =IF(C14<=0,0,D14-E14) | G14: =IF(C14<=0,0,MIN($C$4,MAX(0,C14-F14))) | H14: =MAX(0,C14-F14-G14) | I14: =I13+E14 | J14: =IF(AND(H14=0,C14>0),"<<< PAID OFF","")
A15: 6 | B15: =EDATE(B14,1) | C15: =H14 | D15: =IF(C15<=0,0,MIN(Inputs!$C$28,C15+E15)) | E15: =IF(C15<=0,0,C15*Inputs!$C$64/12) | F15: =IF(C15<=0,0,D15-E15) | G15: =IF(C15<=0,0,MIN($C$4,MAX(0,C15-F15))) | H15: =MAX(0,C15-F15-G15) | I15: =I14+E15 | J15: =IF(AND(H15=0,C15>0),"<<< PAID OFF","")
A16: 7 | B16: =EDATE(B15,1) | C16: =H15 | D16: =IF(C16<=0,0,MIN(Inputs!$C$28,C16+E16)) | E16: =IF(C16<=0,0,C16*Inputs!$C$64/12) | F16: =IF(C16<=0,0,D16-E16) | G16: =IF(C16<=0,0,MIN($C$4,MAX(0,C16-F16))) | H16: =MAX(0,C16-F16-G16) | I16: =I15+E16 | J16: =IF(AND(H16=0,C16>0),"<<< PAID OFF","")
A17: 8 | B17: =EDATE(B16,1) | C17: =H16 | D17: =IF(C17<=0,0,MIN(Inputs!$C$28,C17+E17)) | E17: =IF(C17<=0,0,C17*Inputs!$C$64/12) | F17: =IF(C17<=0,0,D17-E17) | G17: =IF(C17<=0,0,MIN($C$4,MAX(0,C17-F17))) | H17: =MAX(0,C17-F17-G17) | I17: =I16+E17 | J17: =IF(AND(H17=0,C17>0),"<<< PAID OFF","")
A18: 9 | B18: =EDATE(B17,1) | C18: =H17 | D18: =IF(C18<=0,0,MIN(Inputs!$C$28,C18+E18)) | E18: =IF(C18<=0,0,C18*Inputs!$C$64/12) | F18: =IF(C18<=0,0,D18-E18) | G18: =IF(C18<=0,0,MIN($C$4,MAX(0,C18-F18))) | H18: =MAX(0,C18-F18-G18) | I18: =I17+E18 | J18: =IF(AND(H18=0,C18>0),"<<< PAID OFF","")
A19: 10 | B19: =EDATE(B18,1) | C19: =H18 | D19: =IF(C19<=0,0,MIN(Inputs!$C$28,C19+E19)) | E19: =IF(C19<=0,0,C19*Inputs!$C$64/12) | F19: =IF(C19<=0,0,D19-E19) | G19: =IF(C19<=0,0,MIN($C$4,MAX(0,C19-F19))) | H19: =MAX(0,C19-F19-G19) | I19: =I18+E19 | J19: =IF(AND(H19=0,C19>0),"<<< PAID OFF","")
A20: 11 | B20: =EDATE(B19,1) | C20: =H19 | D20: =IF(C20<=0,0,MIN(Inputs!$C$28,C20+E20)) | E20: =IF(C20<=0,0,C20*Inputs!$C$64/12) | F20: =IF(C20<=0,0,D20-E20) | G20: =IF(C20<=0,0,MIN($C$4,MAX(0,C20-F20))) | H20: =MAX(0,C20-F20-G20) | I20: =I19+E20 | J20: =IF(AND(H20=0,C20>0),"<<< PAID OFF","")
A21: 12 | B21: =EDATE(B20,1) | C21: =H20 | D21: =IF(C21<=0,0,MIN(Inputs!$C$28,C21+E21)) | E21: =IF(C21<=0,0,C21*Inputs!$C$64/12) | F21: =IF(C21<=0,0,D21-E21) | G21: =IF(C21<=0,0,MIN($C$4,MAX(0,C21-F21))) | H21: =MAX(0,C21-F21-G21) | I21: =I20+E21 | J21: =IF(AND(H21=0,C21>0),"<<< PAID OFF","")
A22: 13 | B22: =EDATE(B21,1) | C22: =H21 | D22: =IF(C22<=0,0,MIN(Inputs!$C$28,C22+E22)) | E22: =IF(C22<=0,0,C22*Inputs!$C$64/12) | F22: =IF(C22<=0,0,D22-E22) | G22: =IF(C22<=0,0,MIN($C$4,MAX(0,C22-F22))) | H22: =MAX(0,C22-F22-G22) | I22: =I21+E22 | J22: =IF(AND(H22=0,C22>0),"<<< PAID OFF","")
... A93: 84 | B93: =EDATE(B92,1) | C93: =H92 | D93: =IF(C93<=0,0,MIN(Inputs!$C$28,C93+E93)) | E93: =IF(C93<=0,0,C93*Inputs!$C$64/12) | F93: =IF(C93<=0,0,D93-E93) | G93: =IF(C93<=0,0,MIN($C$4,MAX(0,C93-F93))) | H93: =MAX(0,C93-F93-G93) | I93: =I92+E93 | J93: =IF(AND(H93=0,C93>0),"<<< PAID OFF","")

Sheet Credit Builder
A1: CREDIT BUILDER — you have 2 lines and you want a mortgage. Here is the plan.
A2: You asked whether to pay the card in full. Short answer: yes, always the full statement balance - but WHEN you pay changes your score.
A5: A. WHERE YOU STAND
B6: Metric | C6: Value | D6: Target | F6: What it means
B7: Open credit lines | C7: =Inputs!$C$69 | D7: =4 | F7: Two is thin. Scoring models want to see you handle several accounts at once. 4-5 is the sweet spot.
B8: Credit card balance | C8: =Inputs!$C$65 | D8: =0 | F8: Paid in full every month.
B9: Credit limit | C9: =Inputs!$C$67 | D9: ="higher" | F9: Ask for an increase every 6 months. A higher limit lowers utilization with zero effort.
B10: Utilization (reported) | C10: =IFERROR(Inputs!$C$65/Inputs!$C$67,0) | D10: =0.09 | F10: THE lever. 30% of your FICO. Keep the REPORTED figure between 1% and 9%.
B11: Installment loan | C11: ="Auto loan - open" | D11: ="keep" | F11: Your car loan is doing real work here: it gives you credit MIX, which is 10% of the score. Do not rush to kill it for score reasons.
B12: Age of credit history | C12: ="~ thin / young" | D12: ="time" | F12: The one input you cannot buy. Which is why the authorized-user move below is worth so much.
A14: B. THE ANSWER TO YOUR QUESTION: PAY IN FULL - BUT PAY TWICE
B15: The myth | C15: Carrying a small balance 'builds credit'. It does not. It costs you 26.99% APR and does nothing for your score.
B16: The mechanic that matters | C16: Your issuer reports your balance to the bureaus on the STATEMENT CLOSING date, not the due date. Whatever the statement says is what the whole world sees for the next 30 days.
B17: So do this | C17: Payment 1: a few days BEFORE the statement closes, pay the balance down to roughly 5% of your limit. Payment 2: pay the remaining statement balance in full by the 7th. You pay zero interest and you report a perfect small balance.
B18: Why not report $0? | C18: All-zero can actually score slightly lower than a small positive balance. Let ONE card report 1-9% and everything else report zero. This is the 'AZEO' method and it is worth real points at application time.
B19: On a $5,000 limit | C19: Let about $250 report. Then pay it off. That is the whole trick.
A21: C. THE 24-MONTH SEQUENCE (order matters - and there is a hard deadline)
B22: When | C22: Action | F22: Why
B23: Now - Oct 2026 | C23: Ask your current issuer for a credit-limit increase. | F23: Instant utilization improvement, usually a soft pull. Free points.
B24: Now - Oct 2026 | C24: Ask a parent to add you as an AUTHORIZED USER on their oldest, lowest-utilization card. | F24: You inherit that card's full age and limit. Nothing else moves your score this fast, and you live at home - just ask.
B25: Oct - Dec 2026 | C25: Open card #2. Pick one that pays 3-4% on gas. | F25: You spend ~$216/mo on fuel. At 3% that is ~$78/yr back, and it adds a third line.
B26: Mar - Jun 2027 | C26: Open card #3 (or a small credit-builder loan). | F26: Gets you to 4-5 lines with 2+ years of history by the time you apply.
B27: From ~Mar 2028 | C27: STOP. No new accounts, no new inquiries, no new cars. | F27: *** HARD RULE *** New accounts inside 12 months of a mortgage application lower your average account age and add inquiries, exactly when it costs the most. As a broker you already know what a 20-point drop does to pricing.
B28: Always | C28: Never miss a payment by even one day. | F28: Payment history is 35% of the score. One 30-day late can cost 60-100 points and takes 7 years to fall off. Autopay the minimum as a safety net, then pay in full manually.

Sheet Tax Reserve
A1: TAX RESERVE — the biggest unbudgeted number in your plan
A2: If you are 1099, roughly 30 cents of every dollar you earn already belongs to someone else. Confirm your status on Inputs before trusting anything else in this workbook.
B5: YOUR STATUS (from Inputs): | C5: =Inputs!$C$20 | D5: =IF(Inputs!$C$20="1099","You owe your own taxes. Everything below applies.","Your employer withholds. The reserve below is $0 - but so are your deductions.")
A7: A. PROJECTED ANNUAL TAX (on the active scenario)
B8: Line | C8: Amount | G8: Notes
B9: Gross income (draw + commission above it) | C9: =Inputs!$C$22+MAX(0,Inputs!$C$101*12-Inputs!$C$22) | G9: Greater-Of basis. If your comp is Stacked, this understates income - change the toggle.
B10: Less: business mileage deduction | C10: =-IF(Inputs!$C$20="1099",Inputs!$C$40*12*Inputs!$C$75,0) | G10: *** THE BIGGEST ONE YOU ARE PROBABLY MISSING. *** 12,000 mi/yr at the IRS rate. Note this deduction is worth MORE than the fuel actually costs you - the rate covers depreciation, insurance and wear too. You must keep a contemporaneous mileage log (a free app does it via GPS). No log, no deduction.
B11: Less: marketing / advertising | C11: =-IF(AND(Inputs!$C$20="1099",Inputs!$C$19="Self-funded"),Inputs!$C$34*12,0) | G11: Fully deductible if you pay for it. If the company reimburses it, it is theirs to deduct, not yours.
B12: Less: phone (business %) | C12: =-IF(Inputs!$C$20="1099",Inputs!$C$36*12*0.6,0) | G12: Assumes 60% business use. Adjust with your CPA.
B13: Less: other business expenses | C13: =-0 | G13: CRM, NMLS renewal, E&O, association dues, CE, client gifts (capped at $25/person), home office. Track these - they are real money.
B14: =NET SELF-EMPLOYMENT INCOME | C14: =SUM(C9:C13)
B15: Self-employment tax | C15: =-IF(Inputs!$C$20="1099",MAX(0,C14)*0.9235*Inputs!$C$71,0) | G15: 15.3% on 92.35% of net. Half of it is deductible against income tax.
B16: Federal income tax (effective) | C16: =-IF(Inputs!$C$20="1099",MAX(0,C14)*Inputs!$C$72,0) | G16: Estimate. A CPA will do better.
B17: Maine income tax (effective) | C17: =-IF(Inputs!$C$20="1099",MAX(0,C14)*Inputs!$C$73,0) | G17: Maine brackets: 5.8% / 6.75% / 7.15%.
B18: =TOTAL TAX OWED | C18: =-SUM(C15:C17)
B19: =EFFECTIVE TAX RATE ON GROSS | C19: =IFERROR(C18/C9,0) | G19: This is the number to plan around, not the top bracket.
B20: What you should be reserving per month | C20: =C18/12 | G20: Compare against the reserve rate you set on Inputs.
A22: B. QUARTERLY ESTIMATED PAYMENTS (1099 only - these are hard deadlines)
B23: Quarter | C23: Covers | D23: Due date | E23: Amount | G23: Penalty note
B24: Q1 2027 | C24: Jan 1 - Mar 31 2027 | D24: 46492 | E24: =$C$18/4 | G24: Miss these and the IRS charges an underpayment penalty even if you pay in full in April. Safe harbour: pay 100% of last year's tax (110% if your AGI tops $150k) and you cannot be penalised, however big this year turns out.
B25: Q2 2027 | C25: Apr 1 - May 31 2027 | D25: 46553 | E25: =$C$18/4
B26: Q3 2027 | C26: Jun 1 - Aug 31 2027 | D26: 46645 | E26: =$C$18/4
B27: Q4 2027 | C27: Sep 1 - Dec 31 2027 | D27: 46767 | E27: =$C$18/4
A29: C. W-2 vs 1099 — WHY THIS ONE QUESTION IS WORTH THOUSANDS
B30: If W-2 | C30: Taxes withheld automatically. Employer pays half your FICO... half your FICA (7.65%). BUT: you can deduct essentially NONE of your mileage or marketing as an employee. Simpler, safer, more expensive on the deduction side.
B31: If 1099 | C31: You pay the full 15.3% SE tax and must make quarterly payments. BUT: mileage, marketing, phone, home office and CE all come off the top, AND you may qualify for the 20% qualified business income deduction. With 12,000 miles a year, this usually wins.
B32: What to do Monday | C32: Ask the owner, in writing: (1) W-2 or 1099? (2) Is the draw recoverable? (3) If I leave with a negative balance, do you pursue repayment? Get all three in one email and keep the reply.

Sheet Retirement
A1: RETIREMENT — you are 25 with $0 invested. This is your single biggest advantage.
A2: Not because of the amount. Because of the number of years. Every year you delay costs more than the one before it.
B4: Annual contribution (Roth IRA) | C4: 7000 | D4: <- VERIFY the 2026 limit. It was $7,000 for 2025 and the IRS indexes it most years.
B5: Expected annual return | C5: 0.08 | D5: Long-run US equity average is ~10% nominal; 8% is a deliberately conservative planning number.
B6: Retirement age | C6: 65 | E6: VALUE AT 65 IF YOU START NOW: | G6: =FV(C5,C7,-C4,0,0)
B7: Years of compounding | C7: =C6-Inputs!$C$6 | E7: Of which YOUR money: | G7: =C4*C7
E8: ...and growth (tax-free in a Roth): | G8: =G6-G7
B9: If you start at age... | C9: Years to 65 | D9: You contribute | E9: Value at 65 | F9: Cost of waiting | I9: Note
B10: 25 | C10: =$C$6-B10 | D10: =$C$4*C10 | E10: =FV($C$5,C10,-$C$4,0,0) | F10: =$E$10-E10 | I10: Read the 'cost of waiting' column. Waiting ONE year - just until you feel more settled - is the most expensive year in the table, because the year you give up is the one that would have compounded the longest.
B11: 26 | C11: =$C$6-B11 | D11: =$C$4*C11 | E11: =FV($C$5,C11,-$C$4,0,0) | F11: =$E$10-E11
B12: 27 | C12: =$C$6-B12 | D12: =$C$4*C12 | E12: =FV($C$5,C12,-$C$4,0,0) | F12: =$E$10-E12
B13: 28 | C13: =$C$6-B13 | D13: =$C$4*C13 | E13: =FV($C$5,C13,-$C$4,0,0) | F13: =$E$10-E13
B14: 30 | C14: =$C$6-B14 | D14: =$C$4*C14 | E14: =FV($C$5,C14,-$C$4,0,0) | F14: =$E$10-E14
B15: 35 | C15: =$C$6-B15 | D15: =$C$4*C15 | E15: =FV($C$5,C15,-$C$4,0,0) | F15: =$E$10-E15
A17: WHICH ACCOUNT, IN WHICH ORDER
B18: 1. Employer 401(k) up to the match | C18: IF Baxter offers one. A match is a 50-100% instant return - nothing else comes close. If there is no plan, skip to step 2. Ask the owner.
B19: 2. Roth IRA - max it | C19: You are 25 in a low bracket. Pay tax now at ~12-22%, never again. Withdrawals in retirement are tax-free. This is the account for you.
B20: 3. If 1099: SEP-IRA or Solo 401(k) | C20: Self-employed plans let you shelter far more than $7,000 - a Solo 401(k) can take employee AND employer contributions. In a strong year this is how you cut a five-figure tax bill. Worth a CPA conversation once you are closing consistently.
B21: What to buy inside it | C21: A single low-cost total-market or target-date index fund. Do not stock-pick. Money you need inside 3 years (the ring) never goes in here.
B22: A Roth quirk worth knowing | C22: You can withdraw your CONTRIBUTIONS (not earnings) from a Roth at any time, tax and penalty free. It doubles as a deep backup emergency fund - which lowers the risk of maxing it early.

Sheet Goals
A1: GOAL TRACKER — four clocks running at once
A2: Ring in 2 years, house after that, emergency fund now, retirement forever. This sheet shows which ones actually fit.
B6: Goal | C6: Target $ | D6: Target date | E6: Months left | F6: Balance today | G6: Still needed | H6: Needed per month | I6: Model is funding | J6: Reality check
B7: Emergency fund (9 mo) | C7: ='Accounts'!$C$5 | D7: =Inputs!$C$7+365 | E7: =MAX(1,ROUND((D7-Inputs!$C$7)/30.44,0)) | F7: =Inputs!$C$53 | G7: =MAX(0,C7-F7) | H7: =G7/E7 | I7: ='Accounts'!J9 | J7: Fund this before anything else. It is what stops a slow month becoming credit card debt.
B8: Ring + proposal | C8: =Inputs!$C$78 | D8: =Inputs!$C$79 | E8: =MAX(1,ROUND((D8-Inputs!$C$7)/30.44,0)) | F8: =Inputs!$C$60 | G8: =MAX(0,C8-F8) | H8: =G8/E8 | I8: ='Accounts'!V9 | J8: Cash only - never invest money you need inside three years. Open a separate named account so you cannot 'borrow' from it.
B9: House down payment + closing | C9: =Inputs!$C$81*(Inputs!$C$82+Inputs!$C$83) | D9: =Inputs!$C$84 | E9: =MAX(1,ROUND((D9-Inputs!$C$7)/30.44,0)) | F9: =0 | G9: =MAX(0,C9-F9) | H9: =G9/E9 | I9: ='Accounts'!Y9 | J9: 5% down plus 3% costs on a $400k house. FHA at 3.5% down cuts this a lot - see 'Home Purchase'.
B10: Roth IRA (this year) | C10: ='Retirement'!$C$4 | D10: =DATE(YEAR(Inputs!$C$7)+1,4,15) | E10: =MAX(1,ROUND((D10-Inputs!$C$7)/30.44,0)) | F10: =Inputs!$C$61 | G10: =MAX(0,C10-F10) | H10: =G10/E10 | I10: ='Accounts'!R9 | J10: You have until tax day of the following year to fund the prior year's Roth. That is a real extra runway.
B11: Travel | C11: =Inputs!$C$80 | D11: =Inputs!$C$7+365 | E11: =MAX(1,ROUND((D11-Inputs!$C$7)/30.44,0)) | F11: =0 | G11: =MAX(0,C11-F11) | H11: =G11/E11 | I11: ='Accounts'!V9*0 | J11: Shares the special-savings account with the ring. Decide which comes first - you probably cannot do both AND the house.
B12: Auto loan payoff | C12: =0 | D12: ='Car Loan'!$E$5 | E12: =MAX(1,ROUND((D12-Inputs!$C$7)/30.44,0)) | F12: =Inputs!$C$63 | G12: =F12 | H12: =G12/E12 | I12: ='Accounts'!AA9 | J12: Only accelerate this if the APR beats your savings rate. Otherwise the money works harder in the HYSA.
B13: TOTAL REQUIRED PER MONTH | H13: =SUM(H7:H12)
B14: Surplus actually available per month (base case) | H14: =AVERAGE('Cash Flow'!P9:P20)
B15: GAP | H15: =H14-H13 | J15: If the GAP is negative, these goals do not all fit on this income. That is not a failure of budgeting - it is the model telling you to close more loans, move a date, or cut a target. Do not solve it by pretending.

Sheet Home Purchase
A1: HOME PURCHASE — what you can actually qualify for, and when
A2: You underwrite these for a living, so this is the version you would run for a client who is you.
B5: !! THE TIMING PROBLEM — read this before the numbers !!
B6: Commission income generally needs a 2-year history to be used as qualifying income - and Fannie/Freddie normally want a 2-year track record for variable income, averaged. You started 3/31/2026. That puts your first clean 2-year look at roughly APRIL 2028, and only if you have two full years of filed returns or W-2s behind it. A non-recoverable draw documented as guaranteed base salary can sometimes be counted much sooner (often 30 days of stubs), which is one more reason the recoverable/non-recoverable answer matters. Verify against current agency guidelines and your AUS findings - they change.
A10: A. QUALIFYING INCOME & DTI
B11: Input | C11: Value | H11: Notes
B12: Qualifying monthly income | C12: =Inputs!$C$23 | H12: Draw only, to start. Once you have the history, this becomes the 24-month average of draw + commission - and it is where 'Break-Even' pays off.
B13: Max back-end DTI | C13: 0.45 | H13: 45% is a common conventional ceiling; AUS approvals sometimes stretch to 50%. FHA often allows more with compensating factors.
B14: Auto payment | C14: =Inputs!$C$28 | H14: *** This one payment is eating a huge share of your borrowing power. See section C. ***
B15: Credit card minimum | C15: =MAX(25,Inputs!$C$65*0.03) | H15: Underwriting counts the minimum shown on the statement even if you pay in full.
B16: Mortgage rate | C16: 0.065 | H16: Change this to your live pricing.
B17: Term (months) | C17: 360
B18: Property tax rate | C18: 0.012 | H18: Maine mill rates vary a lot by town - Portland differs from Bangor. Use the actual town.
B19: Homeowners insurance rate | C19: 0.0035 | H19: Annual, as a % of price.
B20: PMI rate | C20: 0.005 | H20: Conventional under 20% down. Falls off at 78% LTV. FHA MIP is different and usually permanent.
B22: Max total monthly debt (income x DTI) | C22: =C12*C13
B23: Less existing debts | C23: =-(C14+C15)
B24: =MAX PITI AVAILABLE | C24: =MAX(0,C22+C23)
A26: B. MAX PURCHASE PRICE BY LOAN PROGRAM
B27: Program | C27: Down payment | D27: Max purchase price | E27: Loan amount | F27: Cash to close | H27: Notes
B28: Conventional 5% down | C28: 0.05 | D28: =IFERROR($C$24/((1-C28)*(C16/12)/(1-(1+C16/12)^-C17)+C18/12+C19/12+IF(C28<0.2,(1-C28)*C20/12*1,0)),0) | E28: =D28*(1-C28) | F28: =D28*C28+D28*Inputs!$C$83 | H28: Standard. PMI until 78% LTV.
B29: Conventional 3% down (HomeReady/Home Possible) | C29: 0.03 | D29: =IFERROR($C$24/((1-C29)*(C16/12)/(1-(1+C16/12)^-C17)+C18/12+C19/12+IF(C29<0.2,(1-C29)*C20/12*1,0)),0) | E29: =D29*(1-C29) | F29: =D29*C29+D29*Inputs!$C$83 | H29: Income limits apply. Reduced PMI. Worth checking for a first-time buyer.
B30: FHA 3.5% down | C30: 0.035 | D30: =IFERROR($C$24/((1-C30)*(C16/12)/(1-(1+C16/12)^-C17)+C18/12+C19/12+IF(C30<0.2,(1-C30)*C20/12*1,0)),0) | E30: =D30*(1-C30) | F30: =D30*C30+D30*Inputs!$C$83 | H30: Easier credit and DTI. MIP is generally for the life of the loan now - price it honestly.
B31: VA 0% down | C31: 0 | D31: =IFERROR($C$24/((1-C31)*(C16/12)/(1-(1+C16/12)^-C17)+C18/12+C19/12+IF(C31<0.2,(1-C31)*C20/12*0,0)),0) | E31: =D31*(1-C31) | F31: =D31*C31+D31*Inputs!$C$83 | H31: Only if you have eligible service. No PMI, funding fee instead.
B32: USDA 0% down | C32: 0 | D32: =IFERROR($C$24/((1-C32)*(C16/12)/(1-(1+C16/12)^-C17)+C18/12+C19/12+IF(C32<0.2,(1-C32)*C20/12*0,0)),0) | E32: =D32*(1-C32) | F32: =D32*C32+D32*Inputs!$C$83 | H32: Huge in Maine - most of the state outside Portland/Bangor cores is USDA-eligible. Income limits apply.
B33: MaineHousing First Home Loan | C33: 0.035 | D33: =IFERROR($C$24/((1-C33)*(C16/12)/(1-(1+C16/12)^-C17)+C18/12+C19/12+IF(C33<0.2,(1-C33)*C20/12*1,0)),0) | E33: =D33*(1-C33) | F33: =D33*C33+D33*Inputs!$C$83 | H33: Below-market rate + the Advantage down-payment grant. Income and price limits apply and change - check the current MaineHousing sheet. You sell these; use one.
A36: C. WHAT THE CAR IS COSTING YOU IN BUYING POWER
B37: Max price WITH the $475.69 car payment | C37: =D28 | H37: Every $100/mo of debt costs roughly $15,000-18,000 of purchase price at these rates. Your car payment alone is worth about $475.69/100 x that. Paying it off before you apply is one of the highest-leverage moves available to you - but do NOT drain the down payment to do it. Reserves matter too.
B38: Max price WITHOUT it (car paid off) | C38: =IFERROR((C12*C13-C15)/((1-C28)*(C16/12)/(1-(1+C16/12)^-C17)+C18/12+C19/12+IF(C28<0.2,(1-C28)*C20/12,0)),0)
B39: DIFFERENCE IN BUYING POWER | C39: =C38-C37

Sheet Marketing ROI
A1: MARKETING ROI — $1,000/month has to earn its keep
A2: Log spend and results monthly. At 75 bps on a $300k loan, ONE extra closing every three months already pays for the whole year.
A4: Break-even: extra loans per year needed to justify the spend | F4: =IFERROR(Inputs!$C$34*12/(Inputs!$C$94*Inputs!$C$15),0) | G4: ="...that is one closing every "&TEXT(12/MAX(0.01,F4),"0.0")&" months."
A5: Reminder: if marketing is a RECOVERABLE advance from the owner, it is not free - it is added to the balance you must earn back on 'Draw Recovery'.
A8: Month | B8: Spend | C8: Leads | D8: Apps | E8: Closings | F8: Volume | G8: Commission earned | H8: Cost per lead | I8: Cost per closing | J8: ROI (x spend) | K8: Channel notes
A9: =EOMONTH(Inputs!$C$7,0) | B9: =Inputs!$C$34 | F9: =E9*Inputs!$C$94 | G9: =F9*Inputs!$C$15 | H9: =IFERROR(B9/C9,0) | I9: =IFERROR(B9/E9,0) | J9: =IFERROR(G9/B9,0)
A10: =EOMONTH(Inputs!$C$7,1) | B10: =B9 | F10: =E10*Inputs!$C$94 | G10: =F10*Inputs!$C$15 | H10: =IFERROR(B10/C10,0) | I10: =IFERROR(B10/E10,0) | J10: =IFERROR(G10/B10,0)
A11: =EOMONTH(Inputs!$C$7,2) | B11: =B10 | F11: =E11*Inputs!$C$94 | G11: =F11*Inputs!$C$15 | H11: =IFERROR(B11/C11,0) | I11: =IFERROR(B11/E11,0) | J11: =IFERROR(G11/B11,0)
A12: =EOMONTH(Inputs!$C$7,3) | B12: =B11 | F12: =E12*Inputs!$C$94 | G12: =F12*Inputs!$C$15 | H12: =IFERROR(B12/C12,0) | I12: =IFERROR(B12/E12,0) | J12: =IFERROR(G12/B12,0)
A13: =EOMONTH(Inputs!$C$7,4) | B13: =B12 | F13: =E13*Inputs!$C$94 | G13: =F13*Inputs!$C$15 | H13: =IFERROR(B13/C13,0) | I13: =IFERROR(B13/E13,0) | J13: =IFERROR(G13/B13,0)
A14: =EOMONTH(Inputs!$C$7,5) | B14: =B13 | F14: =E14*Inputs!$C$94 | G14: =F14*Inputs!$C$15 | H14: =IFERROR(B14/C14,0) | I14: =IFERROR(B14/E14,0) | J14: =IFERROR(G14/B14,0)
A15: =EOMONTH(Inputs!$C$7,6) | B15: =B14 | F15: =E15*Inputs!$C$94 | G15: =F15*Inputs!$C$15 | H15: =IFERROR(B15/C15,0) | I15: =IFERROR(B15/E15,0) | J15: =IFERROR(G15/B15,0)
A16: =EOMONTH(Inputs!$C$7,7) | B16: =B15 | F16: =E16*Inputs!$C$94 | G16: =F16*Inputs!$C$15 | H16: =IFERROR(B16/C16,0) | I16: =IFERROR(B16/E16,0) | J16: =IFERROR(G16/B16,0)
A17: =EOMONTH(Inputs!$C$7,8) | B17: =B16 | F17: =E17*Inputs!$C$94 | G17: =F17*Inputs!$C$15 | H17: =IFERROR(B17/C17,0) | I17: =IFERROR(B17/E17,0) | J17: =IFERROR(G17/B17,0)
A18: =EOMONTH(Inputs!$C$7,9) | B18: =B17 | F18: =E18*Inputs!$C$94 | G18: =F18*Inputs!$C$15 | H18: =IFERROR(B18/C18,0) | I18: =IFERROR(B18/E18,0) | J18: =IFERROR(G18/B18,0)
A19: =EOMONTH(Inputs!$C$7,10) | B19: =B18 | F19: =E19*Inputs!$C$94 | G19: =F19*Inputs!$C$15 | H19: =IFERROR(B19/C19,0) | I19: =IFERROR(B19/E19,0) | J19: =IFERROR(G19/B19,0)
A20: =EOMONTH(Inputs!$C$7,11) | B20: =B19 | F20: =E20*Inputs!$C$94 | G20: =F20*Inputs!$C$15 | H20: =IFERROR(B20/C20,0) | I20: =IFERROR(B20/E20,0) | J20: =IFERROR(G20/B20,0)
A21: =EOMONTH(Inputs!$C$7,12) | B21: =B20 | F21: =E21*Inputs!$C$94 | G21: =F21*Inputs!$C$15 | H21: =IFERROR(B21/C21,0) | I21: =IFERROR(B21/E21,0) | J21: =IFERROR(G21/B21,0)
A22: =EOMONTH(Inputs!$C$7,13) | B22: =B21 | F22: =E22*Inputs!$C$94 | G22: =F22*Inputs!$C$15 | H22: =IFERROR(B22/C22,0) | I22: =IFERROR(B22/E22,0) | J22: =IFERROR(G22/B22,0)
A23: =EOMONTH(Inputs!$C$7,14) | B23: =B22 | F23: =E23*Inputs!$C$94 | G23: =F23*Inputs!$C$15 | H23: =IFERROR(B23/C23,0) | I23: =IFERROR(B23/E23,0) | J23: =IFERROR(G23/B23,0)
A24: =EOMONTH(Inputs!$C$7,15) | B24: =B23 | F24: =E24*Inputs!$C$94 | G24: =F24*Inputs!$C$15 | H24: =IFERROR(B24/C24,0) | I24: =IFERROR(B24/E24,0) | J24: =IFERROR(G24/B24,0)
A25: =EOMONTH(Inputs!$C$7,16) | B25: =B24 | F25: =E25*Inputs!$C$94 | G25: =F25*Inputs!$C$15 | H25: =IFERROR(B25/C25,0) | I25: =IFERROR(B25/E25,0) | J25: =IFERROR(G25/B25,0)
A26: =EOMONTH(Inputs!$C$7,17) | B26: =B25 | F26: =E26*Inputs!$C$94 | G26: =F26*Inputs!$C$15 | H26: =IFERROR(B26/C26,0) | I26: =IFERROR(B26/E26,0) | J26: =IFERROR(G26/B26,0)
A27: =EOMONTH(Inputs!$C$7,18) | B27: =B26 | F27: =E27*Inputs!$C$94 | G27: =F27*Inputs!$C$15 | H27: =IFERROR(B27/C27,0) | I27: =IFERROR(B27/E27,0) | J27: =IFERROR(G27/B27,0)
A28: =EOMONTH(Inputs!$C$7,19) | B28: =B27 | F28: =E28*Inputs!$C$94 | G28: =F28*Inputs!$C$15 | H28: =IFERROR(B28/C28,0) | I28: =IFERROR(B28/E28,0) | J28: =IFERROR(G28/B28,0)
A29: =EOMONTH(Inputs!$C$7,20) | B29: =B28 | F29: =E29*Inputs!$C$94 | G29: =F29*Inputs!$C$15 | H29: =IFERROR(B29/C29,0) | I29: =IFERROR(B29/E29,0) | J29: =IFERROR(G29/B29,0)
A30: =EOMONTH(Inputs!$C$7,21) | B30: =B29 | F30: =E30*Inputs!$C$94 | G30: =F30*Inputs!$C$15 | H30: =IFERROR(B30/C30,0) | I30: =IFERROR(B30/E30,0) | J30: =IFERROR(G30/B30,0)
A31: =EOMONTH(Inputs!$C$7,22) | B31: =B30 | F31: =E31*Inputs!$C$94 | G31: =F31*Inputs!$C$15 | H31: =IFERROR(B31/C31,0) | I31: =IFERROR(B31/E31,0) | J31: =IFERROR(G31/B31,0)
A32: =EOMONTH(Inputs!$C$7,23) | B32: =B31 | F32: =E32*Inputs!$C$94 | G32: =F32*Inputs!$C$15 | H32: =IFERROR(B32/C32,0) | I32: =IFERROR(B32/E32,0) | J32: =IFERROR(G32/B32,0)
A33: TOTALS | B33: =SUM(B9:B32) | C33: =SUM(C9:C32) | D33: =SUM(D9:D32) | E33: =SUM(E9:E32) | F33: =SUM(F9:F32) | G33: =SUM(G9:G32) | J33: =IFERROR(G33/B33,0)

Sheet Recommendations
A1: RECOMMENDATIONS — ranked by what they are actually worth to you
A2: You asked what I would suggest. Here it is, in the order I would do it.
A4: THIS WEEK — nothing else in this workbook is reliable until these are done
B5: # | C5: Do this | D5: Why it matters | E5: Worth
B6: 1 | C6: Get three answers from the owner IN WRITING | D6: One email: (a) Is the draw recoverable or non-recoverable? (b) Am I W-2 or 1099? (c) If I leave with a negative draw balance, do you pursue repayment? These three answers swing this model by tens of thousands of dollars, and a verbal answer is worth nothing if the relationship ever sours. If it is recoverable, you are carrying a $13,547.38 liability you may not know about. | E6: $13,547 at risk
B7: 2 | C7: Get checking to a $2,000 cushion before you fund anything else | D7: You have $395.40 in checking. Between now and 10/14 you owe $390.15 on the card and $475.69 on the car - $865.84 against $395.40, with one $1,231.58 draw (9/15) landing in between. That is a genuine overdraft risk in the next 30 days, and an overdraft or a late payment right now would undo months of credit work. See 'Bill Calendar'. | E7: Avoids a 30-day late
B8: 3 | C8: Correct your mental math: you get 24 draws a year, not 26 | D8: Your own dates (3/31, 4/15, 4/30, 5/15, 5/29, 6/15, 6/30, 7/16, 7/30, 8/14, 8/28) are semi-monthly - the 15th and month-end - not every 14 days. Annualized that is $29,557.92, not $32,021.08. If you have been planning on 26 checks you have been overstating your floor by $2,463 a year. | E8: $2,463/yr correction
B9: 4 | C9: Start a mileage log today | D9: 12,000 business miles a year at roughly $0.70/mi is about $8,400 of deduction - materially more than the ~$2,590 the fuel actually costs you, because the IRS rate also covers depreciation, insurance and wear. If you are 1099 this is likely your single largest deduction. It requires a contemporaneous log; a free GPS app does it automatically. No log, no deduction, and it is the first thing an auditor asks for. | E9: ~$2,000-2,500/yr in tax
A10: THIS MONTH
B11: # | C11: Do this | D11: Why it matters | E11: Worth
B12: 5 | C12: Open two accounts that do not exist yet: a Roth IRA and a named ring/travel savings account | D12: Both show $0 in this model because neither exists. The Roth is the bigger one - see item 8. The separate savings account matters for a behavioural reason: money in a named 'Ring' account does not get spent on tires. | E12: Foundational
B13: 6 | C13: Check your HYSA rate against the certificate's 3.687% | D13: Your certificate auto-pulls $1,250 out of savings every 3 months - $416.67/mo of real cash movement. If your HYSA pays more than 3.687% (many pay ~4%), that automatic roll is moving money from a better account to a worse one, and locking it up for 3 months to do it. 'Certificate Ladder' column I runs the comparison over 8 years. Fix: keep the certificate but stop the auto-add, or size it down. | E13: A few hundred/yr
B14: 7 | C14: Set the tax reserve to 30% and automate it - same day, every commission | D14: If you are 1099 nothing is withheld. The classic failure for commission earners is spending Q1 and Q2 money and meeting a five-figure bill in April. Move 30% to a separate account the day each commission lands, before you look at the balance. If you are W-2, set this to 0% on 'Inputs' and skip it. | E14: Avoids a 5-figure surprise
B15: 8 | C15: Fund the Roth IRA before you fund the ring | D15: This is the recommendation you will most want to argue with, so here are the numbers: $7,000/yr from age 25 to 65 at 8% is about $1.81 million, of which roughly $1.53M is growth you never pay tax on. Start at 26 instead and you end with about $145,000 less. One year. And a Roth lets you withdraw your CONTRIBUTIONS at any time penalty-free, so it doubles as deep backup savings - it is not as locked-up as it feels. | E15: ~$145,000 per year of delay
A16: NEXT 90 DAYS — credit, because you want a mortgage
B17: # | C17: Do this | D17: Why it matters | E17: Worth
B18: 9 | C18: Pay the statement balance in full - and make a second payment BEFORE the statement closes | D18: Direct answer to your question. Carrying a balance does NOT build credit; it just costs you 26.99%. But your issuer reports the balance on the STATEMENT CLOSING date, not the due date. So: pay it down to ~5% of your limit a few days before closing, let that small balance report, then pay the rest by the 7th. Zero interest, near-perfect utilization. | E18: 20-40 FICO points
B19: 10 | C19: Get added as an authorized user on a parent's oldest card | D19: You live at home - just ask. You inherit that card's full age and limit. With only 2 lines and a thin file, nothing else moves your score this fast or this cheaply. | E19: Fastest single win
B20: 11 | C20: Add a third and fourth line - then stop | D20: Request a limit increase on your current card now (usually a soft pull, instantly lowers utilization). Open a gas-rewards card in Q4 2026 - you spend ~$216/mo on fuel, so 3% back is ~$78/yr. Add a fourth line by mid-2027. HARD DEADLINE: no new accounts within 12 months of your mortgage application. New inquiries and a lower average account age hit you exactly when pricing matters. | E20: Thin file -> solid file
A21: THE BIG STRUCTURAL DECISIONS
B22: # | C22: Do this | D22: Why it matters | E22: Worth
B23: 12 | C23: Accept that the ring and the house cannot both happen in 2028 | D23: Ring at $12,000 by Sept 2028 plus 8% of a $400,000 house (~$32,000) is ~$44,000 of cash inside about 30 months, on top of a 9-month emergency fund, on an income whose floor is $29,558. 'Goals' does this arithmetic honestly and the GAP row will show it. My suggestion: propose first (it is the dated, non-negotiable one), keep the house fund growing in the background, and buy in 2029-2030 when your income history also supports it. | E23: Sequencing, not sacrifice
B24: 13 | C24: Your mortgage timeline is driven by income history, not by savings | D24: Variable/commission income generally needs a 2-year history to be used as qualifying income. You started 3/31/2026, so your first clean 2-year look is around April 2028 - and on the draw alone, 'Home Purchase' shows what you qualify for is not close to $400,000. This is the real constraint, and you already know it from the other side of the desk. If the draw turns out to be non-recoverable and is documented as guaranteed base salary, it may be usable much sooner - one more reason item 1 matters. Verify against current agency guidelines. | E24: Sets the whole timeline
B25: 14 | C25: Do not accelerate the car loan for its own sake - but do kill it before you apply | D25: Two different questions. As an investment: only prepay if the APR (put the real one on 'Inputs') beats your HYSA rate; at 7.49% vs 4.00% it does, modestly. As mortgage strategy: that $475.69 payment is consuming a large share of your borrowing power - 'Home Purchase' section C prices it exactly. Clearing it before you apply buys more house than the interest saved. But never drain the down payment to do it - lenders want reserves too. | E25: See 'Home Purchase' C
B26: 15 | C26: Plan for health insurance at 26 | D26: You are 25. If you are on a parent's plan you age off at 26 - roughly a year out. That is $350-500/mo appearing in a budget that is already tight, and it is currently modeled at $0. Put a real number on 'Inputs' now so no plan you build this year quietly breaks next year. | E26: $4,200-6,000/yr cliff
B27: 16 | C27: Ask whether Baxter offers a 401(k) with a match | D27: If there is a match, it outranks everything on this list including the Roth - a 50% match is a 50% instant return. If there is no plan and you are 1099, look at a SEP-IRA or Solo 401(k) instead: they shelter far more than $7,000 and become genuinely valuable in a strong year. | E27: Potentially thousands
B28: 17 | C28: Buy disability insurance before you buy the ring | D28: Unglamorous and it is the one that actually protects the plan. You are 25, your entire income depends on you physically driving Maine and closing loans, you have no employer safety net worth the name, and you are about to take on a mortgage and a spouse. Own-occupation coverage is cheapest when you are young and healthy. Roughly 1-3% of income. | E28: Protects everything else
B29: 18 | C29: Small things, because they are free | D29: Amazon Prime annual instead of monthly saves about $41/yr. Aroma Joe's at 4 visits/week is $1,248/yr - not a lecture, just make it a decision rather than a default; the model has a cell for it. And if you are 1099, open a separate business checking account: it makes the deductions in item 4 defensible instead of a reconstruction exercise every April. | E29: ~$100-1,300/yr
C31: One honest caveat: | D31: The two numbers with the largest effect on this entire model - whether the draw is recoverable, and whether you are W-2 or 1099 - are the two I had to guess at. The model currently assumes the pessimistic case for both (recoverable, 1099). Change them on 'Inputs' the moment you know, and everything re-solves.
